Workbook
Name IQ_CH: 110000
Name IQ_CQ: 5000
Name IQ_CY: 10000
Name IQ_DAILY: 500000
Name IQ_FH: 100000
Name IQ_FQ: 500
Name IQ_FY: 1000
Name IQ_LTM: 2000
Name IQ_MONTH: 15000
Name IQ_NTM: 6000
Name IQ_WEEK: 50000
Name IQ_YTD: 3000

Sheet Cover
B2: Avoided Cost Calculator - Gas
B3: 2024 ACC Gas model v1b
B4: Prepared by:
B9: Energy and Environmental Economics, Inc.
B10: 44 Montgomery Street, Suite 1500
B11: San Francisco, CA 94104
B12: Phone: 415-391-5100
B13: 45590
B26: Cell Color Coding
B27: Input
B28: Calculated Value
B29: User Input
B30: Lookup Formula
B31: Yearly Lookup Value
B32: Final Outputs
B33: Values Pasted from Calculation/Macros

Sheet User Dashboard
B2: Main Inputs
C4: User Inputs
B5: Utility | C5: SDG&E
B6: Class | C6: Total Core
B7: End Use | C7: Small Boiler (<100MMBtu/Hr)
B8: Emission Control | C8: Uncontrolled
B10: Cost Test | C10: TRC
B11: Societal Cost of Carbon (SCC) | C11: High | D11: (SCC values are only used for the SCT)
C13: Levelized Results Settings
B14: Start year | C14: 2024
B15: Levelization Period | C15: 1 | D15: (Enter 1 yr to show single year results)
B16: Last Year | C16: =C14+C15-1 -> 2024 | E16: =IF(C16>$AJ$47,_xlfn.CONCAT("Selected Levelization Period extends beyond the modelled years (",E58,"-",$AJ$47,"). Please update the Start Year and/or Levelization Period"),"")
B17: Nominal Discount Rate | C17: =INDEX('Other Inputs'!$C$18:$D$18,MATCH($C$10,'Other Inputs'!$C$16:$D$16,0)) -> 0
B18: Annualization | C18: =-PMT(C17,C15,1,0,1) -> 1
B19: Report Results in Dollar Year | C19: 2024
B20: Inflation Rate | C20: ='Other Inputs'!$C$11 -> 0.02
C22: Components to Include
B23: Market (Commodity) | C23: TRUE
B24: T&D | C24: TRUE
B25: Environment (CO2 & NOx) | C25: TRUE
B26: Upstream methane leakage | C26: TRUE
B27: Behind-the-meter methane leakage | C27: TRUE
B28: Air Quality Adder | C28: TRUE
B29: Final Air Quality Adder | C29: =IF(AND(C10="SCT",C28),TRUE(),FALSE()) -> FALSE | D29: * Included for SCT only. Does not include NOx value, which is included in Environment component
B31: Intermediate Values
C33: Active values based on user inputs | F33: Month | G33: T&D Allocation Factor
B34: NOx (lbs/therm) | C34: =INDEX(Emissions!$F$6:$F$12,MATCH(_xlfn.CONCAT($C$7,"-",$C$8),Emissions!$H$6:$H$12,0)) -> 0.0098 | F34: January | G34: =INDEX('T&D'!$C55:$K55,MATCH(_xlfn.CONCAT($C$5,"-",$C$6),'T&D'!$C$68:$K$68,0)) -> 1.8214936
B35: CO2 (tonnes/therm) | C35: =INDEX(Emissions!$G$6:$G$12,MATCH(_xlfn.CONCAT($C$7,"-",$C$8),Emissions!$H$6:$H$12,0)) -> 0.005307037 | F35: February | G35: =INDEX('T&D'!$C56:$K56,MATCH(_xlfn.CONCAT($C$5,"-",$C$6),'T&D'!$C$68:$K$68,0)) -> 1.8214936
B36: Compression | C36: =INDEX('Other Inputs'!$C5:$E5,MATCH($C$5,'Other Inputs'!$C$4:$E$4,0)) -> 0.004 | F36: March | G36: =INDEX('T&D'!$C57:$K57,MATCH(_xlfn.CONCAT($C$5,"-",$C$6),'T&D'!$C$68:$K$68,0)) -> 1.8214936
B37: Losses and Unaccounted | C37: =INDEX('Other Inputs'!$C6:$E6,MATCH($C$5,'Other Inputs'!$C$4:$E$4,0)) -> 0.01 | F37: April | G37: =INDEX('T&D'!$C58:$K58,MATCH(_xlfn.CONCAT($C$5,"-",$C$6),'T&D'!$C$68:$K$68,0)) -> 0
F38: May | G38: =INDEX('T&D'!$C59:$K59,MATCH(_xlfn.CONCAT($C$5,"-",$C$6),'T&D'!$C$68:$K$68,0)) -> 0
F39: June | G39: =INDEX('T&D'!$C60:$K60,MATCH(_xlfn.CONCAT($C$5,"-",$C$6),'T&D'!$C$68:$K$68,0)) -> 0
F40: July | G40: =INDEX('T&D'!$C61:$K61,MATCH(_xlfn.CONCAT($C$5,"-",$C$6),'T&D'!$C$68:$K$68,0)) -> 0
F41: August | G41: =INDEX('T&D'!$C62:$K62,MATCH(_xlfn.CONCAT($C$5,"-",$C$6),'T&D'!$C$68:$K$68,0)) -> 0
F42: September | G42: =INDEX('T&D'!$C63:$K63,MATCH(_xlfn.CONCAT($C$5,"-",$C$6),'T&D'!$C$68:$K$68,0)) -> 0
F43: October | G43: =INDEX('T&D'!$C64:$K64,MATCH(_xlfn.CONCAT($C$5,"-",$C$6),'T&D'!$C$68:$K$68,0)) -> 0
F44: November | G44: =INDEX('T&D'!$C65:$K65,MATCH(_xlfn.CONCAT($C$5,"-",$C$6),'T&D'!$C$68:$K$68,0)) -> 1.8214936
F45: December | G45: =INDEX('T&D'!$C66:$K66,MATCH(_xlfn.CONCAT($C$5,"-",$C$6),'T&D'!$C$68:$K$68,0)) -> 1.8214936
C47: Annual Cost by Component ($/therm) | E47: 2023 | F47: =E47+1 -> 2024 | G47: =F47+1 -> 2025 | H47: =G47+1 -> 2026 | I47: =H47+1 -> 2027 | J47: =I47+1 -> 2028 | K47: =J47+1 -> 2029 | L47: =K47+1 -> 2030 | M47: =L47+1 -> 2031 | ... AJ47: =AI47+1 -> 2054
C48: Average T&D Cost | E48: =INDEX('T&D'!$D$5:$AJ$13,MATCH(_xlfn.CONCAT($C$5,"-",$C$6),'T&D'!$AL$5:$AL$13,0),MATCH(E$47,'T&D'!$D$4:$AJ$4,0)) -> 0.27 | F48: =INDEX('T&D'!$D$5:$AJ$13,MATCH(_xlfn.CONCAT($C$5,"-",$C$6),'T&D'!$AL$5:$AL$13,0),MATCH(F$47,'T&D'!$D$4:$AJ$4,0)) -> 0.27 | G48: =INDEX('T&D'!$D$5:$AJ$13,MATCH(_xlfn.CONCAT($C$5,"-",$C$6),'T&D'!$AL$5:$AL$13,0),MATCH(G$47,'T&D'!$D$4:$AJ$4,0)) -> 0.28094472 | H48: =INDEX('T&D'!$D$5:$AJ$13,MATCH(_xlfn.CONCAT($C$5,"-",$C$6),'T&D'!$AL$5:$AL$13,0),MATCH(H$47,'T&D'!$D$4:$AJ$4,0)) -> 0.28656361 | I48: =INDEX('T&D'!$D$5:$AJ$13,MATCH(_xlfn.CONCAT($C$5,"-",$C$6),'T&D'!$AL$5:$AL$13,0),MATCH(I$47,'T&D'!$D$4:$AJ$4,0)) -> 0.29229489 | J48: =INDEX('T&D'!$D$5:$AJ$13,MATCH(_xlfn.CONCAT($C$5,"-",$C$6),'T&D'!$AL$5:$AL$13,0),MATCH(J$47,'T&D'!$D$4:$AJ$4,0)) -> 0.29814078 | K48: =INDEX('T&D'!$D$5:$AJ$13,MATCH(_xlfn.CONCAT($C$5,"-",$C$6),'T&D'!$AL$5:$AL$13,0),MATCH(K$47,'T&D'!$D$4:$AJ$4,0)) -> 0.3041036 | L48: =INDEX('T&D'!$D$5:$AJ$13,MATCH(_xlfn.CONCAT($C$5,"-",$C$6),'T&D'!$AL$5:$AL$13,0),MATCH(L$47,'T&D'!$D$4:$AJ$4,0)) -> 0.31018567 | ... AJ48: =INDEX('T&D'!$D$5:$AJ$13,MATCH(_xlfn.CONCAT($C$5,"-",$C$6),'T&D'!$AL$5:$AL$13,0),MATCH(AJ$47,'T&D'!$D$4:$AJ$4,0)) -> 0.49891419
C49: NOx Emissions Cost | E49: =INDEX(Emissions!$C32:$AL32,MATCH(E$47,Emissions!$C$16:$AL$16,0)) -> 0.1627024 | F49: =INDEX(Emissions!$C32:$AL32,MATCH(F$47,Emissions!$C$16:$AL$16,0)) -> 0.17433528 | G49: =INDEX(Emissions!$C32:$AL32,MATCH(G$47,Emissions!$C$16:$AL$16,0)) -> 0.18721723 | H49: =INDEX(Emissions!$C32:$AL32,MATCH(H$47,Emissions!$C$16:$AL$16,0)) -> 0.20009918 | I49: =INDEX(Emissions!$C32:$AL32,MATCH(I$47,Emissions!$C$16:$AL$16,0)) -> 0.21298113 | J49: =INDEX(Emissions!$C32:$AL32,MATCH(J$47,Emissions!$C$16:$AL$16,0)) -> 0.22586307 | K49: =INDEX(Emissions!$C32:$AL32,MATCH(K$47,Emissions!$C$16:$AL$16,0)) -> 0.23874502 | L49: =INDEX(Emissions!$C32:$AL32,MATCH(L$47,Emissions!$C$16:$AL$16,0)) -> 0.25162697 | ... AJ49: =INDEX(Emissions!$C32:$AL32,MATCH(AJ$47,Emissions!$C$16:$AL$16,0)) -> 0.56079377
C50: CO2 Cost | E50: =INDEX(Emissions!$C33:$AL33,MATCH(E$47,Emissions!$C$16:$AL$16,0))*$C$35 -> 0.60500222 | F50: =INDEX(Emissions!$C33:$AL33,MATCH(F$47,Emissions!$C$16:$AL$16,0))*$C$35 -> 0.60500222 | G50: =INDEX(Emissions!$C33:$AL33,MATCH(G$47,Emissions!$C$16:$AL$16,0))*$C$35 -> 0.60500222 | H50: =INDEX(Emissions!$C33:$AL33,MATCH(H$47,Emissions!$C$16:$AL$16,0))*$C$35 -> 0.60500222 | I50: =INDEX(Emissions!$C33:$AL33,MATCH(I$47,Emissions!$C$16:$AL$16,0))*$C$35 -> 0.60500222 | J50: =INDEX(Emissions!$C33:$AL33,MATCH(J$47,Emissions!$C$16:$AL$16,0))*$C$35 -> 0.60500222 | K50: =INDEX(Emissions!$C33:$AL33,MATCH(K$47,Emissions!$C$16:$AL$16,0))*$C$35 -> 0.60500222 | L50: =INDEX(Emissions!$C33:$AL33,MATCH(L$47,Emissions!$C$16:$AL$16,0))*$C$35 -> 0.60500222 | ... AJ50: =INDEX(Emissions!$C33:$AL33,MATCH(AJ$47,Emissions!$C$16:$AL$16,0))*$C$35 -> 0.60500222
C51: Upstream Methane Leakage Cost | E51: =E$50*'Methane Leakage'!$C4 -> 0.033698624 | F51: =F$50*'Methane Leakage'!$C4 -> 0.033698624 | G51: =G$50*'Methane Leakage'!$C4 -> 0.033698624 | H51: =H$50*'Methane Leakage'!$C4 -> 0.033698624 | I51: =I$50*'Methane Leakage'!$C4 -> 0.033698624 | J51: =J$50*'Methane Leakage'!$C4 -> 0.033698624 | K51: =K$50*'Methane Leakage'!$C4 -> 0.033698624 | L51: =L$50*'Methane Leakage'!$C4 -> 0.033698624 | ... AJ51: =AJ$50*'Methane Leakage'!$C4 -> 0.033698624
C52: Behind-the-Meter Methane Leakage Cost | E52: =E$50*'Methane Leakage'!$C7 -> 0.022908387 | F52: =F$50*'Methane Leakage'!$C7 -> 0.022908387 | G52: =G$50*'Methane Leakage'!$C7 -> 0.022908387 | H52: =H$50*'Methane Leakage'!$C7 -> 0.022908387 | I52: =I$50*'Methane Leakage'!$C7 -> 0.022908387 | J52: =J$50*'Methane Leakage'!$C7 -> 0.022908387 | K52: =K$50*'Methane Leakage'!$C7 -> 0.022908387 | L52: =L$50*'Methane Leakage'!$C7 -> 0.022908387 | ... AJ52: =AJ$50*'Methane Leakage'!$C7 -> 0.022908387
C53: Air Quality Adder | E53: =INDEX(Emissions!$D$31:$AL$31,MATCH(E47,Emissions!$D$30:$AL$30,0)) -> 0 | F53: =INDEX(Emissions!$D$31:$AL$31,MATCH(F47,Emissions!$D$30:$AL$30,0)) -> 0 | G53: =INDEX(Emissions!$D$31:$AL$31,MATCH(G47,Emissions!$D$30:$AL$30,0)) -> 0 | H53: =INDEX(Emissions!$D$31:$AL$31,MATCH(H47,Emissions!$D$30:$AL$30,0)) -> 0 | I53: =INDEX(Emissions!$D$31:$AL$31,MATCH(I47,Emissions!$D$30:$AL$30,0)) -> 0 | J53: =INDEX(Emissions!$D$31:$AL$31,MATCH(J47,Emissions!$D$30:$AL$30,0)) -> 0 | K53: =INDEX(Emissions!$D$31:$AL$31,MATCH(K47,Emissions!$D$30:$AL$30,0)) -> 0 | L53: =INDEX(Emissions!$D$31:$AL$31,MATCH(L47,Emissions!$D$30:$AL$30,0)) -> 0 | ... AJ53: =INDEX(Emissions!$D$31:$AL$31,MATCH(AJ47,Emissions!$D$30:$AL$30,0)) -> 0
B55: Results
C57: ="Gas Avoided Cost: " & IF(C23,B23,"") &" " &IF(C24,B24,"") & " " & IF(C25,B25,"") & " " & IF(C26,B26,"") & " " & IF(C27,B27,"") & " " & IF(C29,B29,"") & " (Nominal $/Therm)" -> Gas Avoided Cost: Market (Commodity) T&D Environment (CO2 & NOx) Upstream methane leakage Behind-the-meter methane leakage (Nominal $/Therm)
C58: Levelized | E58: =E$47 -> 2023 | F58: =F$47 -> 2024 | G58: =G$47 -> 2025 | H58: =H$47 -> 2026 | I58: =I$47 -> 2027 | J58: =J$47 -> 2028 | K58: =K$47 -> 2029 | L58: =L$47 -> 2030 | ... AJ58: =AJ$47 -> 2054
B59: January | C59: =-PMT($C$17,$C$15,NPV($C$17,OFFSET(E59,0,$C$72,1,$C$15))) * (1+$C$20)^($C$19-$C$14) -> 1.9215379 | E59: =Commodity!C36*(1+$C$36+$C$37)*$C$23+ $G34*E$48*$C$24*(1+$C$36+$C$37)+ (E$49+E$50)*$C$25+ E$51*$C$26+ E$52*$C$27+ E$53*$C$29 -> 1.9117605 | F59: =Commodity!D36*(1+$C$36+$C$37)*$C$23+ $G34*F$48*$C$24*(1+$C$36+$C$37)+ (F$49+F$50)*$C$25+ F$51*$C$26+ F$52*$C$27+ F$53*$C$29 -> 1.9215379 | G59: =Commodity!E36*(1+$C$36+$C$37)*$C$23+ $G34*G$48*$C$24*(1+$C$36+$C$37)+ (G$49+G$50)*$C$25+ G$51*$C$26+ G$52*$C$27+ G$53*$C$29 -> 1.9698948 | H59: =Commodity!F36*(1+$C$36+$C$37)*$C$23+ $G34*H$48*$C$24*(1+$C$36+$C$37)+ (H$49+H$50)*$C$25+ H$51*$C$26+ H$52*$C$27+ H$53*$C$29 -> 2.0069576 | I59: =Commodity!G36*(1+$C$36+$C$37)*$C$23+ $G34*I$48*$C$24*(1+$C$36+$C$37)+ (I$49+I$50)*$C$25+ I$51*$C$26+ I$52*$C$27+ I$53*$C$29 -> 2.0430923 | J59: =Commodity!H36*(1+$C$36+$C$37)*$C$23+ $G34*J$48*$C$24*(1+$C$36+$C$37)+ (J$49+J$50)*$C$25+ J$51*$C$26+ J$52*$C$27+ J$53*$C$29 -> 2.0794509 | K59: =Commodity!I36*(1+$C$36+$C$37)*$C$23+ $G34*K$48*$C$24*(1+$C$36+$C$37)+ (K$49+K$50)*$C$25+ K$51*$C$26+ K$52*$C$27+ K$53*$C$29 -> 2.1163491 | L59: =Commodity!J36*(1+$C$36+$C$37)*$C$23+ $G34*L$48*$C$24*(1+$C$36+$C$37)+ (L$49+L$50)*$C$25+ L$51*$C$26+ L$52*$C$27+ L$53*$C$29 -> 2.153782 | ... AJ59: =Commodity!AH36*(1+$C$36+$C$37)*$C$23+ $G34*AJ$48*$C$24*(1+$C$36+$C$37)+ (AJ$49+AJ$50)*$C$25+ AJ$51*$C$26+ AJ$52*$C$27+ AJ$53*$C$29 -> 3.25223
B60: February | C60: =-PMT($C$17,$C$15,NPV($C$17,OFFSET(E60,0,$C$72,1,$C$15))) * (1+$C$20)^($C$19-$C$14) -> 1.9088278 | E60: =Commodity!C37*(1+$C$36+$C$37)*$C$23+ $G35*E$48*$C$24*(1+$C$36+$C$37)+ (E$49+E$50)*$C$25+ E$51*$C$26+ E$52*$C$27+ E$53*$C$29 -> 1.8975096 | F60: =Commodity!D37*(1+$C$36+$C$37)*$C$23+ $G35*F$48*$C$24*(1+$C$36+$C$37)+ (F$49+F$50)*$C$25+ F$51*$C$26+ F$52*$C$27+ F$53*$C$29 -> 1.9088278 | G60: =Commodity!E37*(1+$C$36+$C$37)*$C$23+ $G35*G$48*$C$24*(1+$C$36+$C$37)+ (G$49+G$50)*$C$25+ G$51*$C$26+ G$52*$C$27+ G$53*$C$29 -> 1.9567109 | H60: =Commodity!F37*(1+$C$36+$C$37)*$C$23+ $G35*H$48*$C$24*(1+$C$36+$C$37)+ (H$49+H$50)*$C$25+ H$51*$C$26+ H$52*$C$27+ H$53*$C$29 -> 1.9934321 | I60: =Commodity!G37*(1+$C$36+$C$37)*$C$23+ $G35*I$48*$C$24*(1+$C$36+$C$37)+ (I$49+I$50)*$C$25+ I$51*$C$26+ I$52*$C$27+ I$53*$C$29 -> 2.0292814 | J60: =Commodity!H37*(1+$C$36+$C$37)*$C$23+ $G35*J$48*$C$24*(1+$C$36+$C$37)+ (J$49+J$50)*$C$25+ J$51*$C$26+ J$52*$C$27+ J$53*$C$29 -> 2.0653758 | K60: =Commodity!I37*(1+$C$36+$C$37)*$C$23+ $G35*K$48*$C$24*(1+$C$36+$C$37)+ (K$49+K$50)*$C$25+ K$51*$C$26+ K$52*$C$27+ K$53*$C$29 -> 2.101996 | L60: =Commodity!J37*(1+$C$36+$C$37)*$C$23+ $G35*L$48*$C$24*(1+$C$36+$C$37)+ (L$49+L$50)*$C$25+ L$51*$C$26+ L$52*$C$27+ L$53*$C$29 -> 2.1391295 | ... AJ60: =Commodity!AH37*(1+$C$36+$C$37)*$C$23+ $G35*AJ$48*$C$24*(1+$C$36+$C$37)+ (AJ$49+AJ$50)*$C$25+ AJ$51*$C$26+ AJ$52*$C$27+ AJ$53*$C$29 -> 3.2279463
B61: March | C61: =-PMT($C$17,$C$15,NPV($C$17,OFFSET(E61,0,$C$72,1,$C$15))) * (1+$C$20)^($C$19-$C$14) -> 1.8618901 | E61: =Commodity!C38*(1+$C$36+$C$37)*$C$23+ $G36*E$48*$C$24*(1+$C$36+$C$37)+ (E$49+E$50)*$C$25+ E$51*$C$26+ E$52*$C$27+ E$53*$C$29 -> 1.849169 | F61: =Commodity!D38*(1+$C$36+$C$37)*$C$23+ $G36*F$48*$C$24*(1+$C$36+$C$37)+ (F$49+F$50)*$C$25+ F$51*$C$26+ F$52*$C$27+ F$53*$C$29 -> 1.8618901 | G61: =Commodity!E38*(1+$C$36+$C$37)*$C$23+ $G36*G$48*$C$24*(1+$C$36+$C$37)+ (G$49+G$50)*$C$25+ G$51*$C$26+ G$52*$C$27+ G$53*$C$29 -> 1.908433 | H61: =Commodity!F38*(1+$C$36+$C$37)*$C$23+ $G36*H$48*$C$24*(1+$C$36+$C$37)+ (H$49+H$50)*$C$25+ H$51*$C$26+ H$52*$C$27+ H$53*$C$29 -> 1.9440146 | I61: =Commodity!G38*(1+$C$36+$C$37)*$C$23+ $G36*I$48*$C$24*(1+$C$36+$C$37)+ (I$49+I$50)*$C$25+ I$51*$C$26+ I$52*$C$27+ I$53*$C$29 -> 1.9788417 | J61: =Commodity!H38*(1+$C$36+$C$37)*$C$23+ $G36*J$48*$C$24*(1+$C$36+$C$37)+ (J$49+J$50)*$C$25+ J$51*$C$26+ J$52*$C$27+ J$53*$C$29 -> 2.0139307 | K61: =Commodity!I38*(1+$C$36+$C$37)*$C$23+ $G36*K$48*$C$24*(1+$C$36+$C$37)+ (K$49+K$50)*$C$25+ K$51*$C$26+ K$52*$C$27+ K$53*$C$29 -> 2.0495141 | L61: =Commodity!J38*(1+$C$36+$C$37)*$C$23+ $G36*L$48*$C$24*(1+$C$36+$C$37)+ (L$49+L$50)*$C$25+ L$51*$C$26+ L$52*$C$27+ L$53*$C$29 -> 2.0855733 | ... AJ61: =Commodity!AH38*(1+$C$36+$C$37)*$C$23+ $G36*AJ$48*$C$24*(1+$C$36+$C$37)+ (AJ$49+AJ$50)*$C$25+ AJ$51*$C$26+ AJ$52*$C$27+ AJ$53*$C$29 -> 3.1390721
B62: April | C62: =-PMT($C$17,$C$15,NPV($C$17,OFFSET(E62,0,$C$72,1,$C$15))) * (1+$C$20)^($C$19-$C$14) -> 1.3543724 | E62: =Commodity!C39*(1+$C$36+$C$37)*$C$23+ $G37*E$48*$C$24*(1+$C$36+$C$37)+ (E$49+E$50)*$C$25+ E$51*$C$26+ E$52*$C$27+ E$53*$C$29 -> 1.340316 | F62: =Commodity!D39*(1+$C$36+$C$37)*$C$23+ $G37*F$48*$C$24*(1+$C$36+$C$37)+ (F$49+F$50)*$C$25+ F$51*$C$26+ F$52*$C$27+ F$53*$C$29 -> 1.3543724 | G62: =Commodity!E39*(1+$C$36+$C$37)*$C$23+ $G37*G$48*$C$24*(1+$C$36+$C$37)+ (G$49+G$50)*$C$25+ G$51*$C$26+ G$52*$C$27+ G$53*$C$29 -> 1.3803461 | H62: =Commodity!F39*(1+$C$36+$C$37)*$C$23+ $G37*H$48*$C$24*(1+$C$36+$C$37)+ (H$49+H$50)*$C$25+ H$51*$C$26+ H$52*$C$27+ H$53*$C$29 -> 1.4053048 | I62: =Commodity!G39*(1+$C$36+$C$37)*$C$23+ $G37*I$48*$C$24*(1+$C$36+$C$37)+ (I$49+I$50)*$C$25+ I$51*$C$26+ I$52*$C$27+ I$53*$C$29 -> 1.429346 | J62: =Commodity!H39*(1+$C$36+$C$37)*$C$23+ $G37*J$48*$C$24*(1+$C$36+$C$37)+ (J$49+J$50)*$C$25+ J$51*$C$26+ J$52*$C$27+ J$53*$C$29 -> 1.453456 | K62: =Commodity!I39*(1+$C$36+$C$37)*$C$23+ $G37*K$48*$C$24*(1+$C$36+$C$37)+ (K$49+K$50)*$C$25+ K$51*$C$26+ K$52*$C$27+ K$53*$C$29 -> 1.4778337 | L62: =Commodity!J39*(1+$C$36+$C$37)*$C$23+ $G37*L$48*$C$24*(1+$C$36+$C$37)+ (L$49+L$50)*$C$25+ L$51*$C$26+ L$52*$C$27+ L$53*$C$29 -> 1.5024494 | ... AJ62: =Commodity!AH39*(1+$C$36+$C$37)*$C$23+ $G37*AJ$48*$C$24*(1+$C$36+$C$37)+ (AJ$49+AJ$50)*$C$25+ AJ$51*$C$26+ AJ$52*$C$27+ AJ$53*$C$29 -> 2.2006619
B63: May | C63: =-PMT($C$17,$C$15,NPV($C$17,OFFSET(E63,0,$C$72,1,$C$15))) * (1+$C$20)^($C$19-$C$14) -> 1.3725626 | E63: =Commodity!C40*(1+$C$36+$C$37)*$C$23+ $G38*E$48*$C$24*(1+$C$36+$C$37)+ (E$49+E$50)*$C$25+ E$51*$C$26+ E$52*$C$27+ E$53*$C$29 -> 1.3570207 | F63: =Commodity!D40*(1+$C$36+$C$37)*$C$23+ $G38*F$48*$C$24*(1+$C$36+$C$37)+ (F$49+F$50)*$C$25+ F$51*$C$26+ F$52*$C$27+ F$53*$C$29 -> 1.3725626 | G63: =Commodity!E40*(1+$C$36+$C$37)*$C$23+ $G38*G$48*$C$24*(1+$C$36+$C$37)+ (G$49+G$50)*$C$25+ G$51*$C$26+ G$52*$C$27+ G$53*$C$29 -> 1.3988619 | H63: =Commodity!F40*(1+$C$36+$C$37)*$C$23+ $G38*H$48*$C$24*(1+$C$36+$C$37)+ (H$49+H$50)*$C$25+ H$51*$C$26+ H$52*$C$27+ H$53*$C$29 -> 1.4242045 | I63: =Commodity!G40*(1+$C$36+$C$37)*$C$23+ $G38*I$48*$C$24*(1+$C$36+$C$37)+ (I$49+I$50)*$C$25+ I$51*$C$26+ I$52*$C$27+ I$53*$C$29 -> 1.4486269 | J63: =Commodity!H40*(1+$C$36+$C$37)*$C$23+ $G38*J$48*$C$24*(1+$C$36+$C$37)+ (J$49+J$50)*$C$25+ J$51*$C$26+ J$52*$C$27+ J$53*$C$29 -> 1.4731406 | K63: =Commodity!I40*(1+$C$36+$C$37)*$C$23+ $G38*K$48*$C$24*(1+$C$36+$C$37)+ (K$49+K$50)*$C$25+ K$51*$C$26+ K$52*$C$27+ K$53*$C$29 -> 1.497925 | L63: =Commodity!J40*(1+$C$36+$C$37)*$C$23+ $G38*L$48*$C$24*(1+$C$36+$C$37)+ (L$49+L$50)*$C$25+ L$51*$C$26+ L$52*$C$27+ L$53*$C$29 -> 1.5229422 | ... AJ63: =Commodity!AH40*(1+$C$36+$C$37)*$C$23+ $G38*AJ$48*$C$24*(1+$C$36+$C$37)+ (AJ$49+AJ$50)*$C$25+ AJ$51*$C$26+ AJ$52*$C$27+ AJ$53*$C$29 -> 2.2347236
B64: June | C64: =-PMT($C$17,$C$15,NPV($C$17,OFFSET(E64,0,$C$72,1,$C$15))) * (1+$C$20)^($C$19-$C$14) -> 1.3865864 | E64: =Commodity!C41*(1+$C$36+$C$37)*$C$23+ $G39*E$48*$C$24*(1+$C$36+$C$37)+ (E$49+E$50)*$C$25+ E$51*$C$26+ E$52*$C$27+ E$53*$C$29 -> 1.3695061 | F64: =Commodity!D41*(1+$C$36+$C$37)*$C$23+ $G39*F$48*$C$24*(1+$C$36+$C$37)+ (F$49+F$50)*$C$25+ F$51*$C$26+ F$52*$C$27+ F$53*$C$29 -> 1.3865864 | G64: =Commodity!E41*(1+$C$36+$C$37)*$C$23+ $G39*G$48*$C$24*(1+$C$36+$C$37)+ (G$49+G$50)*$C$25+ G$51*$C$26+ G$52*$C$27+ G$53*$C$29 -> 1.4130993 | H64: =Commodity!F41*(1+$C$36+$C$37)*$C$23+ $G39*H$48*$C$24*(1+$C$36+$C$37)+ (H$49+H$50)*$C$25+ H$51*$C$26+ H$52*$C$27+ H$53*$C$29 -> 1.4387266 | I64: =Commodity!G41*(1+$C$36+$C$37)*$C$23+ $G39*I$48*$C$24*(1+$C$36+$C$37)+ (I$49+I$50)*$C$25+ I$51*$C$26+ I$52*$C$27+ I$53*$C$29 -> 1.4634401 | J64: =Commodity!H41*(1+$C$36+$C$37)*$C$23+ $G39*J$48*$C$24*(1+$C$36+$C$37)+ (J$49+J$50)*$C$25+ J$51*$C$26+ J$52*$C$27+ J$53*$C$29 -> 1.4882677 | K64: =Commodity!I41*(1+$C$36+$C$37)*$C$23+ $G39*K$48*$C$24*(1+$C$36+$C$37)+ (K$49+K$50)*$C$25+ K$51*$C$26+ K$52*$C$27+ K$53*$C$29 -> 1.5133667 | L64: =Commodity!J41*(1+$C$36+$C$37)*$C$23+ $G39*L$48*$C$24*(1+$C$36+$C$37)+ (L$49+L$50)*$C$25+ L$51*$C$26+ L$52*$C$27+ L$53*$C$29 -> 1.5386904 | ... AJ64: =Commodity!AH41*(1+$C$36+$C$37)*$C$23+ $G39*AJ$48*$C$24*(1+$C$36+$C$37)+ (AJ$49+AJ$50)*$C$25+ AJ$51*$C$26+ AJ$52*$C$27+ AJ$53*$C$29 -> 2.2609102
B65: July | C65: =-PMT($C$17,$C$15,NPV($C$17,OFFSET(E65,0,$C$72,1,$C$15))) * (1+$C$20)^($C$19-$C$14) -> 1.3911074 | E65: =Commodity!C42*(1+$C$36+$C$37)*$C$23+ $G40*E$48*$C$24*(1+$C$36+$C$37)+ (E$49+E$50)*$C$25+ E$51*$C$26+ E$52*$C$27+ E$53*$C$29 -> 1.3725349 | F65: =Commodity!D42*(1+$C$36+$C$37)*$C$23+ $G40*F$48*$C$24*(1+$C$36+$C$37)+ (F$49+F$50)*$C$25+ F$51*$C$26+ F$52*$C$27+ F$53*$C$29 -> 1.3911074 | G65: =Commodity!E42*(1+$C$36+$C$37)*$C$23+ $G40*G$48*$C$24*(1+$C$36+$C$37)+ (G$49+G$50)*$C$25+ G$51*$C$26+ G$52*$C$27+ G$53*$C$29 -> 1.4175939 | H65: =Commodity!F42*(1+$C$36+$C$37)*$C$23+ $G40*H$48*$C$24*(1+$C$36+$C$37)+ (H$49+H$50)*$C$25+ H$51*$C$26+ H$52*$C$27+ H$53*$C$29 -> 1.4432847 | I65: =Commodity!G42*(1+$C$36+$C$37)*$C$23+ $G40*I$48*$C$24*(1+$C$36+$C$37)+ (I$49+I$50)*$C$25+ I$51*$C$26+ I$52*$C$27+ I$53*$C$29 -> 1.4680847 | J65: =Commodity!H42*(1+$C$36+$C$37)*$C$23+ $G40*J$48*$C$24*(1+$C$36+$C$37)+ (J$49+J$50)*$C$25+ J$51*$C$26+ J$52*$C$27+ J$53*$C$29 -> 1.4930203 | K65: =Commodity!I42*(1+$C$36+$C$37)*$C$23+ $G40*K$48*$C$24*(1+$C$36+$C$37)+ (K$49+K$50)*$C$25+ K$51*$C$26+ K$52*$C$27+ K$53*$C$29 -> 1.5182232 | L65: =Commodity!J42*(1+$C$36+$C$37)*$C$23+ $G40*L$48*$C$24*(1+$C$36+$C$37)+ (L$49+L$50)*$C$25+ L$51*$C$26+ L$52*$C$27+ L$53*$C$29 -> 1.5436385 | ... AJ65: =Commodity!AH42*(1+$C$36+$C$37)*$C$23+ $G40*AJ$48*$C$24*(1+$C$36+$C$37)+ (AJ$49+AJ$50)*$C$25+ AJ$51*$C$26+ AJ$52*$C$27+ AJ$53*$C$29 -> 2.2691653
B66: August | C66: =-PMT($C$17,$C$15,NPV($C$17,OFFSET(E66,0,$C$72,1,$C$15))) * (1+$C$20)^($C$19-$C$14) -> 1.3869705 | E66: =Commodity!C43*(1+$C$36+$C$37)*$C$23+ $G41*E$48*$C$24*(1+$C$36+$C$37)+ (E$49+E$50)*$C$25+ E$51*$C$26+ E$52*$C$27+ E$53*$C$29 -> 1.3670138 | F66: =Commodity!D43*(1+$C$36+$C$37)*$C$23+ $G41*F$48*$C$24*(1+$C$36+$C$37)+ (F$49+F$50)*$C$25+ F$51*$C$26+ F$52*$C$27+ F$53*$C$29 -> 1.3869705 | G66: =Commodity!E43*(1+$C$36+$C$37)*$C$23+ $G41*G$48*$C$24*(1+$C$36+$C$37)+ (G$49+G$50)*$C$25+ G$51*$C$26+ G$52*$C$27+ G$53*$C$29 -> 1.4132186 | H66: =Commodity!F43*(1+$C$36+$C$37)*$C$23+ $G41*H$48*$C$24*(1+$C$36+$C$37)+ (H$49+H$50)*$C$25+ H$51*$C$26+ H$52*$C$27+ H$53*$C$29 -> 1.4387731 | I66: =Commodity!G43*(1+$C$36+$C$37)*$C$23+ $G41*I$48*$C$24*(1+$C$36+$C$37)+ (I$49+I$50)*$C$25+ I$51*$C$26+ I$52*$C$27+ I$53*$C$29 -> 1.4634737 | J66: =Commodity!H43*(1+$C$36+$C$37)*$C$23+ $G41*J$48*$C$24*(1+$C$36+$C$37)+ (J$49+J$50)*$C$25+ J$51*$C$26+ J$52*$C$27+ J$53*$C$29 -> 1.4883294 | K66: =Commodity!I43*(1+$C$36+$C$37)*$C$23+ $G41*K$48*$C$24*(1+$C$36+$C$37)+ (K$49+K$50)*$C$25+ K$51*$C$26+ K$52*$C$27+ K$53*$C$29 -> 1.513444 | L66: =Commodity!J43*(1+$C$36+$C$37)*$C$23+ $G41*L$48*$C$24*(1+$C$36+$C$37)+ (L$49+L$50)*$C$25+ L$51*$C$26+ L$52*$C$27+ L$53*$C$29 -> 1.5387553 | ... AJ66: =Commodity!AH43*(1+$C$36+$C$37)*$C$23+ $G41*AJ$48*$C$24*(1+$C$36+$C$37)+ (AJ$49+AJ$50)*$C$25+ AJ$51*$C$26+ AJ$52*$C$27+ AJ$53*$C$29 -> 2.261096
B67: September | C67: =-PMT($C$17,$C$15,NPV($C$17,OFFSET(E67,0,$C$72,1,$C$15))) * (1+$C$20)^($C$19-$C$14) -> 1.3948746 | E67: =Commodity!C44*(1+$C$36+$C$37)*$C$23+ $G42*E$48*$C$24*(1+$C$36+$C$37)+ (E$49+E$50)*$C$25+ E$51*$C$26+ E$52*$C$27+ E$53*$C$29 -> 1.3733425 | F67: =Commodity!D44*(1+$C$36+$C$37)*$C$23+ $G42*F$48*$C$24*(1+$C$36+$C$37)+ (F$49+F$50)*$C$25+ F$51*$C$26+ F$52*$C$27+ F$53*$C$29 -> 1.3948746 | G67: =Commodity!E44*(1+$C$36+$C$37)*$C$23+ $G42*G$48*$C$24*(1+$C$36+$C$37)+ (G$49+G$50)*$C$25+ G$51*$C$26+ G$52*$C$27+ G$53*$C$29 -> 1.4211755 | H67: =Commodity!F44*(1+$C$36+$C$37)*$C$23+ $G42*H$48*$C$24*(1+$C$36+$C$37)+ (H$49+H$50)*$C$25+ H$51*$C$26+ H$52*$C$27+ H$53*$C$29 -> 1.4468703 | I67: =Commodity!G44*(1+$C$36+$C$37)*$C$23+ $G42*I$48*$C$24*(1+$C$36+$C$37)+ (I$49+I$50)*$C$25+ I$51*$C$26+ I$52*$C$27+ I$53*$C$29 -> 1.4717297 | J67: =Commodity!H44*(1+$C$36+$C$37)*$C$23+ $G42*J$48*$C$24*(1+$C$36+$C$37)+ (J$49+J$50)*$C$25+ J$51*$C$26+ J$52*$C$27+ J$53*$C$29 -> 1.4967672 | K67: =Commodity!I44*(1+$C$36+$C$37)*$C$23+ $G42*K$48*$C$24*(1+$C$36+$C$37)+ (K$49+K$50)*$C$25+ K$51*$C$26+ K$52*$C$27+ K$53*$C$29 -> 1.5220608 | L67: =Commodity!J44*(1+$C$36+$C$37)*$C$23+ $G42*L$48*$C$24*(1+$C$36+$C$37)+ (L$49+L$50)*$C$25+ L$51*$C$26+ L$52*$C$27+ L$53*$C$29 -> 1.5475398 | ... AJ67: =Commodity!AH44*(1+$C$36+$C$37)*$C$23+ $G42*AJ$48*$C$24*(1+$C$36+$C$37)+ (AJ$49+AJ$50)*$C$25+ AJ$51*$C$26+ AJ$52*$C$27+ AJ$53*$C$29 -> 2.2757224
B68: October | C68: =-PMT($C$17,$C$15,NPV($C$17,OFFSET(E68,0,$C$72,1,$C$15))) * (1+$C$20)^($C$19-$C$14) -> 1.3918063 | E68: =Commodity!C45*(1+$C$36+$C$37)*$C$23+ $G43*E$48*$C$24*(1+$C$36+$C$37)+ (E$49+E$50)*$C$25+ E$51*$C$26+ E$52*$C$27+ E$53*$C$29 -> 1.3688814 | F68: =Commodity!D45*(1+$C$36+$C$37)*$C$23+ $G43*F$48*$C$24*(1+$C$36+$C$37)+ (F$49+F$50)*$C$25+ F$51*$C$26+ F$52*$C$27+ F$53*$C$29 -> 1.3918063 | G68: =Commodity!E45*(1+$C$36+$C$37)*$C$23+ $G43*G$48*$C$24*(1+$C$36+$C$37)+ (G$49+G$50)*$C$25+ G$51*$C$26+ G$52*$C$27+ G$53*$C$29 -> 1.4178953 | H68: =Commodity!F45*(1+$C$36+$C$37)*$C$23+ $G43*H$48*$C$24*(1+$C$36+$C$37)+ (H$49+H$50)*$C$25+ H$51*$C$26+ H$52*$C$27+ H$53*$C$29 -> 1.4434786 | I68: =Commodity!G45*(1+$C$36+$C$37)*$C$23+ $G43*I$48*$C$24*(1+$C$36+$C$37)+ (I$49+I$50)*$C$25+ I$51*$C$26+ I$52*$C$27+ I$53*$C$29 -> 1.4682616 | J68: =Commodity!H45*(1+$C$36+$C$37)*$C$23+ $G43*J$48*$C$24*(1+$C$36+$C$37)+ (J$49+J$50)*$C$25+ J$51*$C$26+ J$52*$C$27+ J$53*$C$29 -> 1.4932424 | K68: =Commodity!I45*(1+$C$36+$C$37)*$C$23+ $G43*K$48*$C$24*(1+$C$36+$C$37)+ (K$49+K$50)*$C$25+ K$51*$C$26+ K$52*$C$27+ K$53*$C$29 -> 1.5184714 | L68: =Commodity!J45*(1+$C$36+$C$37)*$C$23+ $G43*L$48*$C$24*(1+$C$36+$C$37)+ (L$49+L$50)*$C$25+ L$51*$C$26+ L$52*$C$27+ L$53*$C$29 -> 1.5438706 | ... AJ68: =Commodity!AH45*(1+$C$36+$C$37)*$C$23+ $G43*AJ$48*$C$24*(1+$C$36+$C$37)+ (AJ$49+AJ$50)*$C$25+ AJ$51*$C$26+ AJ$52*$C$27+ AJ$53*$C$29 -> 2.2696689
B69: November | C69: =-PMT($C$17,$C$15,NPV($C$17,OFFSET(E69,0,$C$72,1,$C$15))) * (1+$C$20)^($C$19-$C$14) -> 1.9181295 | E69: =Commodity!C46*(1+$C$36+$C$37)*$C$23+ $G44*E$48*$C$24*(1+$C$36+$C$37)+ (E$49+E$50)*$C$25+ E$51*$C$26+ E$52*$C$27+ E$53*$C$29 -> 1.8931247 | F69: =Commodity!D46*(1+$C$36+$C$37)*$C$23+ $G44*F$48*$C$24*(1+$C$36+$C$37)+ (F$49+F$50)*$C$25+ F$51*$C$26+ F$52*$C$27+ F$53*$C$29 -> 1.9181295 | G69: =Commodity!E46*(1+$C$36+$C$37)*$C$23+ $G44*G$48*$C$24*(1+$C$36+$C$37)+ (G$49+G$50)*$C$25+ G$51*$C$26+ G$52*$C$27+ G$53*$C$29 -> 1.9649449 | H69: =Commodity!F46*(1+$C$36+$C$37)*$C$23+ $G44*H$48*$C$24*(1+$C$36+$C$37)+ (H$49+H$50)*$C$25+ H$51*$C$26+ H$52*$C$27+ H$53*$C$29 -> 2.0014945 | I69: =Commodity!G46*(1+$C$36+$C$37)*$C$23+ $G44*I$48*$C$24*(1+$C$36+$C$37)+ (I$49+I$50)*$C$25+ I$51*$C$26+ I$52*$C$27+ I$53*$C$29 -> 2.0374436 | J69: =Commodity!H46*(1+$C$36+$C$37)*$C$23+ $G44*J$48*$C$24*(1+$C$36+$C$37)+ (J$49+J$50)*$C$25+ J$51*$C$26+ J$52*$C$27+ J$53*$C$29 -> 2.0738338 | K69: =Commodity!I46*(1+$C$36+$C$37)*$C$23+ $G44*K$48*$C$24*(1+$C$36+$C$37)+ (K$49+K$50)*$C$25+ K$51*$C$26+ K$52*$C$27+ K$53*$C$29 -> 2.1106936 | L69: =Commodity!J46*(1+$C$36+$C$37)*$C$23+ $G44*L$48*$C$24*(1+$C$36+$C$37)+ (L$49+L$50)*$C$25+ L$51*$C$26+ L$52*$C$27+ L$53*$C$29 -> 2.1479375 | ... AJ69: =Commodity!AH46*(1+$C$36+$C$37)*$C$23+ $G44*AJ$48*$C$24*(1+$C$36+$C$37)+ (AJ$49+AJ$50)*$C$25+ AJ$51*$C$26+ AJ$52*$C$27+ AJ$53*$C$29 -> 3.2429407
B70: December | C70: =-PMT($C$17,$C$15,NPV($C$17,OFFSET(E70,0,$C$72,1,$C$15))) * (1+$C$20)^($C$19-$C$14) -> 1.9229842 | E70: =Commodity!C47*(1+$C$36+$C$37)*$C$23+ $G45*E$48*$C$24*(1+$C$36+$C$37)+ (E$49+E$50)*$C$25+ E$51*$C$26+ E$52*$C$27+ E$53*$C$29 -> 1.8963378 | F70: =Commodity!D47*(1+$C$36+$C$37)*$C$23+ $G45*F$48*$C$24*(1+$C$36+$C$37)+ (F$49+F$50)*$C$25+ F$51*$C$26+ F$52*$C$27+ F$53*$C$29 -> 1.9229842 | G70: =Commodity!E47*(1+$C$36+$C$37)*$C$23+ $G45*G$48*$C$24*(1+$C$36+$C$37)+ (G$49+G$50)*$C$25+ G$51*$C$26+ G$52*$C$27+ G$53*$C$29 -> 1.9697677 | H70: =Commodity!F47*(1+$C$36+$C$37)*$C$23+ $G45*H$48*$C$24*(1+$C$36+$C$37)+ (H$49+H$50)*$C$25+ H$51*$C$26+ H$52*$C$27+ H$53*$C$29 -> 2.0063843 | I70: =Commodity!G47*(1+$C$36+$C$37)*$C$23+ $G45*I$48*$C$24*(1+$C$36+$C$37)+ (I$49+I$50)*$C$25+ I$51*$C$26+ I$52*$C$27+ I$53*$C$29 -> 2.042426 | J70: =Commodity!H47*(1+$C$36+$C$37)*$C$23+ $G45*J$48*$C$24*(1+$C$36+$C$37)+ (J$49+J$50)*$C$25+ J$51*$C$26+ J$52*$C$27+ J$53*$C$29 -> 2.0789325 | K70: =Commodity!I47*(1+$C$36+$C$37)*$C$23+ $G45*K$48*$C$24*(1+$C$36+$C$37)+ (K$49+K$50)*$C$25+ K$51*$C$26+ K$52*$C$27+ K$53*$C$29 -> 2.1159039 | L70: =Commodity!J47*(1+$C$36+$C$37)*$C$23+ $G45*L$48*$C$24*(1+$C$36+$C$37)+ (L$49+L$50)*$C$25+ L$51*$C$26+ L$52*$C$27+ L$53*$C$29 -> 2.1532458 | ... AJ70: =Commodity!AH47*(1+$C$36+$C$37)*$C$23+ $G45*AJ$48*$C$24*(1+$C$36+$C$37)+ (AJ$49+AJ$50)*$C$25+ AJ$51*$C$26+ AJ$52*$C$27+ AJ$53*$C$29 -> 3.2517979
B72: Offset | C72: =MATCH($C$14,$E$58:$AJ$58,0)-1 -> 1
B74: Results by Component
B76: Market | C76: Levelized | E76: =E$47 -> 2023 | F76: =F$47 -> 2024 | G76: =G$47 -> 2025 | H76: =H$47 -> 2026 | I76: =I$47 -> 2027 | J76: =J$47 -> 2028 | K76: =K$47 -> 2029 | L76: =L$47 -> 2030 | ... AJ76: =AJ$47 -> 2054
B77: January | C77: =-PMT($C$17,$C$15,NPV($C$17,OFFSET(E77,0,$C$72,1,$C$15))) * (1+$C$20)^($C$19-$C$14) -> 0.5869049 | E77: =Commodity!C36*(1+$C$36+$C$37)*$C$23 -> 0.58876032 | F77: =Commodity!D36*(1+$C$36+$C$37)*$C$23 -> 0.5869049 | G77: =Commodity!E36*(1+$C$36+$C$37)*$C$23 -> 0.60216494 | H77: =Commodity!F36*(1+$C$36+$C$37)*$C$23 -> 0.61596774 | I77: =Commodity!G36*(1+$C$36+$C$37)*$C$23 -> 0.62863484 | J77: =Commodity!H36*(1+$C$36+$C$37)*$C$23 -> 0.64131418 | K77: =Commodity!I36*(1+$C$36+$C$37)*$C$23 -> 0.65431712 | L77: =Commodity!J36*(1+$C$36+$C$37)*$C$23 -> 0.66763452 | ... AJ77: =Commodity!AH36*(1+$C$36+$C$37)*$C$23 -> 1.1083352
B78: February | C78: =-PMT($C$17,$C$15,NPV($C$17,OFFSET(E78,0,$C$72,1,$C$15))) * (1+$C$20)^($C$19-$C$14) -> 0.57419474 | E78: =Commodity!C37*(1+$C$36+$C$37)*$C$23 -> 0.57450943 | F78: =Commodity!D37*(1+$C$36+$C$37)*$C$23 -> 0.57419474 | G78: =Commodity!E37*(1+$C$36+$C$37)*$C$23 -> 0.58898105 | H78: =Commodity!F37*(1+$C$36+$C$37)*$C$23 -> 0.60244222 | I78: =Commodity!G37*(1+$C$36+$C$37)*$C$23 -> 0.61482395 | J78: =Commodity!H37*(1+$C$36+$C$37)*$C$23 -> 0.62723908 | K78: =Commodity!I37*(1+$C$36+$C$37)*$C$23 -> 0.63996409 | L78: =Commodity!J37*(1+$C$36+$C$37)*$C$23 -> 0.65298206 | ... AJ78: =Commodity!AH37*(1+$C$36+$C$37)*$C$23 -> 1.0840515
B79: March | C79: =-PMT($C$17,$C$15,NPV($C$17,OFFSET(E79,0,$C$72,1,$C$15))) * (1+$C$20)^($C$19-$C$14) -> 0.52725709 | E79: =Commodity!C38*(1+$C$36+$C$37)*$C$23 -> 0.52616883 | F79: =Commodity!D38*(1+$C$36+$C$37)*$C$23 -> 0.52725709 | G79: =Commodity!E38*(1+$C$36+$C$37)*$C$23 -> 0.54070321 | H79: =Commodity!F38*(1+$C$36+$C$37)*$C$23 -> 0.5530248 | I79: =Commodity!G38*(1+$C$36+$C$37)*$C$23 -> 0.56438425 | J79: =Commodity!H38*(1+$C$36+$C$37)*$C$23 -> 0.57579401 | K79: =Commodity!I38*(1+$C$36+$C$37)*$C$23 -> 0.58748218 | L79: =Commodity!J38*(1+$C$36+$C$37)*$C$23 -> 0.59942589 | ... AJ79: =Commodity!AH38*(1+$C$36+$C$37)*$C$23 -> 0.99517736
B80: April | C80: =-PMT($C$17,$C$15,NPV($C$17,OFFSET(E80,0,$C$72,1,$C$15))) * (1+$C$20)^($C$19-$C$14) -> 0.51842792 | E80: =Commodity!C39*(1+$C$36+$C$37)*$C$23 -> 0.51600433 | F80: =Commodity!D39*(1+$C$36+$C$37)*$C$23 -> 0.51842792 | G80: =Commodity!E39*(1+$C$36+$C$37)*$C$23 -> 0.53151965 | H80: =Commodity!F39*(1+$C$36+$C$37)*$C$23 -> 0.54359639 | I80: =Commodity!G39*(1+$C$36+$C$37)*$C$23 -> 0.55475565 | J80: =Commodity!H39*(1+$C$36+$C$37)*$C$23 -> 0.56598371 | K80: =Commodity!I39*(1+$C$36+$C$37)*$C$23 -> 0.57747945 | L80: =Commodity!J39*(1+$C$36+$C$37)*$C$23 -> 0.58921323 | ... AJ80: =Commodity!AH39*(1+$C$36+$C$37)*$C$23 -> 0.97825888
B81: May | C81: =-PMT($C$17,$C$15,NPV($C$17,OFFSET(E81,0,$C$72,1,$C$15))) * (1+$C$20)^($C$19-$C$14) -> 0.53661804 | E81: =Commodity!C40*(1+$C$36+$C$37)*$C$23 -> 0.53270904 | F81: =Commodity!D40*(1+$C$36+$C$37)*$C$23 -> 0.53661804 | G81: =Commodity!E40*(1+$C$36+$C$37)*$C$23 -> 0.55003543 | H81: =Commodity!F40*(1+$C$36+$C$37)*$C$23 -> 0.56249605 | I81: =Commodity!G40*(1+$C$36+$C$37)*$C$23 -> 0.57403656 | J81: =Commodity!H40*(1+$C$36+$C$37)*$C$23 -> 0.58566825 | K81: =Commodity!I40*(1+$C$36+$C$37)*$C$23 -> 0.59757076 | L81: =Commodity!J40*(1+$C$36+$C$37)*$C$23 -> 0.60970597 | ... AJ81: =Commodity!AH40*(1+$C$36+$C$37)*$C$23 -> 1.0123206
B82: June | C82: =-PMT($C$17,$C$15,NPV($C$17,OFFSET(E82,0,$C$72,1,$C$15))) * (1+$C$20)^($C$19-$C$14) -> 0.55064193 | E82: =Commodity!C41*(1+$C$36+$C$37)*$C$23 -> 0.54519445 | F82: =Commodity!D41*(1+$C$36+$C$37)*$C$23 -> 0.55064193 | G82: =Commodity!E41*(1+$C$36+$C$37)*$C$23 -> 0.56427284 | H82: =Commodity!F41*(1+$C$36+$C$37)*$C$23 -> 0.57701822 | I82: =Commodity!G41*(1+$C$36+$C$37)*$C$23 -> 0.58884975 | J82: =Commodity!H41*(1+$C$36+$C$37)*$C$23 -> 0.60079535 | K82: =Commodity!I41*(1+$C$36+$C$37)*$C$23 -> 0.61301243 | L82: =Commodity!J41*(1+$C$36+$C$37)*$C$23 -> 0.62545423 | ... AJ82: =Commodity!AH41*(1+$C$36+$C$37)*$C$23 -> 1.0385072
B83: July | C83: =-PMT($C$17,$C$15,NPV($C$17,OFFSET(E83,0,$C$72,1,$C$15))) * (1+$C$20)^($C$19-$C$14) -> 0.55516285 | E83: =Commodity!C42*(1+$C$36+$C$37)*$C$23 -> 0.54822322 | F83: =Commodity!D42*(1+$C$36+$C$37)*$C$23 -> 0.55516285 | G83: =Commodity!E42*(1+$C$36+$C$37)*$C$23 -> 0.56876749 | H83: =Commodity!F42*(1+$C$36+$C$37)*$C$23 -> 0.58157632 | I83: =Commodity!G42*(1+$C$36+$C$37)*$C$23 -> 0.59349434 | J83: =Commodity!H42*(1+$C$36+$C$37)*$C$23 -> 0.60554801 | K83: =Commodity!I42*(1+$C$36+$C$37)*$C$23 -> 0.61786893 | L83: =Commodity!J42*(1+$C$36+$C$37)*$C$23 -> 0.63040227 | ... AJ83: =Commodity!AH42*(1+$C$36+$C$37)*$C$23 -> 1.0467622
B84: August | C84: =-PMT($C$17,$C$15,NPV($C$17,OFFSET(E84,0,$C$72,1,$C$15))) * (1+$C$20)^($C$19-$C$14) -> 0.55102601 | E84: =Commodity!C43*(1+$C$36+$C$37)*$C$23 -> 0.54270211 | F84: =Commodity!D43*(1+$C$36+$C$37)*$C$23 -> 0.55102601 | G84: =Commodity!E43*(1+$C$36+$C$37)*$C$23 -> 0.56439217 | H84: =Commodity!F43*(1+$C$36+$C$37)*$C$23 -> 0.57706469 | I84: =Commodity!G43*(1+$C$36+$C$37)*$C$23 -> 0.58888334 | J84: =Commodity!H43*(1+$C$36+$C$37)*$C$23 -> 0.60085711 | K84: =Commodity!I43*(1+$C$36+$C$37)*$C$23 -> 0.61308972 | L84: =Commodity!J43*(1+$C$36+$C$37)*$C$23 -> 0.62551913 | ... AJ84: =Commodity!AH43*(1+$C$36+$C$37)*$C$23 -> 1.038693
B85: September | C85: =-PMT($C$17,$C$15,NPV($C$17,OFFSET(E85,0,$C$72,1,$C$15))) * (1+$C$20)^($C$19-$C$14) -> 0.5589301 | E85: =Commodity!C44*(1+$C$36+$C$37)*$C$23 -> 0.54903091 | F85: =Commodity!D44*(1+$C$36+$C$37)*$C$23 -> 0.5589301 | G85: =Commodity!E44*(1+$C$36+$C$37)*$C$23 -> 0.572349 | H85: =Commodity!F44*(1+$C$36+$C$37)*$C$23 -> 0.58516186 | I85: =Commodity!G44*(1+$C$36+$C$37)*$C$23 -> 0.59713932 | J85: =Commodity!H44*(1+$C$36+$C$37)*$C$23 -> 0.60929491 | K85: =Commodity!I44*(1+$C$36+$C$37)*$C$23 -> 0.62170654 | L85: =Commodity!J44*(1+$C$36+$C$37)*$C$23 -> 0.63430356 | ... AJ85: =Commodity!AH44*(1+$C$36+$C$37)*$C$23 -> 1.0533194
B86: October | C86: =-PMT($C$17,$C$15,NPV($C$17,OFFSET(E86,0,$C$72,1,$C$15))) * (1+$C$20)^($C$19-$C$14) -> 0.55586181 | E86: =Commodity!C45*(1+$C$36+$C$37)*$C$23 -> 0.54456974 | F86: =Commodity!D45*(1+$C$36+$C$37)*$C$23 -> 0.55586181 | G86: =Commodity!E45*(1+$C$36+$C$37)*$C$23 -> 0.56906889 | H86: =Commodity!F45*(1+$C$36+$C$37)*$C$23 -> 0.58177022 | I86: =Commodity!G45*(1+$C$36+$C$37)*$C$23 -> 0.59367128 | J86: =Commodity!H45*(1+$C$36+$C$37)*$C$23 -> 0.60577014 | K86: =Commodity!I45*(1+$C$36+$C$37)*$C$23 -> 0.61811717 | L86: =Commodity!J45*(1+$C$36+$C$37)*$C$23 -> 0.63063441 | ... AJ86: =Commodity!AH45*(1+$C$36+$C$37)*$C$23 -> 1.0472659
B87: November | C87: =-PMT($C$17,$C$15,NPV($C$17,OFFSET(E87,0,$C$72,1,$C$15))) * (1+$C$20)^($C$19-$C$14) -> 0.58349642 | E87: =Commodity!C46*(1+$C$36+$C$37)*$C$23 -> 0.57012449 | F87: =Commodity!D46*(1+$C$36+$C$37)*$C$23 -> 0.58349642 | G87: =Commodity!E46*(1+$C$36+$C$37)*$C$23 -> 0.59721511 | H87: =Commodity!F46*(1+$C$36+$C$37)*$C$23 -> 0.61050468 | I87: =Commodity!G46*(1+$C$36+$C$37)*$C$23 -> 0.62298621 | J87: =Commodity!H46*(1+$C$36+$C$37)*$C$23 -> 0.63569706 | K87: =Commodity!I46*(1+$C$36+$C$37)*$C$23 -> 0.64866163 | L87: =Commodity!J46*(1+$C$36+$C$37)*$C$23 -> 0.66179003 | ... AJ87: =Commodity!AH46*(1+$C$36+$C$37)*$C$23 -> 1.0990459
B88: December | C88: =-PMT($C$17,$C$15,NPV($C$17,OFFSET(E88,0,$C$72,1,$C$15))) * (1+$C$20)^($C$19-$C$14) -> 0.58835117 | E88: =Commodity!C47*(1+$C$36+$C$37)*$C$23 -> 0.57333759 | F88: =Commodity!D47*(1+$C$36+$C$37)*$C$23 -> 0.58835117 | G88: =Commodity!E47*(1+$C$36+$C$37)*$C$23 -> 0.6020379 | H88: =Commodity!F47*(1+$C$36+$C$37)*$C$23 -> 0.61539448 | I88: =Commodity!G47*(1+$C$36+$C$37)*$C$23 -> 0.6279686 | J88: =Commodity!H47*(1+$C$36+$C$37)*$C$23 -> 0.64079577 | K88: =Commodity!I47*(1+$C$36+$C$37)*$C$23 -> 0.65387195 | L88: =Commodity!J47*(1+$C$36+$C$37)*$C$23 -> 0.66709834 | ... AJ88: =Commodity!AH47*(1+$C$36+$C$37)*$C$23 -> 1.1079032
B90: T&D | C90: Levelized | E90: =E$47 -> 2023 | F90: =F$47 -> 2024 | G90: =G$47 -> 2025 | H90: =H$47 -> 2026 | I90: =I$47 -> 2027 | J90: =J$47 -> 2028 | K90: =K$47 -> 2029 | L90: =L$47 -> 2030 | ... AJ90: =AJ$47 -> 2054
B91: January | C91: =-PMT($C$17,$C$15,NPV($C$17,OFFSET(E91,0,$C$72,1,$C$15))) * (1+$C$20)^($C$19-$C$14) -> 0.49868852 | E91: =$G34*E$48*$C$24*(1+$C$36+$C$37) -> 0.49868852 | F91: =$G34*F$48*$C$24*(1+$C$36+$C$37) -> 0.49868852 | G91: =$G34*G$48*$C$24*(1+$C$36+$C$37) -> 0.51890336 | H91: =$G34*H$48*$C$24*(1+$C$36+$C$37) -> 0.52928143 | I91: =$G34*I$48*$C$24*(1+$C$36+$C$37) -> 0.53986706 | J91: =$G34*J$48*$C$24*(1+$C$36+$C$37) -> 0.5506644 | K91: =$G34*K$48*$C$24*(1+$C$36+$C$37) -> 0.56167769 | L91: =$G34*L$48*$C$24*(1+$C$36+$C$37) -> 0.57291124 | ... AJ91: =$G34*AJ$48*$C$24*(1+$C$36+$C$37) -> 0.92149178
B92: February | C92: =-PMT($C$17,$C$15,NPV($C$17,OFFSET(E92,0,$C$72,1,$C$15))) * (1+$C$20)^($C$19-$C$14) -> 0.49868852 | E92: =$G35*E$48*$C$24*(1+$C$36+$C$37) -> 0.49868852 | F92: =$G35*F$48*$C$24*(1+$C$36+$C$37) -> 0.49868852 | G92: =$G35*G$48*$C$24*(1+$C$36+$C$37) -> 0.51890336 | H92: =$G35*H$48*$C$24*(1+$C$36+$C$37) -> 0.52928143 | I92: =$G35*I$48*$C$24*(1+$C$36+$C$37) -> 0.53986706 | J92: =$G35*J$48*$C$24*(1+$C$36+$C$37) -> 0.5506644 | K92: =$G35*K$48*$C$24*(1+$C$36+$C$37) -> 0.56167769 | L92: =$G35*L$48*$C$24*(1+$C$36+$C$37) -> 0.57291124 | ... AJ92: =$G35*AJ$48*$C$24*(1+$C$36+$C$37) -> 0.92149178
B93: March | C93: =-PMT($C$17,$C$15,NPV($C$17,OFFSET(E93,0,$C$72,1,$C$15))) * (1+$C$20)^($C$19-$C$14) -> 0.49868852 | E93: =$G36*E$48*$C$24*(1+$C$36+$C$37) -> 0.49868852 | F93: =$G36*F$48*$C$24*(1+$C$36+$C$37) -> 0.49868852 | G93: =$G36*G$48*$C$24*(1+$C$36+$C$37) -> 0.51890336 | H93: =$G36*H$48*$C$24*(1+$C$36+$C$37) -> 0.52928143 | I93: =$G36*I$48*$C$24*(1+$C$36+$C$37) -> 0.53986706 | J93: =$G36*J$48*$C$24*(1+$C$36+$C$37) -> 0.5506644 | K93: =$G36*K$48*$C$24*(1+$C$36+$C$37) -> 0.56167769 | L93: =$G36*L$48*$C$24*(1+$C$36+$C$37) -> 0.57291124 | ... AJ93: =$G36*AJ$48*$C$24*(1+$C$36+$C$37) -> 0.92149178
B94: April | C94: =-PMT($C$17,$C$15,NPV($C$17,OFFSET(E94,0,$C$72,1,$C$15))) * (1+$C$20)^($C$19-$C$14) -> 0 | E94: =$G37*E$48*$C$24*(1+$C$36+$C$37) -> 0 | F94: =$G37*F$48*$C$24*(1+$C$36+$C$37) -> 0 | G94: =$G37*G$48*$C$24*(1+$C$36+$C$37) -> 0 | H94: =$G37*H$48*$C$24*(1+$C$36+$C$37) -> 0 | I94: =$G37*I$48*$C$24*(1+$C$36+$C$37) -> 0 | J94: =$G37*J$48*$C$24*(1+$C$36+$C$37) -> 0 | K94: =$G37*K$48*$C$24*(1+$C$36+$C$37) -> 0 | L94: =$G37*L$48*$C$24*(1+$C$36+$C$37) -> 0 | ... AJ94: =$G37*AJ$48*$C$24*(1+$C$36+$C$37) -> 0
B95: May | C95: =-PMT($C$17,$C$15,NPV($C$17,OFFSET(E95,0,$C$72,1,$C$15))) * (1+$C$20)^($C$19-$C$14) -> 0 | E95: =$G38*E$48*$C$24*(1+$C$36+$C$37) -> 0 | F95: =$G38*F$48*$C$24*(1+$C$36+$C$37) -> 0 | G95: =$G38*G$48*$C$24*(1+$C$36+$C$37) -> 0 | H95: =$G38*H$48*$C$24*(1+$C$36+$C$37) -> 0 | I95: =$G38*I$48*$C$24*(1+$C$36+$C$37) -> 0 | J95: =$G38*J$48*$C$24*(1+$C$36+$C$37) -> 0 | K95: =$G38*K$48*$C$24*(1+$C$36+$C$37) -> 0 | L95: =$G38*L$48*$C$24*(1+$C$36+$C$37) -> 0 | ... AJ95: =$G38*AJ$48*$C$24*(1+$C$36+$C$37) -> 0
B96: June | C96: =-PMT($C$17,$C$15,NPV($C$17,OFFSET(E96,0,$C$72,1,$C$15))) * (1+$C$20)^($C$19-$C$14) -> 0 | E96: =$G39*E$48*$C$24*(1+$C$36+$C$37) -> 0 | F96: =$G39*F$48*$C$24*(1+$C$36+$C$37) -> 0 | G96: =$G39*G$48*$C$24*(1+$C$36+$C$37) -> 0 | H96: =$G39*H$48*$C$24*(1+$C$36+$C$37) -> 0 | I96: =$G39*I$48*$C$24*(1+$C$36+$C$37) -> 0 | J96: =$G39*J$48*$C$24*(1+$C$36+$C$37) -> 0 | K96: =$G39*K$48*$C$24*(1+$C$36+$C$37) -> 0 | L96: =$G39*L$48*$C$24*(1+$C$36+$C$37) -> 0 | ... AJ96: =$G39*AJ$48*$C$24*(1+$C$36+$C$37) -> 0
B97: July | C97: =-PMT($C$17,$C$15,NPV($C$17,OFFSET(E97,0,$C$72,1,$C$15))) * (1+$C$20)^($C$19-$C$14) -> 0 | E97: =$G40*E$48*$C$24*(1+$C$36+$C$37) -> 0 | F97: =$G40*F$48*$C$24*(1+$C$36+$C$37) -> 0 | G97: =$G40*G$48*$C$24*(1+$C$36+$C$37) -> 0 | H97: =$G40*H$48*$C$24*(1+$C$36+$C$37) -> 0 | I97: =$G40*I$48*$C$24*(1+$C$36+$C$37) -> 0 | J97: =$G40*J$48*$C$24*(1+$C$36+$C$37) -> 0 | K97: =$G40*K$48*$C$24*(1+$C$36+$C$37) -> 0 | L97: =$G40*L$48*$C$24*(1+$C$36+$C$37) -> 0 | ... AJ97: =$G40*AJ$48*$C$24*(1+$C$36+$C$37) -> 0
B98: August | C98: =-PMT($C$17,$C$15,NPV($C$17,OFFSET(E98,0,$C$72,1,$C$15))) * (1+$C$20)^($C$19-$C$14) -> 0 | E98: =$G41*E$48*$C$24*(1+$C$36+$C$37) -> 0 | F98: =$G41*F$48*$C$24*(1+$C$36+$C$37) -> 0 | G98: =$G41*G$48*$C$24*(1+$C$36+$C$37) -> 0 | H98: =$G41*H$48*$C$24*(1+$C$36+$C$37) -> 0 | I98: =$G41*I$48*$C$24*(1+$C$36+$C$37) -> 0 | J98: =$G41*J$48*$C$24*(1+$C$36+$C$37) -> 0 | K98: =$G41*K$48*$C$24*(1+$C$36+$C$37) -> 0 | L98: =$G41*L$48*$C$24*(1+$C$36+$C$37) -> 0 | ... AJ98: =$G41*AJ$48*$C$24*(1+$C$36+$C$37) -> 0
B99: September | C99: =-PMT($C$17,$C$15,NPV($C$17,OFFSET(E99,0,$C$72,1,$C$15))) * (1+$C$20)^($C$19-$C$14) -> 0 | E99: =$G42*E$48*$C$24*(1+$C$36+$C$37) -> 0 | F99: =$G42*F$48*$C$24*(1+$C$36+$C$37) -> 0 | G99: =$G42*G$48*$C$24*(1+$C$36+$C$37) -> 0 | H99: =$G42*H$48*$C$24*(1+$C$36+$C$37) -> 0 | I99: =$G42*I$48*$C$24*(1+$C$36+$C$37) -> 0 | J99: =$G42*J$48*$C$24*(1+$C$36+$C$37) -> 0 | K99: =$G42*K$48*$C$24*(1+$C$36+$C$37) -> 0 | L99: =$G42*L$48*$C$24*(1+$C$36+$C$37) -> 0 | ... AJ99: =$G42*AJ$48*$C$24*(1+$C$36+$C$37) -> 0
B100: October | C100: =-PMT($C$17,$C$15,NPV($C$17,OFFSET(E100,0,$C$72,1,$C$15))) * (1+$C$20)^($C$19-$C$14) -> 0 | E100: =$G43*E$48*$C$24*(1+$C$36+$C$37) -> 0 | F100: =$G43*F$48*$C$24*(1+$C$36+$C$37) -> 0 | G100: =$G43*G$48*$C$24*(1+$C$36+$C$37) -> 0 | H100: =$G43*H$48*$C$24*(1+$C$36+$C$37) -> 0 | I100: =$G43*I$48*$C$24*(1+$C$36+$C$37) -> 0 | J100: =$G43*J$48*$C$24*(1+$C$36+$C$37) -> 0 | K100: =$G43*K$48*$C$24*(1+$C$36+$C$37) -> 0 | L100: =$G43*L$48*$C$24*(1+$C$36+$C$37) -> 0 | ... AJ100: =$G43*AJ$48*$C$24*(1+$C$36+$C$37) -> 0
B101: November | C101: =-PMT($C$17,$C$15,NPV($C$17,OFFSET(E101,0,$C$72,1,$C$15))) * (1+$C$20)^($C$19-$C$14) -> 0.49868852 | E101: =$G44*E$48*$C$24*(1+$C$36+$C$37) -> 0.49868852 | F101: =$G44*F$48*$C$24*(1+$C$36+$C$37) -> 0.49868852 | G101: =$G44*G$48*$C$24*(1+$C$36+$C$37) -> 0.51890336 | H101: =$G44*H$48*$C$24*(1+$C$36+$C$37) -> 0.52928143 | I101: =$G44*I$48*$C$24*(1+$C$36+$C$37) -> 0.53986706 | J101: =$G44*J$48*$C$24*(1+$C$36+$C$37) -> 0.5506644 | K101: =$G44*K$48*$C$24*(1+$C$36+$C$37) -> 0.56167769 | L101: =$G44*L$48*$C$24*(1+$C$36+$C$37) -> 0.57291124 | ... AJ101: =$G44*AJ$48*$C$24*(1+$C$36+$C$37) -> 0.92149178
B102: December | C102: =-PMT($C$17,$C$15,NPV($C$17,OFFSET(E102,0,$C$72,1,$C$15))) * (1+$C$20)^($C$19-$C$14) -> 0.49868852 | E102: =$G45*E$48*$C$24*(1+$C$36+$C$37) -> 0.49868852 | F102: =$G45*F$48*$C$24*(1+$C$36+$C$37) -> 0.49868852 | G102: =$G45*G$48*$C$24*(1+$C$36+$C$37) -> 0.51890336 | H102: =$G45*H$48*$C$24*(1+$C$36+$C$37) -> 0.52928143 | I102: =$G45*I$48*$C$24*(1+$C$36+$C$37) -> 0.53986706 | J102: =$G45*J$48*$C$24*(1+$C$36+$C$37) -> 0.5506644 | K102: =$G45*K$48*$C$24*(1+$C$36+$C$37) -> 0.56167769 | L102: =$G45*L$48*$C$24*(1+$C$36+$C$37) -> 0.57291124 | ... AJ102: =$G45*AJ$48*$C$24*(1+$C$36+$C$37) -> 0.92149178
B104: Environment | C104: Levelized | E104: =E$47 -> 2023 | F104: =F$47 -> 2024 | G104: =G$47 -> 2025 | H104: =H$47 -> 2026 | I104: =I$47 -> 2027 | J104: =J$47 -> 2028 | K104: =K$47 -> 2029 | L104: =L$47 -> 2030 | ... AJ104: =AJ$47 -> 2054
B105: January | C105: =-PMT($C$17,$C$15,NPV($C$17,OFFSET(E105,0,$C$72,1,$C$15))) * (1+$C$20)^($C$19-$C$14) -> 0.7793375 | E105: =(E$49+E$50)*$C$25 -> 0.76770463 | F105: =(F$49+F$50)*$C$25 -> 0.7793375 | G105: =(G$49+G$50)*$C$25 -> 0.79221945 | H105: =(H$49+H$50)*$C$25 -> 0.8051014 | I105: =(I$49+I$50)*$C$25 -> 0.81798335 | J105: =(J$49+J$50)*$C$25 -> 0.8308653 | K105: =(K$49+K$50)*$C$25 -> 0.84374725 | L105: =(L$49+L$50)*$C$25 -> 0.8566292 | ... AJ105: =(AJ$49+AJ$50)*$C$25 -> 1.165796
B106: February | C106: =-PMT($C$17,$C$15,NPV($C$17,OFFSET(E106,0,$C$72,1,$C$15))) * (1+$C$20)^($C$19-$C$14) -> 0.7793375 | E106: =(E$49+E$50)*$C$25 -> 0.76770463 | F106: =(F$49+F$50)*$C$25 -> 0.7793375 | G106: =(G$49+G$50)*$C$25 -> 0.79221945 | H106: =(H$49+H$50)*$C$25 -> 0.8051014 | I106: =(I$49+I$50)*$C$25 -> 0.81798335 | J106: =(J$49+J$50)*$C$25 -> 0.8308653 | K106: =(K$49+K$50)*$C$25 -> 0.84374725 | L106: =(L$49+L$50)*$C$25 -> 0.8566292 | ... AJ106: =(AJ$49+AJ$50)*$C$25 -> 1.165796
B107: March | C107: =-PMT($C$17,$C$15,NPV($C$17,OFFSET(E107,0,$C$72,1,$C$15))) * (1+$C$20)^($C$19-$C$14) -> 0.7793375 | E107: =(E$49+E$50)*$C$25 -> 0.76770463 | F107: =(F$49+F$50)*$C$25 -> 0.7793375 | G107: =(G$49+G$50)*$C$25 -> 0.79221945 | H107: =(H$49+H$50)*$C$25 -> 0.8051014 | I107: =(I$49+I$50)*$C$25 -> 0.81798335 | J107: =(J$49+J$50)*$C$25 -> 0.8308653 | K107: =(K$49+K$50)*$C$25 -> 0.84374725 | L107: =(L$49+L$50)*$C$25 -> 0.8566292 | ... AJ107: =(AJ$49+AJ$50)*$C$25 -> 1.165796
B108: April | C108: =-PMT($C$17,$C$15,NPV($C$17,OFFSET(E108,0,$C$72,1,$C$15))) * (1+$C$20)^($C$19-$C$14) -> 0.7793375 | E108: =(E$49+E$50)*$C$25 -> 0.76770463 | F108: =(F$49+F$50)*$C$25 -> 0.7793375 | G108: =(G$49+G$50)*$C$25 -> 0.79221945 | H108: =(H$49+H$50)*$C$25 -> 0.8051014 | I108: =(I$49+I$50)*$C$25 -> 0.81798335 | J108: =(J$49+J$50)*$C$25 -> 0.8308653 | K108: =(K$49+K$50)*$C$25 -> 0.84374725 | L108: =(L$49+L$50)*$C$25 -> 0.8566292 | ... AJ108: =(AJ$49+AJ$50)*$C$25 -> 1.165796
B109: May | C109: =-PMT($C$17,$C$15,NPV($C$17,OFFSET(E109,0,$C$72,1,$C$15))) * (1+$C$20)^($C$19-$C$14) -> 0.7793375 | E109: =(E$49+E$50)*$C$25 -> 0.76770463 | F109: =(F$49+F$50)*$C$25 -> 0.7793375 | G109: =(G$49+G$50)*$C$25 -> 0.79221945 | H109: =(H$49+H$50)*$C$25 -> 0.8051014 | I109: =(I$49+I$50)*$C$25 -> 0.81798335 | J109: =(J$49+J$50)*$C$25 -> 0.8308653 | K109: =(K$49+K$50)*$C$25 -> 0.84374725 | L109: =(L$49+L$50)*$C$25 -> 0.8566292 | ... AJ109: =(AJ$49+AJ$50)*$C$25 -> 1.165796
B110: June | C110: =-PMT($C$17,$C$15,NPV($C$17,OFFSET(E110,0,$C$72,1,$C$15))) * (1+$C$20)^($C$19-$C$14) -> 0.7793375 | E110: =(E$49+E$50)*$C$25 -> 0.76770463 | F110: =(F$49+F$50)*$C$25 -> 0.7793375 | G110: =(G$49+G$50)*$C$25 -> 0.79221945 | H110: =(H$49+H$50)*$C$25 -> 0.8051014 | I110: =(I$49+I$50)*$C$25 -> 0.81798335 | J110: =(J$49+J$50)*$C$25 -> 0.8308653 | K110: =(K$49+K$50)*$C$25 -> 0.84374725 | L110: =(L$49+L$50)*$C$25 -> 0.8566292 | ... AJ110: =(AJ$49+AJ$50)*$C$25 -> 1.165796
B111: July | C111: =-PMT($C$17,$C$15,NPV($C$17,OFFSET(E111,0,$C$72,1,$C$15))) * (1+$C$20)^($C$19-$C$14) -> 0.7793375 | E111: =(E$49+E$50)*$C$25 -> 0.76770463 | F111: =(F$49+F$50)*$C$25 -> 0.7793375 | G111: =(G$49+G$50)*$C$25 -> 0.79221945 | H111: =(H$49+H$50)*$C$25 -> 0.8051014 | I111: =(I$49+I$50)*$C$25 -> 0.81798335 | J111: =(J$49+J$50)*$C$25 -> 0.8308653 | K111: =(K$49+K$50)*$C$25 -> 0.84374725 | L111: =(L$49+L$50)*$C$25 -> 0.8566292 | ... AJ111: =(AJ$49+AJ$50)*$C$25 -> 1.165796
B112: August | C112: =-PMT($C$17,$C$15,NPV($C$17,OFFSET(E112,0,$C$72,1,$C$15))) * (1+$C$20)^($C$19-$C$14) -> 0.7793375 | E112: =(E$49+E$50)*$C$25 -> 0.76770463 | F112: =(F$49+F$50)*$C$25 -> 0.7793375 | G112: =(G$49+G$50)*$C$25 -> 0.79221945 | H112: =(H$49+H$50)*$C$25 -> 0.8051014 | I112: =(I$49+I$50)*$C$25 -> 0.81798335 | J112: =(J$49+J$50)*$C$25 -> 0.8308653 | K112: =(K$49+K$50)*$C$25 -> 0.84374725 | L112: =(L$49+L$50)*$C$25 -> 0.8566292 | ... AJ112: =(AJ$49+AJ$50)*$C$25 -> 1.165796
B113: September | C113: =-PMT($C$17,$C$15,NPV($C$17,OFFSET(E113,0,$C$72,1,$C$15))) * (1+$C$20)^($C$19-$C$14) -> 0.7793375 | E113: =(E$49+E$50)*$C$25 -> 0.76770463 | F113: =(F$49+F$50)*$C$25 -> 0.7793375 | G113: =(G$49+G$50)*$C$25 -> 0.79221945 | H113: =(H$49+H$50)*$C$25 -> 0.8051014 | I113: =(I$49+I$50)*$C$25 -> 0.81798335 | J113: =(J$49+J$50)*$C$25 -> 0.8308653 | K113: =(K$49+K$50)*$C$25 -> 0.84374725 | L113: =(L$49+L$50)*$C$25 -> 0.8566292 | ... AJ113: =(AJ$49+AJ$50)*$C$25 -> 1.165796
B114: October | C114: =-PMT($C$17,$C$15,NPV($C$17,OFFSET(E114,0,$C$72,1,$C$15))) * (1+$C$20)^($C$19-$C$14) -> 0.7793375 | E114: =(E$49+E$50)*$C$25 -> 0.76770463 | F114: =(F$49+F$50)*$C$25 -> 0.7793375 | G114: =(G$49+G$50)*$C$25 -> 0.79221945 | H114: =(H$49+H$50)*$C$25 -> 0.8051014 | I114: =(I$49+I$50)*$C$25 -> 0.81798335 | J114: =(J$49+J$50)*$C$25 -> 0.8308653 | K114: =(K$49+K$50)*$C$25 -> 0.84374725 | L114: =(L$49+L$50)*$C$25 -> 0.8566292 | ... AJ114: =(AJ$49+AJ$50)*$C$25 -> 1.165796
B115: November | C115: =-PMT($C$17,$C$15,NPV($C$17,OFFSET(E115,0,$C$72,1,$C$15))) * (1+$C$20)^($C$19-$C$14) -> 0.7793375 | E115: =(E$49+E$50)*$C$25 -> 0.76770463 | F115: =(F$49+F$50)*$C$25 -> 0.7793375 | G115: =(G$49+G$50)*$C$25 -> 0.79221945 | H115: =(H$49+H$50)*$C$25 -> 0.8051014 | I115: =(I$49+I$50)*$C$25 -> 0.81798335 | J115: =(J$49+J$50)*$C$25 -> 0.8308653 | K115: =(K$49+K$50)*$C$25 -> 0.84374725 | L115: =(L$49+L$50)*$C$25 -> 0.8566292 | ... AJ115: =(AJ$49+AJ$50)*$C$25 -> 1.165796
...

Sheet Output
B2: Output Summary
C4: User Inputs (Select on Dashboard)
B5: Utility | C5: ='User Dashboard'!C5 -> SDG&E
B6: Class | C6: ='User Dashboard'!C6 -> Total Core
B7: End Use | C7: ='User Dashboard'!C7 -> Small Boiler (<100MMBtu/Hr)
B8: Emission Control | C8: ='User Dashboard'!C8 -> Uncontrolled
C10: Levelized Results Settings (Select on Dashboard)
B11: Start year | C11: ='User Dashboard'!C14 -> 2024
B12: Levelization Period | C12: ='User Dashboard'!C15 -> 1
B13: Last Year | C13: ='User Dashboard'!C16 -> 2024
C15: Levelized Gas Avoided Costs | H15: Monthly Gas Avoided Costs
C16: Monthly | D16: Annual Average | H16: ='User Dashboard'!E58 -> 2023 | I16: ='User Dashboard'!F58 -> 2024 | J16: ='User Dashboard'!G58 -> 2025 | K16: ='User Dashboard'!H58 -> 2026 | L16: ='User Dashboard'!I58 -> 2027 | M16: ='User Dashboard'!J58 -> 2028 | N16: ='User Dashboard'!K58 -> 2029 | O16: ='User Dashboard'!L58 -> 2030 | ... AM16: ='User Dashboard'!AJ58 -> 2054
B17: January | C17: ='User Dashboard'!C59 -> 1.9215379 | D17: =AVERAGE($C$17:$C$28) -> 1.6009708 | G17: January | H17: ='User Dashboard'!E59 -> 1.9117605 | I17: ='User Dashboard'!F59 -> 1.9215379 | J17: ='User Dashboard'!G59 -> 1.9698948 | K17: ='User Dashboard'!H59 -> 2.0069576 | L17: ='User Dashboard'!I59 -> 2.0430923 | M17: ='User Dashboard'!J59 -> 2.0794509 | N17: ='User Dashboard'!K59 -> 2.1163491 | O17: ='User Dashboard'!L59 -> 2.153782 | ... AM17: ='User Dashboard'!AJ59 -> 3.25223
B18: February | C18: ='User Dashboard'!C60 -> 1.9088278 | D18: =AVERAGE($C$17:$C$28) -> 1.6009708 | G18: February | H18: ='User Dashboard'!E60 -> 1.8975096 | I18: ='User Dashboard'!F60 -> 1.9088278 | J18: ='User Dashboard'!G60 -> 1.9567109 | K18: ='User Dashboard'!H60 -> 1.9934321 | L18: ='User Dashboard'!I60 -> 2.0292814 | M18: ='User Dashboard'!J60 -> 2.0653758 | N18: ='User Dashboard'!K60 -> 2.101996 | O18: ='User Dashboard'!L60 -> 2.1391295 | ... AM18: ='User Dashboard'!AJ60 -> 3.2279463
B19: March | C19: ='User Dashboard'!C61 -> 1.8618901 | D19: =AVERAGE($C$17:$C$28) -> 1.6009708 | G19: March | H19: ='User Dashboard'!E61 -> 1.849169 | I19: ='User Dashboard'!F61 -> 1.8618901 | J19: ='User Dashboard'!G61 -> 1.908433 | K19: ='User Dashboard'!H61 -> 1.9440146 | L19: ='User Dashboard'!I61 -> 1.9788417 | M19: ='User Dashboard'!J61 -> 2.0139307 | N19: ='User Dashboard'!K61 -> 2.0495141 | O19: ='User Dashboard'!L61 -> 2.0855733 | ... AM19: ='User Dashboard'!AJ61 -> 3.1390721
B20: April | C20: ='User Dashboard'!C62 -> 1.3543724 | D20: =AVERAGE($C$17:$C$28) -> 1.6009708 | G20: April | H20: ='User Dashboard'!E62 -> 1.340316 | I20: ='User Dashboard'!F62 -> 1.3543724 | J20: ='User Dashboard'!G62 -> 1.3803461 | K20: ='User Dashboard'!H62 -> 1.4053048 | L20: ='User Dashboard'!I62 -> 1.429346 | M20: ='User Dashboard'!J62 -> 1.453456 | N20: ='User Dashboard'!K62 -> 1.4778337 | O20: ='User Dashboard'!L62 -> 1.5024494 | ... AM20: ='User Dashboard'!AJ62 -> 2.2006619
B21: May | C21: ='User Dashboard'!C63 -> 1.3725626 | D21: =AVERAGE($C$17:$C$28) -> 1.6009708 | G21: May | H21: ='User Dashboard'!E63 -> 1.3570207 | I21: ='User Dashboard'!F63 -> 1.3725626 | J21: ='User Dashboard'!G63 -> 1.3988619 | K21: ='User Dashboard'!H63 -> 1.4242045 | L21: ='User Dashboard'!I63 -> 1.4486269 | M21: ='User Dashboard'!J63 -> 1.4731406 | N21: ='User Dashboard'!K63 -> 1.497925 | O21: ='User Dashboard'!L63 -> 1.5229422 | ... AM21: ='User Dashboard'!AJ63 -> 2.2347236
B22: June | C22: ='User Dashboard'!C64 -> 1.3865864 | D22: =AVERAGE($C$17:$C$28) -> 1.6009708 | G22: June | H22: ='User Dashboard'!E64 -> 1.3695061 | I22: ='User Dashboard'!F64 -> 1.3865864 | J22: ='User Dashboard'!G64 -> 1.4130993 | K22: ='User Dashboard'!H64 -> 1.4387266 | L22: ='User Dashboard'!I64 -> 1.4634401 | M22: ='User Dashboard'!J64 -> 1.4882677 | N22: ='User Dashboard'!K64 -> 1.5133667 | O22: ='User Dashboard'!L64 -> 1.5386904 | ... AM22: ='User Dashboard'!AJ64 -> 2.2609102
B23: July | C23: ='User Dashboard'!C65 -> 1.3911074 | D23: =AVERAGE($C$17:$C$28) -> 1.6009708 | G23: July | H23: ='User Dashboard'!E65 -> 1.3725349 | I23: ='User Dashboard'!F65 -> 1.3911074 | J23: ='User Dashboard'!G65 -> 1.4175939 | K23: ='User Dashboard'!H65 -> 1.4432847 | L23: ='User Dashboard'!I65 -> 1.4680847 | M23: ='User Dashboard'!J65 -> 1.4930203 | N23: ='User Dashboard'!K65 -> 1.5182232 | O23: ='User Dashboard'!L65 -> 1.5436385 | ... AM23: ='User Dashboard'!AJ65 -> 2.2691653
B24: August | C24: ='User Dashboard'!C66 -> 1.3869705 | D24: =AVERAGE($C$17:$C$28) -> 1.6009708 | G24: August | H24: ='User Dashboard'!E66 -> 1.3670138 | I24: ='User Dashboard'!F66 -> 1.3869705 | J24: ='User Dashboard'!G66 -> 1.4132186 | K24: ='User Dashboard'!H66 -> 1.4387731 | L24: ='User Dashboard'!I66 -> 1.4634737 | M24: ='User Dashboard'!J66 -> 1.4883294 | N24: ='User Dashboard'!K66 -> 1.513444 | O24: ='User Dashboard'!L66 -> 1.5387553 | ... AM24: ='User Dashboard'!AJ66 -> 2.261096
B25: September | C25: ='User Dashboard'!C67 -> 1.3948746 | D25: =AVERAGE($C$17:$C$28) -> 1.6009708 | G25: September | H25: ='User Dashboard'!E67 -> 1.3733425 | I25: ='User Dashboard'!F67 -> 1.3948746 | J25: ='User Dashboard'!G67 -> 1.4211755 | K25: ='User Dashboard'!H67 -> 1.4468703 | L25: ='User Dashboard'!I67 -> 1.4717297 | M25: ='User Dashboard'!J67 -> 1.4967672 | N25: ='User Dashboard'!K67 -> 1.5220608 | O25: ='User Dashboard'!L67 -> 1.5475398 | ... AM25: ='User Dashboard'!AJ67 -> 2.2757224
B26: October | C26: ='User Dashboard'!C68 -> 1.3918063 | D26: =AVERAGE($C$17:$C$28) -> 1.6009708 | G26: October | H26: ='User Dashboard'!E68 -> 1.3688814 | I26: ='User Dashboard'!F68 -> 1.3918063 | J26: ='User Dashboard'!G68 -> 1.4178953 | K26: ='User Dashboard'!H68 -> 1.4434786 | L26: ='User Dashboard'!I68 -> 1.4682616 | M26: ='User Dashboard'!J68 -> 1.4932424 | N26: ='User Dashboard'!K68 -> 1.5184714 | O26: ='User Dashboard'!L68 -> 1.5438706 | ... AM26: ='User Dashboard'!AJ68 -> 2.2696689
B27: November | C27: ='User Dashboard'!C69 -> 1.9181295 | D27: =AVERAGE($C$17:$C$28) -> 1.6009708 | G27: November | H27: ='User Dashboard'!E69 -> 1.8931247 | I27: ='User Dashboard'!F69 -> 1.9181295 | J27: ='User Dashboard'!G69 -> 1.9649449 | K27: ='User Dashboard'!H69 -> 2.0014945 | L27: ='User Dashboard'!I69 -> 2.0374436 | M27: ='User Dashboard'!J69 -> 2.0738338 | N27: ='User Dashboard'!K69 -> 2.1106936 | O27: ='User Dashboard'!L69 -> 2.1479375 | ... AM27: ='User Dashboard'!AJ69 -> 3.2429407
B28: December | C28: ='User Dashboard'!C70 -> 1.9229842 | D28: =AVERAGE($C$17:$C$28) -> 1.6009708 | G28: December | H28: ='User Dashboard'!E70 -> 1.8963378 | I28: ='User Dashboard'!F70 -> 1.9229842 | J28: ='User Dashboard'!G70 -> 1.9697677 | K28: ='User Dashboard'!H70 -> 2.0063843 | L28: ='User Dashboard'!I70 -> 2.042426 | M28: ='User Dashboard'!J70 -> 2.0789325 | N28: ='User Dashboard'!K70 -> 2.1159039 | O28: ='User Dashboard'!L70 -> 2.1532458 | ... AM28: ='User Dashboard'!AJ70 -> 3.2517979
B51: Chart titles:
B52: =C15&": "&C5&", "&C6&", "&C7&", "&C8 -> Levelized Gas Avoided Costs: SDG&E, Total Core, Small Boiler (<100MMBtu/Hr), Uncontrolled
B53: =H15&": "&C5&", "&C6&", "&C7&", "&C8 -> Monthly Gas Avoided Costs: SDG&E, Total Core, Small Boiler (<100MMBtu/Hr), Uncontrolled

Sheet Commodity
B2: Gas Commodity Costs ($/MMBtu)
B4: CA Gas Price Forecast ($/MMBtu) ($Nominal) | C4: ='User Dashboard'!E$58 -> 2023 | D4: ='User Dashboard'!F$58 -> 2024 | E4: ='User Dashboard'!G$58 -> 2025 | F4: ='User Dashboard'!H$58 -> 2026 | G4: ='User Dashboard'!I$58 -> 2027 | H4: ='User Dashboard'!J$58 -> 2028 | I4: ='User Dashboard'!K$58 -> 2029 | J4: ='User Dashboard'!L$58 -> 2030 | ... AH4: ='User Dashboard'!AJ$58 -> 2054
B5: 36526 | C5: ='IEPR Gas Prices Nominal'!T6 -> 5.8063148 | D5: ='IEPR Gas Prices Nominal'!U6 -> 5.7880168 | E5: ='IEPR Gas Prices Nominal'!V6 -> 5.9385103 | F5: ='IEPR Gas Prices Nominal'!W6 -> 6.0746326 | G5: ='IEPR Gas Prices Nominal'!X6 -> 6.1995546 | H5: ='IEPR Gas Prices Nominal'!Y6 -> 6.3245975 | I5: ='IEPR Gas Prices Nominal'!Z6 -> 6.4528316 | J5: ='IEPR Gas Prices Nominal'!AA6 -> 6.5841668 | ... AH5: ='IEPR Gas Prices Nominal'!AY6 -> 10.930327
B6: 36557 | C6: ='IEPR Gas Prices Nominal'!T7 -> 5.6657735 | D6: ='IEPR Gas Prices Nominal'!U7 -> 5.66267 | E6: ='IEPR Gas Prices Nominal'!V7 -> 5.8084916 | F6: ='IEPR Gas Prices Nominal'!W7 -> 5.9412448 | G6: ='IEPR Gas Prices Nominal'!X7 -> 6.0633526 | H6: ='IEPR Gas Prices Nominal'!Y7 -> 6.1857897 | I6: ='IEPR Gas Prices Nominal'!Z7 -> 6.3112829 | J6: ='IEPR Gas Prices Nominal'!AA7 -> 6.4396653 | ... AH6: ='IEPR Gas Prices Nominal'!AY7 -> 10.690843
B7: 36586 | C7: ='IEPR Gas Prices Nominal'!T8 -> 5.1890417 | D7: ='IEPR Gas Prices Nominal'!U8 -> 5.1997741 | E7: ='IEPR Gas Prices Nominal'!V8 -> 5.3323788 | F7: ='IEPR Gas Prices Nominal'!W8 -> 5.4538935 | G7: ='IEPR Gas Prices Nominal'!X8 -> 5.5659196 | H7: ='IEPR Gas Prices Nominal'!Y8 -> 5.6784419 | I7: ='IEPR Gas Prices Nominal'!Z8 -> 5.7937098 | J7: ='IEPR Gas Prices Nominal'!AA8 -> 5.9114979 | ... AH7: ='IEPR Gas Prices Nominal'!AY8 -> 9.8143723
B8: 36617 | C8: ='IEPR Gas Prices Nominal'!T9 -> 5.0888001 | D8: ='IEPR Gas Prices Nominal'!U9 -> 5.1127013 | E8: ='IEPR Gas Prices Nominal'!V9 -> 5.2418111 | F8: ='IEPR Gas Prices Nominal'!W9 -> 5.3609111 | G8: ='IEPR Gas Prices Nominal'!X9 -> 5.470963 | H8: ='IEPR Gas Prices Nominal'!Y9 -> 5.5816934 | I8: ='IEPR Gas Prices Nominal'!Z9 -> 5.6950636 | J8: ='IEPR Gas Prices Nominal'!AA9 -> 5.8107813 | ... AH8: ='IEPR Gas Prices Nominal'!AY9 -> 9.6475235
B9: 36647 | C9: ='IEPR Gas Prices Nominal'!T10 -> 5.2535408 | D9: ='IEPR Gas Prices Nominal'!U10 -> 5.2920912 | E9: ='IEPR Gas Prices Nominal'!V10 -> 5.4244125 | F9: ='IEPR Gas Prices Nominal'!W10 -> 5.5472983 | G9: ='IEPR Gas Prices Nominal'!X10 -> 5.66111 | H9: ='IEPR Gas Prices Nominal'!Y10 -> 5.775821 | I9: ='IEPR Gas Prices Nominal'!Z10 -> 5.8932028 | J9: ='IEPR Gas Prices Nominal'!AA10 -> 6.0128794 | ... AH9: ='IEPR Gas Prices Nominal'!AY10 -> 9.983438
B10: 36678 | C10: ='IEPR Gas Prices Nominal'!T11 -> 5.3766711 | D10: ='IEPR Gas Prices Nominal'!U11 -> 5.4303937 | E10: ='IEPR Gas Prices Nominal'!V11 -> 5.5648209 | F10: ='IEPR Gas Prices Nominal'!W11 -> 5.690515 | G10: ='IEPR Gas Prices Nominal'!X11 -> 5.8071968 | H10: ='IEPR Gas Prices Nominal'!Y11 -> 5.9250034 | I10: ='IEPR Gas Prices Nominal'!Z11 -> 6.0454874 | J10: ='IEPR Gas Prices Nominal'!AA11 -> 6.1681877 | ... AH10: ='IEPR Gas Prices Nominal'!AY11 -> 10.241688
B11: 36708 | C11: ='IEPR Gas Prices Nominal'!T12 -> 5.4065406 | D11: ='IEPR Gas Prices Nominal'!U12 -> 5.4749788 | E11: ='IEPR Gas Prices Nominal'!V12 -> 5.6091468 | F11: ='IEPR Gas Prices Nominal'!W12 -> 5.7354667 | G11: ='IEPR Gas Prices Nominal'!X12 -> 5.8530014 | H11: ='IEPR Gas Prices Nominal'!Y12 -> 5.9718739 | I11: ='IEPR Gas Prices Nominal'!Z12 -> 6.0933819 | J11: ='IEPR Gas Prices Nominal'!AA12 -> 6.2169849 | ... AH11: ='IEPR Gas Prices Nominal'!AY12 -> 10.323099
B12: 36739 | C12: ='IEPR Gas Prices Nominal'!T13 -> 5.3520919 | D12: ='IEPR Gas Prices Nominal'!U13 -> 5.4341815 | E12: ='IEPR Gas Prices Nominal'!V13 -> 5.5659978 | F12: ='IEPR Gas Prices Nominal'!W13 -> 5.6909733 | G12: ='IEPR Gas Prices Nominal'!X13 -> 5.807528 | H12: ='IEPR Gas Prices Nominal'!Y13 -> 5.9256125 | I12: ='IEPR Gas Prices Nominal'!Z13 -> 6.0462497 | J12: ='IEPR Gas Prices Nominal'!AA13 -> 6.1688277 | ... AH12: ='IEPR Gas Prices Nominal'!AY13 -> 10.243521
B13: 36770 | C13: ='IEPR Gas Prices Nominal'!T14 -> 5.414506 | D13: ='IEPR Gas Prices Nominal'!U14 -> 5.5121311 | E13: ='IEPR Gas Prices Nominal'!V14 -> 5.6444675 | F13: ='IEPR Gas Prices Nominal'!W14 -> 5.770827 | G13: ='IEPR Gas Prices Nominal'!X14 -> 5.8889479 | H13: ='IEPR Gas Prices Nominal'!Y14 -> 6.0088255 | I13: ='IEPR Gas Prices Nominal'!Z14 -> 6.1312282 | J13: ='IEPR Gas Prices Nominal'!AA14 -> 6.2554591 | ... AH13: ='IEPR Gas Prices Nominal'!AY14 -> 10.387765
B14: 36800 | C14: ='IEPR Gas Prices Nominal'!T15 -> 5.3705103 | D14: ='IEPR Gas Prices Nominal'!U15 -> 5.4818719 | E14: ='IEPR Gas Prices Nominal'!V15 -> 5.6121192 | F14: ='IEPR Gas Prices Nominal'!W15 -> 5.7373789 | G14: ='IEPR Gas Prices Nominal'!X15 -> 5.8547463 | H14: ='IEPR Gas Prices Nominal'!Y15 -> 5.9740645 | I14: ='IEPR Gas Prices Nominal'!Z15 -> 6.0958301 | J14: ='IEPR Gas Prices Nominal'!AA15 -> 6.2192743 | ... AH14: ='IEPR Gas Prices Nominal'!AY15 -> 10.328066
B15: 36831 | C15: ='IEPR Gas Prices Nominal'!T16 -> 5.6225295 | D15: ='IEPR Gas Prices Nominal'!U16 -> 5.7544026 | E15: ='IEPR Gas Prices Nominal'!V16 -> 5.8896954 | F15: ='IEPR Gas Prices Nominal'!W16 -> 6.0207562 | G15: ='IEPR Gas Prices Nominal'!X16 -> 6.1438483 | H15: ='IEPR Gas Prices Nominal'!Y16 -> 6.2692018 | I15: ='IEPR Gas Prices Nominal'!Z16 -> 6.3970575 | J15: ='IEPR Gas Prices Nominal'!AA16 -> 6.5265289 | ... AH15: ='IEPR Gas Prices Nominal'!AY16 -> 10.838717
B16: 36861 | C16: ='IEPR Gas Prices Nominal'!T17 -> 5.6542169 | D16: ='IEPR Gas Prices Nominal'!U17 -> 5.8022798 | E16: ='IEPR Gas Prices Nominal'!V17 -> 5.9372574 | F16: ='IEPR Gas Prices Nominal'!W17 -> 6.0689791 | G16: ='IEPR Gas Prices Nominal'!X17 -> 6.1929842 | H16: ='IEPR Gas Prices Nominal'!Y17 -> 6.319485 | I16: ='IEPR Gas Prices Nominal'!Z17 -> 6.4484413 | J16: ='IEPR Gas Prices Nominal'!AA17 -> 6.5788791 | ... AH16: ='IEPR Gas Prices Nominal'!AY17 -> 10.926067
B18: CA Gas Price Forecast ($/MMBtu) ($2022) | C18: ='User Dashboard'!E$58 -> 2023 | D18: ='User Dashboard'!F$58 -> 2024 | E18: ='User Dashboard'!G$58 -> 2025 | F18: ='User Dashboard'!H$58 -> 2026 | G18: ='User Dashboard'!I$58 -> 2027 | H18: ='User Dashboard'!J$58 -> 2028 | I18: ='User Dashboard'!K$58 -> 2029 | J18: ='User Dashboard'!L$58 -> 2030 | ... AH18: ='User Dashboard'!AJ$58 -> 2054
B19: 36526 | C19: ='IEPR Gas Prices Real'!T6 -> 5.6743612 | D19: ='IEPR Gas Prices Real'!U6 -> 5.5275616 | E19: ='IEPR Gas Prices Real'!V6 -> 5.5416814 | F19: ='IEPR Gas Prices Real'!W6 -> 5.5406483 | G19: ='IEPR Gas Prices Real'!X6 -> 5.5355627 | H19: ='IEPR Gas Prices Real'!Y6 -> 5.5298933 | I19: ='IEPR Gas Prices Real'!Z6 -> 5.5256846 | J19: ='IEPR Gas Prices Real'!AA6 -> 5.5221248 | ... AH19: ='IEPR Gas Prices Real'!AY6 -> 5.4298282
B20: 36557 | C20: ='IEPR Gas Prices Real'!T7 -> 5.5370138 | D20: ='IEPR Gas Prices Real'!U7 -> 5.4078553 | E20: ='IEPR Gas Prices Real'!V7 -> 5.420351 | F20: ='IEPR Gas Prices Real'!W7 -> 5.4189859 | G20: ='IEPR Gas Prices Real'!X7 -> 5.4139484 | H20: ='IEPR Gas Prices Real'!Y7 -> 5.4085271 | I20: ='IEPR Gas Prices Real'!Z7 -> 5.4044737 | J20: ='IEPR Gas Prices Real'!AA7 -> 5.4009318 | ... AH20: ='IEPR Gas Prices Real'!AY7 -> 5.3108603
B21: 36586 | C21: ='IEPR Gas Prices Real'!T8 -> 5.0711162 | D21: ='IEPR Gas Prices Real'!U8 -> 4.9657893 | E21: ='IEPR Gas Prices Real'!V8 -> 4.9760534 | F21: ='IEPR Gas Prices Real'!W8 -> 4.9744747 | G21: ='IEPR Gas Prices Real'!X8 -> 4.969792 | H21: ='IEPR Gas Prices Real'!Y8 -> 4.9649291 | I21: ='IEPR Gas Prices Real'!Z8 -> 4.9612659 | J21: ='IEPR Gas Prices Real'!AA8 -> 4.957959 | ... AH21: ='IEPR Gas Prices Real'!AY8 -> 4.8754583
B22: 36617 | C22: ='IEPR Gas Prices Real'!T9 -> 4.9731527 | D22: ='IEPR Gas Prices Real'!U9 -> 4.8826347 | E22: ='IEPR Gas Prices Real'!V9 -> 4.8915378 | F22: ='IEPR Gas Prices Real'!W9 -> 4.8896658 | G22: ='IEPR Gas Prices Real'!X9 -> 4.8850056 | H22: ='IEPR Gas Prices Real'!Y9 -> 4.8803373 | I22: ='IEPR Gas Prices Real'!Z9 -> 4.8767932 | J22: ='IEPR Gas Prices Real'!AA9 -> 4.8734883 | ... AH22: ='IEPR Gas Prices Real'!AY9 -> 4.7925732
B23: 36647 | C23: ='IEPR Gas Prices Real'!T10 -> 5.1341495 | D23: ='IEPR Gas Prices Real'!U10 -> 5.0539521 | E23: ='IEPR Gas Prices Real'!V10 -> 5.0619372 | F23: ='IEPR Gas Prices Real'!W10 -> 5.0596689 | G23: ='IEPR Gas Prices Real'!X10 -> 5.0547872 | H23: ='IEPR Gas Prices Real'!Y10 -> 5.0500722 | I23: ='IEPR Gas Prices Real'!Z10 -> 5.0464636 | J23: ='IEPR Gas Prices Real'!AA10 -> 5.0429874 | ... AH23: ='IEPR Gas Prices Real'!AY10 -> 4.9594445
B24: 36678 | C24: ='IEPR Gas Prices Real'!T11 -> 5.2544816 | D24: ='IEPR Gas Prices Real'!U11 -> 5.1860312 | E24: ='IEPR Gas Prices Real'!V11 -> 5.1929631 | F24: ='IEPR Gas Prices Real'!W11 -> 5.1902962 | G24: ='IEPR Gas Prices Real'!X11 -> 5.1852276 | H24: ='IEPR Gas Prices Real'!Y11 -> 5.1805094 | I24: ='IEPR Gas Prices Real'!Z11 -> 5.176868 | J24: ='IEPR Gas Prices Real'!AA11 -> 5.1732441 | ... AH24: ='IEPR Gas Prices Real'!AY11 -> 5.0877347
B25: 36708 | C25: ='IEPR Gas Prices Real'!T12 -> 5.2836723 | D25: ='IEPR Gas Prices Real'!U12 -> 5.22861 | E25: ='IEPR Gas Prices Real'!V12 -> 5.234327 | F25: ='IEPR Gas Prices Real'!W12 -> 5.2312965 | G25: ='IEPR Gas Prices Real'!X12 -> 5.2261264 | H25: ='IEPR Gas Prices Real'!Y12 -> 5.2214905 | I25: ='IEPR Gas Prices Real'!Z12 -> 5.2178809 | J25: ='IEPR Gas Prices Real'!AA12 -> 5.2141702 | ... AH25: ='IEPR Gas Prices Real'!AY12 -> 5.1281771
B26: 36739 | C26: ='IEPR Gas Prices Real'!T13 -> 5.2304609 | D26: ='IEPR Gas Prices Real'!U13 -> 5.1896486 | E26: ='IEPR Gas Prices Real'!V13 -> 5.1940613 | F26: ='IEPR Gas Prices Real'!W13 -> 5.1907142 | G26: ='IEPR Gas Prices Real'!X13 -> 5.1855233 | H26: ='IEPR Gas Prices Real'!Y13 -> 5.181042 | I26: ='IEPR Gas Prices Real'!Z13 -> 5.1775207 | J26: ='IEPR Gas Prices Real'!AA13 -> 5.1737809 | ... AH26: ='IEPR Gas Prices Real'!AY13 -> 5.0886452
B27: 36770 | C27: ='IEPR Gas Prices Real'!T14 -> 5.2914566 | D27: ='IEPR Gas Prices Real'!U14 -> 5.2640905 | E27: ='IEPR Gas Prices Real'!V14 -> 5.2672874 | F27: ='IEPR Gas Prices Real'!W14 -> 5.2635485 | G27: ='IEPR Gas Prices Real'!X14 -> 5.258223 | H27: ='IEPR Gas Prices Real'!Y14 -> 5.253799 | I27: ='IEPR Gas Prices Real'!Z14 -> 5.2502895 | J27: ='IEPR Gas Prices Real'!AA14 -> 5.2464385 | ... AH27: ='IEPR Gas Prices Real'!AY14 -> 5.1603012
B28: 36800 | C28: ='IEPR Gas Prices Real'!T15 -> 5.2484607 | D28: ='IEPR Gas Prices Real'!U15 -> 5.235193 | E28: ='IEPR Gas Prices Real'!V15 -> 5.2371008 | F28: ='IEPR Gas Prices Real'!W15 -> 5.2330406 | G28: ='IEPR Gas Prices Real'!X15 -> 5.2276845 | H28: ='IEPR Gas Prices Real'!Y15 -> 5.2234058 | I28: ='IEPR Gas Prices Real'!Z15 -> 5.2199773 | J28: ='IEPR Gas Prices Real'!AA15 -> 5.2160903 | ... AH28: ='IEPR Gas Prices Real'!AY15 -> 5.1306442
B29: 36831 | C29: ='IEPR Gas Prices Real'!T16 -> 5.4947526 | D29: ='IEPR Gas Prices Real'!U16 -> 5.49546 | E29: ='IEPR Gas Prices Real'!V16 -> 5.4961285 | F29: ='IEPR Gas Prices Real'!W16 -> 5.4915079 | G29: ='IEPR Gas Prices Real'!X16 -> 5.4858227 | H29: ='IEPR Gas Prices Real'!Y16 -> 5.4814582 | I29: ='IEPR Gas Prices Real'!Z16 -> 5.4779242 | J29: ='IEPR Gas Prices Real'!AA16 -> 5.473784 | ... AH29: ='IEPR Gas Prices Real'!AY16 -> 5.384319
B30: 36861 | C30: ='IEPR Gas Prices Real'!T17 -> 5.5257199 | D30: ='IEPR Gas Prices Real'!U17 -> 5.5411828 | E30: ='IEPR Gas Prices Real'!V17 -> 5.5405123 | F30: ='IEPR Gas Prices Real'!W17 -> 5.5354918 | G30: ='IEPR Gas Prices Real'!X17 -> 5.529696 | H30: ='IEPR Gas Prices Real'!Y17 -> 5.5254232 | I30: ='IEPR Gas Prices Real'!Z17 -> 5.5219252 | J30: ='IEPR Gas Prices Real'!AA17 -> 5.51769 | ... AH30: ='IEPR Gas Prices Real'!AY17 -> 5.4277116
B33: Gas Commodity Costs ($/therm)
B35: CA Gas Price Forecast ($/therm) ($Nominal) | C35: ='User Dashboard'!E$58 -> 2023 | D35: ='User Dashboard'!F$58 -> 2024 | E35: ='User Dashboard'!G$58 -> 2025 | F35: ='User Dashboard'!H$58 -> 2026 | G35: ='User Dashboard'!I$58 -> 2027 | H35: ='User Dashboard'!J$58 -> 2028 | I35: ='User Dashboard'!K$58 -> 2029 | J35: ='User Dashboard'!L$58 -> 2030 | ... AH35: ='User Dashboard'!AJ$58 -> 2054
B36: 36526 | C36: =C5/'Other Inputs'!$C$22 -> 0.58063148 | D36: =D5/'Other Inputs'!$C$22 -> 0.57880168 | E36: =E5/'Other Inputs'!$C$22 -> 0.59385103 | F36: =F5/'Other Inputs'!$C$22 -> 0.60746326 | G36: =G5/'Other Inputs'!$C$22 -> 0.61995546 | H36: =H5/'Other Inputs'!$C$22 -> 0.63245975 | I36: =I5/'Other Inputs'!$C$22 -> 0.64528316 | J36: =J5/'Other Inputs'!$C$22 -> 0.65841668 | ... AH36: =AH5/'Other Inputs'!$C$22 -> 1.0930327
B37: 36557 | C37: =C6/'Other Inputs'!$C$22 -> 0.56657735 | D37: =D6/'Other Inputs'!$C$22 -> 0.566267 | E37: =E6/'Other Inputs'!$C$22 -> 0.58084916 | F37: =F6/'Other Inputs'!$C$22 -> 0.59412448 | G37: =G6/'Other Inputs'!$C$22 -> 0.60633526 | H37: =H6/'Other Inputs'!$C$22 -> 0.61857897 | I37: =I6/'Other Inputs'!$C$22 -> 0.63112829 | J37: =J6/'Other Inputs'!$C$22 -> 0.64396653 | ... AH37: =AH6/'Other Inputs'!$C$22 -> 1.0690843
B38: 36586 | C38: =C7/'Other Inputs'!$C$22 -> 0.51890417 | D38: =D7/'Other Inputs'!$C$22 -> 0.51997741 | E38: =E7/'Other Inputs'!$C$22 -> 0.53323788 | F38: =F7/'Other Inputs'!$C$22 -> 0.54538935 | G38: =G7/'Other Inputs'!$C$22 -> 0.55659196 | H38: =H7/'Other Inputs'!$C$22 -> 0.56784419 | I38: =I7/'Other Inputs'!$C$22 -> 0.57937098 | J38: =J7/'Other Inputs'!$C$22 -> 0.59114979 | ... AH38: =AH7/'Other Inputs'!$C$22 -> 0.98143723
B39: 36617 | C39: =C8/'Other Inputs'!$C$22 -> 0.50888001 | D39: =D8/'Other Inputs'!$C$22 -> 0.51127013 | E39: =E8/'Other Inputs'!$C$22 -> 0.52418111 | F39: =F8/'Other Inputs'!$C$22 -> 0.53609111 | G39: =G8/'Other Inputs'!$C$22 -> 0.5470963 | H39: =H8/'Other Inputs'!$C$22 -> 0.55816934 | I39: =I8/'Other Inputs'!$C$22 -> 0.56950636 | J39: =J8/'Other Inputs'!$C$22 -> 0.58107813 | ... AH39: =AH8/'Other Inputs'!$C$22 -> 0.96475235
B40: 36647 | C40: =C9/'Other Inputs'!$C$22 -> 0.52535408 | D40: =D9/'Other Inputs'!$C$22 -> 0.52920912 | E40: =E9/'Other Inputs'!$C$22 -> 0.54244125 | F40: =F9/'Other Inputs'!$C$22 -> 0.55472983 | G40: =G9/'Other Inputs'!$C$22 -> 0.566111 | H40: =H9/'Other Inputs'!$C$22 -> 0.5775821 | I40: =I9/'Other Inputs'!$C$22 -> 0.58932028 | J40: =J9/'Other Inputs'!$C$22 -> 0.60128794 | ... AH40: =AH9/'Other Inputs'!$C$22 -> 0.9983438
B41: 36678 | C41: =C10/'Other Inputs'!$C$22 -> 0.53766711 | D41: =D10/'Other Inputs'!$C$22 -> 0.54303937 | E41: =E10/'Other Inputs'!$C$22 -> 0.55648209 | F41: =F10/'Other Inputs'!$C$22 -> 0.5690515 | G41: =G10/'Other Inputs'!$C$22 -> 0.58071968 | H41: =H10/'Other Inputs'!$C$22 -> 0.59250034 | I41: =I10/'Other Inputs'!$C$22 -> 0.60454874 | J41: =J10/'Other Inputs'!$C$22 -> 0.61681877 | ... AH41: =AH10/'Other Inputs'!$C$22 -> 1.0241688
B42: 36708 | C42: =C11/'Other Inputs'!$C$22 -> 0.54065406 | D42: =D11/'Other Inputs'!$C$22 -> 0.54749788 | E42: =E11/'Other Inputs'!$C$22 -> 0.56091468 | F42: =F11/'Other Inputs'!$C$22 -> 0.57354667 | G42: =G11/'Other Inputs'!$C$22 -> 0.58530014 | H42: =H11/'Other Inputs'!$C$22 -> 0.59718739 | I42: =I11/'Other Inputs'!$C$22 -> 0.60933819 | J42: =J11/'Other Inputs'!$C$22 -> 0.62169849 | ... AH42: =AH11/'Other Inputs'!$C$22 -> 1.0323099
B43: 36739 | C43: =C12/'Other Inputs'!$C$22 -> 0.53520919 | D43: =D12/'Other Inputs'!$C$22 -> 0.54341815 | E43: =E12/'Other Inputs'!$C$22 -> 0.55659978 | F43: =F12/'Other Inputs'!$C$22 -> 0.56909733 | G43: =G12/'Other Inputs'!$C$22 -> 0.5807528 | H43: =H12/'Other Inputs'!$C$22 -> 0.59256125 | I43: =I12/'Other Inputs'!$C$22 -> 0.60462497 | J43: =J12/'Other Inputs'!$C$22 -> 0.61688277 | ... AH43: =AH12/'Other Inputs'!$C$22 -> 1.0243521
B44: 36770 | C44: =C13/'Other Inputs'!$C$22 -> 0.5414506 | D44: =D13/'Other Inputs'!$C$22 -> 0.55121311 | E44: =E13/'Other Inputs'!$C$22 -> 0.56444675 | F44: =F13/'Other Inputs'!$C$22 -> 0.5770827 | G44: =G13/'Other Inputs'!$C$22 -> 0.58889479 | H44: =H13/'Other Inputs'!$C$22 -> 0.60088255 | I44: =I13/'Other Inputs'!$C$22 -> 0.61312282 | J44: =J13/'Other Inputs'!$C$22 -> 0.62554591 | ... AH44: =AH13/'Other Inputs'!$C$22 -> 1.0387765
B45: 36800 | C45: =C14/'Other Inputs'!$C$22 -> 0.53705103 | D45: =D14/'Other Inputs'!$C$22 -> 0.54818719 | E45: =E14/'Other Inputs'!$C$22 -> 0.56121192 | F45: =F14/'Other Inputs'!$C$22 -> 0.57373789 | G45: =G14/'Other Inputs'!$C$22 -> 0.58547463 | H45: =H14/'Other Inputs'!$C$22 -> 0.59740645 | I45: =I14/'Other Inputs'!$C$22 -> 0.60958301 | J45: =J14/'Other Inputs'!$C$22 -> 0.62192743 | ... AH45: =AH14/'Other Inputs'!$C$22 -> 1.0328066
B46: 36831 | C46: =C15/'Other Inputs'!$C$22 -> 0.56225295 | D46: =D15/'Other Inputs'!$C$22 -> 0.57544026 | E46: =E15/'Other Inputs'!$C$22 -> 0.58896954 | F46: =F15/'Other Inputs'!$C$22 -> 0.60207562 | G46: =G15/'Other Inputs'!$C$22 -> 0.61438483 | H46: =H15/'Other Inputs'!$C$22 -> 0.62692018 | I46: =I15/'Other Inputs'!$C$22 -> 0.63970575 | J46: =J15/'Other Inputs'!$C$22 -> 0.65265289 | ... AH46: =AH15/'Other Inputs'!$C$22 -> 1.0838717
B47: 36861 | C47: =C16/'Other Inputs'!$C$22 -> 0.56542169 | D47: =D16/'Other Inputs'!$C$22 -> 0.58022798 | E47: =E16/'Other Inputs'!$C$22 -> 0.59372574 | F47: =F16/'Other Inputs'!$C$22 -> 0.60689791 | G47: =G16/'Other Inputs'!$C$22 -> 0.61929842 | H47: =H16/'Other Inputs'!$C$22 -> 0.6319485 | I47: =I16/'Other Inputs'!$C$22 -> 0.64484413 | J47: =J16/'Other Inputs'!$C$22 -> 0.65788791 | ... AH47: =AH16/'Other Inputs'!$C$22 -> 1.0926067
B49: CA Gas Price Forecast ($/therm) ($2022) | C49: ='User Dashboard'!E$58 -> 2023 | D49: ='User Dashboard'!F$58 -> 2024 | E49: ='User Dashboard'!G$58 -> 2025 | F49: ='User Dashboard'!H$58 -> 2026 | G49: ='User Dashboard'!I$58 -> 2027 | H49: ='User Dashboard'!J$58 -> 2028 | I49: ='User Dashboard'!K$58 -> 2029 | J49: ='User Dashboard'!L$58 -> 2030 | ... AH49: ='User Dashboard'!AJ$58 -> 2054
B50: 36526 | C50: =C19/'Other Inputs'!$C$22 -> 0.56743612 | D50: =D19/'Other Inputs'!$C$22 -> 0.55275616 | E50: =E19/'Other Inputs'!$C$22 -> 0.55416814 | F50: =F19/'Other Inputs'!$C$22 -> 0.55406483 | G50: =G19/'Other Inputs'!$C$22 -> 0.55355627 | H50: =H19/'Other Inputs'!$C$22 -> 0.55298933 | I50: =I19/'Other Inputs'!$C$22 -> 0.55256846 | J50: =J19/'Other Inputs'!$C$22 -> 0.55221248 | ... AH50: =AH19/'Other Inputs'!$C$22 -> 0.54298282
B51: 36557 | C51: =C20/'Other Inputs'!$C$22 -> 0.55370138 | D51: =D20/'Other Inputs'!$C$22 -> 0.54078553 | E51: =E20/'Other Inputs'!$C$22 -> 0.5420351 | F51: =F20/'Other Inputs'!$C$22 -> 0.54189859 | G51: =G20/'Other Inputs'!$C$22 -> 0.54139484 | H51: =H20/'Other Inputs'!$C$22 -> 0.54085271 | I51: =I20/'Other Inputs'!$C$22 -> 0.54044737 | J51: =J20/'Other Inputs'!$C$22 -> 0.54009318 | ... AH51: =AH20/'Other Inputs'!$C$22 -> 0.53108603
B52: 36586 | C52: =C21/'Other Inputs'!$C$22 -> 0.50711162 | D52: =D21/'Other Inputs'!$C$22 -> 0.49657893 | E52: =E21/'Other Inputs'!$C$22 -> 0.49760534 | F52: =F21/'Other Inputs'!$C$22 -> 0.49744747 | G52: =G21/'Other Inputs'!$C$22 -> 0.4969792 | H52: =H21/'Other Inputs'!$C$22 -> 0.49649291 | I52: =I21/'Other Inputs'!$C$22 -> 0.49612659 | J52: =J21/'Other Inputs'!$C$22 -> 0.4957959 | ... AH52: =AH21/'Other Inputs'!$C$22 -> 0.48754583
B53: 36617 | C53: =C22/'Other Inputs'!$C$22 -> 0.49731527 | D53: =D22/'Other Inputs'!$C$22 -> 0.48826347 | E53: =E22/'Other Inputs'!$C$22 -> 0.48915378 | F53: =F22/'Other Inputs'!$C$22 -> 0.48896658 | G53: =G22/'Other Inputs'!$C$22 -> 0.48850056 | H53: =H22/'Other Inputs'!$C$22 -> 0.48803373 | I53: =I22/'Other Inputs'!$C$22 -> 0.48767932 | J53: =J22/'Other Inputs'!$C$22 -> 0.48734883 | ... AH53: =AH22/'Other Inputs'!$C$22 -> 0.47925732
B54: 36647 | C54: =C23/'Other Inputs'!$C$22 -> 0.51341495 | D54: =D23/'Other Inputs'!$C$22 -> 0.50539521 | E54: =E23/'Other Inputs'!$C$22 -> 0.50619372 | F54: =F23/'Other Inputs'!$C$22 -> 0.50596689 | G54: =G23/'Other Inputs'!$C$22 -> 0.50547872 | H54: =H23/'Other Inputs'!$C$22 -> 0.50500722 | I54: =I23/'Other Inputs'!$C$22 -> 0.50464636 | J54: =J23/'Other Inputs'!$C$22 -> 0.50429874 | ... AH54: =AH23/'Other Inputs'!$C$22 -> 0.49594445
B55: 36678 | C55: =C24/'Other Inputs'!$C$22 -> 0.52544816 | D55: =D24/'Other Inputs'!$C$22 -> 0.51860312 | E55: =E24/'Other Inputs'!$C$22 -> 0.51929631 | F55: =F24/'Other Inputs'!$C$22 -> 0.51902962 | G55: =G24/'Other Inputs'!$C$22 -> 0.51852276 | H55: =H24/'Other Inputs'!$C$22 -> 0.51805094 | I55: =I24/'Other Inputs'!$C$22 -> 0.5176868 | J55: =J24/'Other Inputs'!$C$22 -> 0.51732441 | ... AH55: =AH24/'Other Inputs'!$C$22 -> 0.50877347
B56: 36708 | C56: =C25/'Other Inputs'!$C$22 -> 0.52836723 | D56: =D25/'Other Inputs'!$C$22 -> 0.522861 | E56: =E25/'Other Inputs'!$C$22 -> 0.5234327 | F56: =F25/'Other Inputs'!$C$22 -> 0.52312965 | G56: =G25/'Other Inputs'!$C$22 -> 0.52261264 | H56: =H25/'Other Inputs'!$C$22 -> 0.52214905 | I56: =I25/'Other Inputs'!$C$22 -> 0.52178809 | J56: =J25/'Other Inputs'!$C$22 -> 0.52141702 | ... AH56: =AH25/'Other Inputs'!$C$22 -> 0.51281771
B57: 36739 | C57: =C26/'Other Inputs'!$C$22 -> 0.52304609 | D57: =D26/'Other Inputs'!$C$22 -> 0.51896486 | E57: =E26/'Other Inputs'!$C$22 -> 0.51940613 | F57: =F26/'Other Inputs'!$C$22 -> 0.51907142 | G57: =G26/'Other Inputs'!$C$22 -> 0.51855233 | H57: =H26/'Other Inputs'!$C$22 -> 0.5181042 | I57: =I26/'Other Inputs'!$C$22 -> 0.51775207 | J57: =J26/'Other Inputs'!$C$22 -> 0.51737809 | ... AH57: =AH26/'Other Inputs'!$C$22 -> 0.50886452
B58: 36770 | C58: =C27/'Other Inputs'!$C$22 -> 0.52914566 | D58: =D27/'Other Inputs'!$C$22 -> 0.52640905 | E58: =E27/'Other Inputs'!$C$22 -> 0.52672874 | F58: =F27/'Other Inputs'!$C$22 -> 0.52635485 | G58: =G27/'Other Inputs'!$C$22 -> 0.5258223 | H58: =H27/'Other Inputs'!$C$22 -> 0.5253799 | I58: =I27/'Other Inputs'!$C$22 -> 0.52502895 | J58: =J27/'Other Inputs'!$C$22 -> 0.52464385 | ... AH58: =AH27/'Other Inputs'!$C$22 -> 0.51603012
B59: 36800 | C59: =C28/'Other Inputs'!$C$22 -> 0.52484607 | D59: =D28/'Other Inputs'!$C$22 -> 0.5235193 | E59: =E28/'Other Inputs'!$C$22 -> 0.52371008 | F59: =F28/'Other Inputs'!$C$22 -> 0.52330406 | G59: =G28/'Other Inputs'!$C$22 -> 0.52276845 | H59: =H28/'Other Inputs'!$C$22 -> 0.52234058 | I59: =I28/'Other Inputs'!$C$22 -> 0.52199773 | J59: =J28/'Other Inputs'!$C$22 -> 0.52160903 | ... AH59: =AH28/'Other Inputs'!$C$22 -> 0.51306442
B60: 36831 | C60: =C29/'Other Inputs'!$C$22 -> 0.54947526 | D60: =D29/'Other Inputs'!$C$22 -> 0.549546 | E60: =E29/'Other Inputs'!$C$22 -> 0.54961285 | F60: =F29/'Other Inputs'!$C$22 -> 0.54915079 | G60: =G29/'Other Inputs'!$C$22 -> 0.54858227 | H60: =H29/'Other Inputs'!$C$22 -> 0.54814582 | I60: =I29/'Other Inputs'!$C$22 -> 0.54779242 | J60: =J29/'Other Inputs'!$C$22 -> 0.5473784 | ... AH60: =AH29/'Other Inputs'!$C$22 -> 0.5384319
B61: 36861 | C61: =C30/'Other Inputs'!$C$22 -> 0.55257199 | D61: =D30/'Other Inputs'!$C$22 -> 0.55411828 | E61: =E30/'Other Inputs'!$C$22 -> 0.55405123 | F61: =F30/'Other Inputs'!$C$22 -> 0.55354918 | G61: =G30/'Other Inputs'!$C$22 -> 0.5529696 | H61: =H30/'Other Inputs'!$C$22 -> 0.55254232 | I61: =I30/'Other Inputs'!$C$22 -> 0.55219252 | J61: =J30/'Other Inputs'!$C$22 -> 0.551769 | ... AH61: =AH30/'Other Inputs'!$C$22 -> 0.54277116

Sheet Emissions
B2: Gas Emissions Values
B4: Gas Emissions Rates
B5: Combustor Type | C5: Controls | D5: NOx (lb/MMBtu) | E5: CO2 (lb/MMBtu) | F5: Nox (lbs / Therm) | G5: CO2 (Tonnes / Therm) | H5: Key
B6: Large Boiler (>100MMBtu/Hr) | C6: Uncontrolled | D6: 0.186 | E6: 117 | F6: =D6/10 -> 0.0186 | G6: =E6/(10*2204.62) -> 0.005307037 | H6: =_xlfn.CONCAT(B6,"-",C6) -> Large Boiler (>100MMBtu/Hr)-Uncontrolled
B7: Large Boiler (>100MMBtu/Hr) | C7: Low Nox Burner | D7: 0.137 | E7: 117 | F7: =D7/10 -> 0.0137 | G7: =E7/(10*2204.62) -> 0.005307037 | H7: =_xlfn.CONCAT(B7,"-",C7) -> Large Boiler (>100MMBtu/Hr)-Low Nox Burner
B8: Large Boiler (>100MMBtu/Hr) | C8: Flue Gas Recirculation | D8: 0.098 | E8: 117 | F8: =D8/10 -> 0.0098 | G8: =E8/(10*2204.62) -> 0.005307037 | H8: =_xlfn.CONCAT(B8,"-",C8) -> Large Boiler (>100MMBtu/Hr)-Flue Gas Recirculation
B9: Small Boiler (<100MMBtu/Hr) | C9: Uncontrolled | D9: 0.098 | E9: 117 | F9: =D9/10 -> 0.0098 | G9: =E9/(10*2204.62) -> 0.005307037 | H9: =_xlfn.CONCAT(B9,"-",C9) -> Small Boiler (<100MMBtu/Hr)-Uncontrolled
B10: Small Boiler (<100MMBtu/Hr) | C10: Low Nox Burner | D10: 0.049 | E10: 117 | F10: =D10/10 -> 0.0049 | G10: =E10/(10*2204.62) -> 0.005307037 | H10: =_xlfn.CONCAT(B10,"-",C10) -> Small Boiler (<100MMBtu/Hr)-Low Nox Burner
B11: Small Boiler (<100MMBtu/Hr) | C11: Flue Gas Recirculation | D11: 0.031 | E11: 117 | F11: =D11/10 -> 0.0031 | G11: =E11/(10*2204.62) -> 0.005307037 | H11: =_xlfn.CONCAT(B11,"-",C11) -> Small Boiler (<100MMBtu/Hr)-Flue Gas Recirculation
B12: Residential Furnace | C12: Uncontrolled | D12: 0.092 | E12: 117 | F12: =D12/10 -> 0.0092 | G12: =E12/(10*2204.62) -> 0.005307037 | H12: =_xlfn.CONCAT(B12,"-",C12) -> Residential Furnace-Uncontrolled
B16: Gas Emissions Costs - TRC | C16: 2019 | D16: 2020 | E16: 2021 | F16: 2022 | G16: 2023 | H16: =G16+1 -> 2024 | I16: =H16+1 -> 2025 | J16: =I16+1 -> 2026 | K16: =J16+1 -> 2027 | L16: =K16+1 -> 2028 | M16: =L16+1 -> 2029 | N16: =M16+1 -> 2030 | O16: =N16+1 -> 2031 | ... AF16: =AE16+1 -> 2048 | AG16: 2049 | AH16: 2050 | AI16: 2051 | AJ16: 2052 | AK16: 2053 | AL16: 2054
B17: NOx (nominal $/lb) | C17: 11.339585 | D17: 12.473543 | E17: 13.720898 | F17: 15.092987 | G17: 16.602286 | H17: =TREND($C17:$G17,$C$16:$G$16,H$16) -> 17.789314 | I17: =TREND($C17:$G17,$C$16:$G$16,I$16) -> 19.103799 | J17: =TREND($C17:$G17,$C$16:$G$16,J$16) -> 20.418283 | K17: =TREND($C17:$G17,$C$16:$G$16,K$16) -> 21.732768 | L17: =TREND($C17:$G17,$C$16:$G$16,L$16) -> 23.047253 | M17: =TREND($C17:$G17,$C$16:$G$16,M$16) -> 24.361737 | N17: =TREND($C17:$G17,$C$16:$G$16,N$16) -> 25.676222 | O17: =TREND($C17:$G17,$C$16:$G$16,O$16) -> 26.990707 | ... AL17: =TREND($C17:$G17,$C$16:$G$16,AL$16) -> 57.223854
B18: NOx (nominal $/therm) | C18: =C17*'User Dashboard'!$C$34 -> 0.11112793 | D18: =D17*'User Dashboard'!$C$34 -> 0.12224072 | E18: =E17*'User Dashboard'!$C$34 -> 0.1344648 | F18: =F17*'User Dashboard'!$C$34 -> 0.14791128 | G18: =G17*'User Dashboard'!$C$34 -> 0.1627024 | H18: =H17*'User Dashboard'!$C$34 -> 0.17433528 | I18: =I17*'User Dashboard'!$C$34 -> 0.18721723 | J18: =J17*'User Dashboard'!$C$34 -> 0.20009918 | ... AL18: =AL17*'User Dashboard'!$C$34 -> 0.56079377
B19: CO2 (nominal $/tonne) | C19: =$D$19*(1+'Other Inputs'!$C$18)^(Emissions!C$16-2020) -> 114 | D19: 114 | E19: =$D$19*(1+'Other Inputs'!$C$18)^(Emissions!E$16-2020) -> 114 | F19: =$D$19*(1+'Other Inputs'!$C$18)^(Emissions!F$16-2020) -> 114 | G19: =$D$19*(1+'Other Inputs'!$C$18)^(Emissions!G$16-2020) -> 114 | H19: =$D$19*(1+'Other Inputs'!$C$18)^(Emissions!H$16-2020) -> 114 | I19: =$D$19*(1+'Other Inputs'!$C$18)^(Emissions!I$16-2020) -> 114 | J19: =$D$19*(1+'Other Inputs'!$C$18)^(Emissions!J$16-2020) -> 114 | K19: =$D$19*(1+'Other Inputs'!$C$18)^(Emissions!K$16-2020) -> 114 | L19: =$D$19*(1+'Other Inputs'!$C$18)^(Emissions!L$16-2020) -> 114 | ... AL19: =$D$19*(1+'Other Inputs'!$C$18)^(Emissions!AL$16-2020) -> 114
B20: PM10 (nominal $/lb) | C20: 15.86307 | D20: 17.449377 | E20: 19.194314 | F20: 21.113746 | G20: 23.22512 | H20: =TREND($C20:$G20,$C$16:$G$16,H$16) -> 24.885666 | I20: =TREND($C20:$G20,$C$16:$G$16,I$16) -> 26.724513 | J20: =TREND($C20:$G20,$C$16:$G$16,J$16) -> 28.563361 | K20: =TREND($C20:$G20,$C$16:$G$16,K$16) -> 30.402208 | L20: =TREND($C20:$G20,$C$16:$G$16,L$16) -> 32.241055 | M20: =TREND($C20:$G20,$C$16:$G$16,M$16) -> 34.079902 | N20: =TREND($C20:$G20,$C$16:$G$16,N$16) -> 35.918749 | O20: =TREND($C20:$G20,$C$16:$G$16,O$16) -> 37.757596 | ... AL20: =TREND($C20:$G20,$C$16:$G$16,AL$16) -> 80.051078
B22: Gas Emissions Costs - SCT | D22: 2020 | E22: 2021 | F22: 2022 | G22: 2023 | H22: =G22+1 -> 2024 | I22: =H22+1 -> 2025 | J22: =I22+1 -> 2026 | K22: =J22+1 -> 2027 | L22: =K22+1 -> 2028 | M22: =L22+1 -> 2029 | N22: =M22+1 -> 2030 | O22: =N22+1 -> 2031 | ... AF22: =AE22+1 -> 2048 | AG22: 2049 | AH22: 2050 | AI22: 2051 | AJ22: 2052 | AK22: 2053 | AL22: 2054
B23: Air Quality Adder (2020 $/therm) | D23: 1.23 | E23: =D23 -> 1.23 | F23: =E23 -> 1.23 | G23: =F23 -> 1.23 | H23: =G23 -> 1.23 | I23: =H23 -> 1.23 | J23: =I23 -> 1.23 | K23: =J23 -> 1.23 | L23: =K23 -> 1.23 | ... AL23: =AK23 -> 1.23
B24: Air Quality Adder (nominal $/therm) | D24: =D23*(1+'Other Inputs'!$C$11)^(Emissions!D22-2020) -> 1.23 | E24: =E23*(1+'Other Inputs'!$C$11)^(Emissions!E22-2020) -> 1.2546 | F24: =F23*(1+'Other Inputs'!$C$11)^(Emissions!F22-2020) -> 1.279692 | G24: =G23*(1+'Other Inputs'!$C$11)^(Emissions!G22-2020) -> 1.3052858 | H24: =H23*(1+'Other Inputs'!$C$11)^(Emissions!H22-2020) -> 1.3313916 | I24: =I23*(1+'Other Inputs'!$C$11)^(Emissions!I22-2020) -> 1.3580194 | J24: =J23*(1+'Other Inputs'!$C$11)^(Emissions!J22-2020) -> 1.3851798 | K24: =K23*(1+'Other Inputs'!$C$11)^(Emissions!K22-2020) -> 1.4128834 | ... AL24: =AL23*(1+'Other Inputs'!$C$11)^(Emissions!AL22-2020) -> 2.4116315
B25: Social Cost of Carbon Base (2020 $/tonne) | D25: 51 | E25: =D25+($I25-$D25)/($I$22-$D$22) -> 52 | F25: =E25+($I25-$D25)/($I$22-$D$22) -> 53 | G25: =F25+($I25-$D25)/($I$22-$D$22) -> 54 | H25: =G25+($I25-$D25)/($I$22-$D$22) -> 55 | I25: 56 | J25: =I25+($N25-$I25)/($N$22-$I$22) -> 57.2 | K25: =J25+($N25-$I25)/($N$22-$I$22) -> 58.4 | L25: =K25+($N25-$I25)/($N$22-$I$22) -> 59.6 | M25: =L25+($N25-$I25)/($N$22-$I$22) -> 60.8 | N25: 62 | O25: =N25+($S25-$N25)/($S$22-$N$22) -> 63 | P25: =O25+($S25-$N25)/($S$22-$N$22) -> 64 | Q25: =P25+($S25-$N25)/($S$22-$N$22) -> 65 | R25: =Q25+($S25-$N25)/($S$22-$N$22) -> 66 | S25: 67 | T25: =S25+($X25-$S25)/($X$22-$S$22) -> 68.2 | U25: =T25+($X25-$S25)/($X$22-$S$22) -> 69.4 | V25: =U25+($X25-$S25)/($X$22-$S$22) -> 70.6 | W25: =V25+($X25-$S25)/($X$22-$S$22) -> 71.8 | X25: 73 | Y25: =X25+($AC25-$X25)/($AC$22-$X$22) -> 74.2 | Z25: =Y25+($AC25-$X25)/($AC$22-$X$22) -> 75.4 | AA25: =Z25+($AC25-$X25)/($AC$22-$X$22) -> 76.6 | AB25: =AA25+($AC25-$X25)/($AC$22-$X$22) -> 77.8 | AC25: 79 | AD25: =AC25+($AC25-$X25)/($AC$22-$X$22) -> 80.2 | AE25: =AD25+($AC25-$X25)/($AC$22-$X$22) -> 81.4 | AF25: =AE25+($AC25-$X25)/($AC$22-$X$22) -> 82.6 | AG25: =AF25+($AC25-$X25)/($AC$22-$X$22) -> 83.8 | AH25: =AG25+($AC25-$X25)/($AC$22-$X$22) -> 85 | AI25: =AH25+($AC25-$X25)/($AC$22-$X$22) -> 86.2 | AJ25: =AI25+($AC25-$X25)/($AC$22-$X$22) -> 87.4 | AK25: =AJ25+($AC25-$X25)/($AC$22-$X$22) -> 88.6 | AL25: =AK25+($AC25-$X25)/($AC$22-$X$22) -> 89.8
B26: Social Cost of Carbon High (2020 $/tonne) | D26: 152 | E26: =D26+($I26-$D26)/($I$22-$D$22) -> 155.4 | F26: =E26+($I26-$D26)/($I$22-$D$22) -> 158.8 | G26: =F26+($I26-$D26)/($I$22-$D$22) -> 162.2 | H26: =G26+($I26-$D26)/($I$22-$D$22) -> 165.6 | I26: 169 | J26: =I26+($N26-$I26)/($N$22-$I$22) -> 172.6 | K26: =J26+($N26-$I26)/($N$22-$I$22) -> 176.2 | L26: =K26+($N26-$I26)/($N$22-$I$22) -> 179.8 | M26: =L26+($N26-$I26)/($N$22-$I$22) -> 183.4 | N26: 187 | O26: =N26+($S26-$N26)/($S$22-$N$22) -> 190.8 | P26: =O26+($S26-$N26)/($S$22-$N$22) -> 194.6 | Q26: =P26+($S26-$N26)/($S$22-$N$22) -> 198.4 | R26: =Q26+($S26-$N26)/($S$22-$N$22) -> 202.2 | S26: 206 | T26: =S26+($X26-$S26)/($X$22-$S$22) -> 209.8 | U26: =T26+($X26-$S26)/($X$22-$S$22) -> 213.6 | V26: =U26+($X26-$S26)/($X$22-$S$22) -> 217.4 | W26: =V26+($X26-$S26)/($X$22-$S$22) -> 221.2 | X26: 225 | Y26: =X26+($AC26-$X26)/($AC$22-$X$22) -> 228.4 | Z26: =Y26+($AC26-$X26)/($AC$22-$X$22) -> 231.8 | AA26: =Z26+($AC26-$X26)/($AC$22-$X$22) -> 235.2 | AB26: =AA26+($AC26-$X26)/($AC$22-$X$22) -> 238.6 | AC26: 242 | AD26: =AC26+($AC26-$X26)/($AC$22-$X$22) -> 245.4 | AE26: =AD26+($AC26-$X26)/($AC$22-$X$22) -> 248.8 | AF26: =AE26+($AC26-$X26)/($AC$22-$X$22) -> 252.2 | AG26: =AF26+($AC26-$X26)/($AC$22-$X$22) -> 255.6 | AH26: =AG26+($AC26-$X26)/($AC$22-$X$22) -> 259 | AI26: =AH26+($AC26-$X26)/($AC$22-$X$22) -> 262.4 | AJ26: =AI26+($AC26-$X26)/($AC$22-$X$22) -> 265.8 | AK26: =AJ26+($AC26-$X26)/($AC$22-$X$22) -> 269.2 | AL26: =AK26+($AC26-$X26)/($AC$22-$X$22) -> 272.6
B27: Social Cost of Carbon Base (nominal $/tonne) | D27: =D25*(1+'Other Inputs'!$C$11)^(D22-2020) -> 51 | E27: =E25*(1+'Other Inputs'!$C$11)^(E22-2020) -> 53.04 | F27: =F25*(1+'Other Inputs'!$C$11)^(F22-2020) -> 55.1412 | G27: =G25*(1+'Other Inputs'!$C$11)^(G22-2020) -> 57.305232 | H27: =H25*(1+'Other Inputs'!$C$11)^(H22-2020) -> 59.533769 | I27: =I25*(1+'Other Inputs'!$C$11)^(I22-2020) -> 61.828525 | J27: =J25*(1+'Other Inputs'!$C$11)^(J22-2020) -> 64.41649 | K27: =K25*(1+'Other Inputs'!$C$11)^(K22-2020) -> 67.083243 | ... AL27: =AL25*(1+'Other Inputs'!$C$11)^(AL22-2020) -> 176.06871
B28: Social Cost of Carbon High (nominal $/tonne) | D28: =D26*(1+'Other Inputs'!$C$11)^(D22-2020) -> 152 | E28: =E26*(1+'Other Inputs'!$C$11)^(E22-2020) -> 158.508 | F28: =F26*(1+'Other Inputs'!$C$11)^(F22-2020) -> 165.21552 | G28: =G26*(1+'Other Inputs'!$C$11)^(G22-2020) -> 172.12794 | H28: =H26*(1+'Other Inputs'!$C$11)^(H22-2020) -> 179.25077 | I28: =I26*(1+'Other Inputs'!$C$11)^(I22-2020) -> 186.58966 | J28: =J26*(1+'Other Inputs'!$C$11)^(J22-2020) -> 194.37563 | K28: =K26*(1+'Other Inputs'!$C$11)^(K22-2020) -> 202.39841 | ... AL28: =AL26*(1+'Other Inputs'!$C$11)^(AL22-2020) -> 534.48029
B30: Gas Emissions Costs - Active | D30: 2020 | E30: 2021 | F30: 2022 | G30: 2023 | H30: 2024 | I30: 2025 | J30: 2026 | K30: 2027 | L30: 2028 | M30: 2029 | N30: 2030 | O30: 2031 | P30: 2032 | Q30: 2033 | R30: 2034 | S30: 2035 | T30: 2036 | U30: 2037 | V30: 2038 | W30: 2039 | X30: 2040 | Y30: 2041 | Z30: 2042 | AA30: 2043 | AB30: 2044 | AC30: 2045 | AD30: 2046 | AE30: 2047 | AF30: 2048 | AG30: 2049 | AH30: 2050 | AI30: 2051 | AJ30: 2052 | AK30: 2053 | AL30: 2054
B31: Air Quality Adder (nominal $/therm) | D31: =IF('User Dashboard'!$C$10="TRC",0,D24)*('User Dashboard'!$C$34/MAX(Emissions!$F$6:$F$12)) -> 0 | E31: =IF('User Dashboard'!$C$10="TRC",0,E24)*('User Dashboard'!$C$34/MAX(Emissions!$F$6:$F$12)) -> 0 | F31: =IF('User Dashboard'!$C$10="TRC",0,F24)*('User Dashboard'!$C$34/MAX(Emissions!$F$6:$F$12)) -> 0 | G31: =IF('User Dashboard'!$C$10="TRC",0,G24)*('User Dashboard'!$C$34/MAX(Emissions!$F$6:$F$12)) -> 0 | H31: =IF('User Dashboard'!$C$10="TRC",0,H24)*('User Dashboard'!$C$34/MAX(Emissions!$F$6:$F$12)) -> 0 | I31: =IF('User Dashboard'!$C$10="TRC",0,I24)*('User Dashboard'!$C$34/MAX(Emissions!$F$6:$F$12)) -> 0 | J31: =IF('User Dashboard'!$C$10="TRC",0,J24)*('User Dashboard'!$C$34/MAX(Emissions!$F$6:$F$12)) -> 0 | K31: =IF('User Dashboard'!$C$10="TRC",0,K24)*('User Dashboard'!$C$34/MAX(Emissions!$F$6:$F$12)) -> 0 | ... AL31: =IF('User Dashboard'!$C$10="TRC",0,AL24)*('User Dashboard'!$C$34/MAX(Emissions!$F$6:$F$12)) -> 0
B32: NOx Cost (nominal $/therm) | D32: =IF('User Dashboard'!$C$10="TRC",D18,0) -> 0.12224072 | E32: =IF('User Dashboard'!$C$10="TRC",E18,0) -> 0.1344648 | F32: =IF('User Dashboard'!$C$10="TRC",F18,0) -> 0.14791128 | G32: =IF('User Dashboard'!$C$10="TRC",G18,0) -> 0.1627024 | H32: =IF('User Dashboard'!$C$10="TRC",H18,0) -> 0.17433528 | I32: =IF('User Dashboard'!$C$10="TRC",I18,0) -> 0.18721723 | J32: =IF('User Dashboard'!$C$10="TRC",J18,0) -> 0.20009918 | K32: =IF('User Dashboard'!$C$10="TRC",K18,0) -> 0.21298113 | ... AL32: =IF('User Dashboard'!$C$10="TRC",AL18,0) -> 0.56079377
B33: CO2 Cost (nominal $/tonne) | D33: =IF('User Dashboard'!$C$10="TRC",D19,MAX(IF('User Dashboard'!$C$11="Base",D27,D28),D19)) -> 114 | E33: =IF('User Dashboard'!$C$10="TRC",E19,MAX(IF('User Dashboard'!$C$11="Base",E27,E28),E19)) -> 114 | F33: =IF('User Dashboard'!$C$10="TRC",F19,MAX(IF('User Dashboard'!$C$11="Base",F27,F28),F19)) -> 114 | G33: =IF('User Dashboard'!$C$10="TRC",G19,MAX(IF('User Dashboard'!$C$11="Base",G27,G28),G19)) -> 114 | H33: =IF('User Dashboard'!$C$10="TRC",H19,MAX(IF('User Dashboard'!$C$11="Base",H27,H28),H19)) -> 114 | I33: =IF('User Dashboard'!$C$10="TRC",I19,MAX(IF('User Dashboard'!$C$11="Base",I27,I28),I19)) -> 114 | J33: =IF('User Dashboard'!$C$10="TRC",J19,MAX(IF('User Dashboard'!$C$11="Base",J27,J28),J19)) -> 114 | K33: =IF('User Dashboard'!$C$10="TRC",K19,MAX(IF('User Dashboard'!$C$11="Base",K27,K28),K19)) -> 114 | ... AL33: =IF('User Dashboard'!$C$10="TRC",AL19,MAX(IF('User Dashboard'!$C$11="Base",AL27,AL28),AL19)) -> 114

Sheet T&D
B2: Gas Transportation Marginal Costs ($/therm, nominal)
B3: Transportation Marginal Costs
C4: Nominal $/Therm | D4: 2022 | E4: =D4+1 -> 2023 | F4: =E4+1 -> 2024 | G4: =F4+1 -> 2025 | H4: =G4+1 -> 2026 | I4: =H4+1 -> 2027 | J4: =I4+1 -> 2028 | K4: =J4+1 -> 2029 | L4: =K4+1 -> 2030 | ... AJ4: =AI4+1 -> 2054 | AL4: Key
B5: PG&E | C5: Residential | D5: 0.3825 | E5: 0.37003 | F5: 0.3825 | G5: =AVERAGE($D16:$F16)*(1+'User Dashboard'!$C$20)^('T&D'!G$4-2022) -> 0.39368042 | H5: =AVERAGE($D16:$F16)*(1+'User Dashboard'!$C$20)^('T&D'!H$4-2022) -> 0.40155403 | I5: =AVERAGE($D16:$F16)*(1+'User Dashboard'!$C$20)^('T&D'!I$4-2022) -> 0.40958511 | J5: =AVERAGE($D16:$F16)*(1+'User Dashboard'!$C$20)^('T&D'!J$4-2022) -> 0.41777682 | K5: =AVERAGE($D16:$F16)*(1+'User Dashboard'!$C$20)^('T&D'!K$4-2022) -> 0.42613235 | L5: =AVERAGE($D16:$F16)*(1+'User Dashboard'!$C$20)^('T&D'!L$4-2022) -> 0.434655 | M5: =AVERAGE($D16:$F16)*(1+'User Dashboard'!$C$20)^('T&D'!M$4-2022) -> 0.4433481 | N5: =AVERAGE($D16:$F16)*(1+'User Dashboard'!$C$20)^('T&D'!N$4-2022) -> 0.45221506 | ... AJ5: =AVERAGE($D16:$F16)*(1+'User Dashboard'!$C$20)^('T&D'!AJ$4-2022) -> 0.69911529 | AL5: =_xlfn.CONCAT($B$5,"-",C5) -> PG&E-Residential
C6: Commercial | D6: 0.23276 | E6: 0.236267 | F6: 0.20595 | G6: =AVERAGE($D17:$F17)*(1+'User Dashboard'!$C$20)^('T&D'!G$4-2022) -> 0.23429599 | H6: =AVERAGE($D17:$F17)*(1+'User Dashboard'!$C$20)^('T&D'!H$4-2022) -> 0.23898191 | I6: =AVERAGE($D17:$F17)*(1+'User Dashboard'!$C$20)^('T&D'!I$4-2022) -> 0.24376154 | J6: =AVERAGE($D17:$F17)*(1+'User Dashboard'!$C$20)^('T&D'!J$4-2022) -> 0.24863678 | K6: =AVERAGE($D17:$F17)*(1+'User Dashboard'!$C$20)^('T&D'!K$4-2022) -> 0.25360951 | L6: =AVERAGE($D17:$F17)*(1+'User Dashboard'!$C$20)^('T&D'!L$4-2022) -> 0.2586817 | M6: =AVERAGE($D17:$F17)*(1+'User Dashboard'!$C$20)^('T&D'!M$4-2022) -> 0.26385534 | N6: =AVERAGE($D17:$F17)*(1+'User Dashboard'!$C$20)^('T&D'!N$4-2022) -> 0.26913244 | ... AJ6: =AVERAGE($D17:$F17)*(1+'User Dashboard'!$C$20)^('T&D'!AJ$4-2022) -> 0.41607328 | AL6: =_xlfn.CONCAT($B$5,"-",C6) -> PG&E-Commercial
C7: Total Core | D7: 0.28163 | E7: 0.285878 | F7: 0.31218 | G7: =AVERAGE($D18:$F18)*(1+'User Dashboard'!$C$20)^('T&D'!G$4-2022) -> 0.30490636 | H7: =AVERAGE($D18:$F18)*(1+'User Dashboard'!$C$20)^('T&D'!H$4-2022) -> 0.31100449 | I7: =AVERAGE($D18:$F18)*(1+'User Dashboard'!$C$20)^('T&D'!I$4-2022) -> 0.31722458 | J7: =AVERAGE($D18:$F18)*(1+'User Dashboard'!$C$20)^('T&D'!J$4-2022) -> 0.32356907 | K7: =AVERAGE($D18:$F18)*(1+'User Dashboard'!$C$20)^('T&D'!K$4-2022) -> 0.33004045 | L7: =AVERAGE($D18:$F18)*(1+'User Dashboard'!$C$20)^('T&D'!L$4-2022) -> 0.33664126 | M7: =AVERAGE($D18:$F18)*(1+'User Dashboard'!$C$20)^('T&D'!M$4-2022) -> 0.34337408 | N7: =AVERAGE($D18:$F18)*(1+'User Dashboard'!$C$20)^('T&D'!N$4-2022) -> 0.35024157 | ... AJ7: =AVERAGE($D18:$F18)*(1+'User Dashboard'!$C$20)^('T&D'!AJ$4-2022) -> 0.54146634 | AL7: =_xlfn.CONCAT($B$5,"-",C7) -> PG&E-Total Core
B8: SoCal Gas | C8: Residential | D8: 0.23 | E8: 0.22 | F8: 0.22 | G8: =AVERAGE($D19:$F19)*(1+'User Dashboard'!$C$20)^('T&D'!G$4-2022) -> 0.23245528 | H8: =AVERAGE($D19:$F19)*(1+'User Dashboard'!$C$20)^('T&D'!H$4-2022) -> 0.23710439 | I8: =AVERAGE($D19:$F19)*(1+'User Dashboard'!$C$20)^('T&D'!I$4-2022) -> 0.24184647 | J8: =AVERAGE($D19:$F19)*(1+'User Dashboard'!$C$20)^('T&D'!J$4-2022) -> 0.2466834 | K8: =AVERAGE($D19:$F19)*(1+'User Dashboard'!$C$20)^('T&D'!K$4-2022) -> 0.25161707 | L8: =AVERAGE($D19:$F19)*(1+'User Dashboard'!$C$20)^('T&D'!L$4-2022) -> 0.25664941 | M8: =AVERAGE($D19:$F19)*(1+'User Dashboard'!$C$20)^('T&D'!M$4-2022) -> 0.2617824 | N8: =AVERAGE($D19:$F19)*(1+'User Dashboard'!$C$20)^('T&D'!N$4-2022) -> 0.26701805 | ... AJ8: =AVERAGE($D19:$F19)*(1+'User Dashboard'!$C$20)^('T&D'!AJ$4-2022) -> 0.41280447 | AL8: =_xlfn.CONCAT($B$8,"-",C8) -> SoCal Gas-Residential
C9: Commercial | D9: 0.13 | E9: 0.13 | F9: 0.13 | G9: =AVERAGE($D20:$F20)*(1+'User Dashboard'!$C$20)^('T&D'!G$4-2022) -> 0.13526968 | H9: =AVERAGE($D20:$F20)*(1+'User Dashboard'!$C$20)^('T&D'!H$4-2022) -> 0.13797507 | I9: =AVERAGE($D20:$F20)*(1+'User Dashboard'!$C$20)^('T&D'!I$4-2022) -> 0.14073458 | J9: =AVERAGE($D20:$F20)*(1+'User Dashboard'!$C$20)^('T&D'!J$4-2022) -> 0.14354927 | K9: =AVERAGE($D20:$F20)*(1+'User Dashboard'!$C$20)^('T&D'!K$4-2022) -> 0.14642025 | L9: =AVERAGE($D20:$F20)*(1+'User Dashboard'!$C$20)^('T&D'!L$4-2022) -> 0.14934866 | M9: =AVERAGE($D20:$F20)*(1+'User Dashboard'!$C$20)^('T&D'!M$4-2022) -> 0.15233563 | N9: =AVERAGE($D20:$F20)*(1+'User Dashboard'!$C$20)^('T&D'!N$4-2022) -> 0.15538234 | ... AJ9: =AVERAGE($D20:$F20)*(1+'User Dashboard'!$C$20)^('T&D'!AJ$4-2022) -> 0.24021794 | AL9: =_xlfn.CONCAT($B$8,"-",C9) -> SoCal Gas-Commercial
C10: Total Core | D10: 0.19 | E10: 0.19 | F10: 0.19 | G10: =AVERAGE($D21:$F21)*(1+'User Dashboard'!$C$20)^('T&D'!G$4-2022) -> 0.19770184 | H10: =AVERAGE($D21:$F21)*(1+'User Dashboard'!$C$20)^('T&D'!H$4-2022) -> 0.20165588 | I10: =AVERAGE($D21:$F21)*(1+'User Dashboard'!$C$20)^('T&D'!I$4-2022) -> 0.20568899 | J10: =AVERAGE($D21:$F21)*(1+'User Dashboard'!$C$20)^('T&D'!J$4-2022) -> 0.20980277 | K10: =AVERAGE($D21:$F21)*(1+'User Dashboard'!$C$20)^('T&D'!K$4-2022) -> 0.21399883 | L10: =AVERAGE($D21:$F21)*(1+'User Dashboard'!$C$20)^('T&D'!L$4-2022) -> 0.21827881 | M10: =AVERAGE($D21:$F21)*(1+'User Dashboard'!$C$20)^('T&D'!M$4-2022) -> 0.22264438 | N10: =AVERAGE($D21:$F21)*(1+'User Dashboard'!$C$20)^('T&D'!N$4-2022) -> 0.22709727 | ... AJ10: =AVERAGE($D21:$F21)*(1+'User Dashboard'!$C$20)^('T&D'!AJ$4-2022) -> 0.35108776 | AL10: =_xlfn.CONCAT($B$8,"-",C10) -> SoCal Gas-Total Core
B11: SDG&E | C11: Residential | D11: 0.33 | E11: 0.33 | F11: 0.33 | G11: =AVERAGE($D22:$F22)*(1+'User Dashboard'!$C$20)^('T&D'!G$4-2022) -> 0.34337688 | H11: =AVERAGE($D22:$F22)*(1+'User Dashboard'!$C$20)^('T&D'!H$4-2022) -> 0.35024442 | I11: =AVERAGE($D22:$F22)*(1+'User Dashboard'!$C$20)^('T&D'!I$4-2022) -> 0.35724931 | J11: =AVERAGE($D22:$F22)*(1+'User Dashboard'!$C$20)^('T&D'!J$4-2022) -> 0.36439429 | K11: =AVERAGE($D22:$F22)*(1+'User Dashboard'!$C$20)^('T&D'!K$4-2022) -> 0.37168218 | L11: =AVERAGE($D22:$F22)*(1+'User Dashboard'!$C$20)^('T&D'!L$4-2022) -> 0.37911582 | M11: =AVERAGE($D22:$F22)*(1+'User Dashboard'!$C$20)^('T&D'!M$4-2022) -> 0.38669814 | N11: =AVERAGE($D22:$F22)*(1+'User Dashboard'!$C$20)^('T&D'!N$4-2022) -> 0.3944321 | ... AJ11: =AVERAGE($D22:$F22)*(1+'User Dashboard'!$C$20)^('T&D'!AJ$4-2022) -> 0.60978401 | AL11: =_xlfn.CONCAT($B$11,"-",C11) -> SDG&E-Residential
C12: Commercial | D12: 0.2 | E12: 0.2 | F12: 0.2 | G12: =AVERAGE($D23:$F23)*(1+'User Dashboard'!$C$20)^('T&D'!G$4-2022) -> 0.2081072 | H12: =AVERAGE($D23:$F23)*(1+'User Dashboard'!$C$20)^('T&D'!H$4-2022) -> 0.21226934 | I12: =AVERAGE($D23:$F23)*(1+'User Dashboard'!$C$20)^('T&D'!I$4-2022) -> 0.21651473 | J12: =AVERAGE($D23:$F23)*(1+'User Dashboard'!$C$20)^('T&D'!J$4-2022) -> 0.22084503 | K12: =AVERAGE($D23:$F23)*(1+'User Dashboard'!$C$20)^('T&D'!K$4-2022) -> 0.22526193 | L12: =AVERAGE($D23:$F23)*(1+'User Dashboard'!$C$20)^('T&D'!L$4-2022) -> 0.22976716 | M12: =AVERAGE($D23:$F23)*(1+'User Dashboard'!$C$20)^('T&D'!M$4-2022) -> 0.23436251 | N12: =AVERAGE($D23:$F23)*(1+'User Dashboard'!$C$20)^('T&D'!N$4-2022) -> 0.23904976 | ... AJ12: =AVERAGE($D23:$F23)*(1+'User Dashboard'!$C$20)^('T&D'!AJ$4-2022) -> 0.36956607 | AL12: =_xlfn.CONCAT($B$11,"-",C12) -> SDG&E-Commercial
C13: Total Core | D13: 0.27 | E13: 0.27 | F13: 0.27 | G13: =AVERAGE($D24:$F24)*(1+'User Dashboard'!$C$20)^('T&D'!G$4-2022) -> 0.28094472 | H13: =AVERAGE($D24:$F24)*(1+'User Dashboard'!$C$20)^('T&D'!H$4-2022) -> 0.28656361 | I13: =AVERAGE($D24:$F24)*(1+'User Dashboard'!$C$20)^('T&D'!I$4-2022) -> 0.29229489 | J13: =AVERAGE($D24:$F24)*(1+'User Dashboard'!$C$20)^('T&D'!J$4-2022) -> 0.29814078 | K13: =AVERAGE($D24:$F24)*(1+'User Dashboard'!$C$20)^('T&D'!K$4-2022) -> 0.3041036 | L13: =AVERAGE($D24:$F24)*(1+'User Dashboard'!$C$20)^('T&D'!L$4-2022) -> 0.31018567 | M13: =AVERAGE($D24:$F24)*(1+'User Dashboard'!$C$20)^('T&D'!M$4-2022) -> 0.31638939 | N13: =AVERAGE($D24:$F24)*(1+'User Dashboard'!$C$20)^('T&D'!N$4-2022) -> 0.32271717 | ... AJ13: =AVERAGE($D24:$F24)*(1+'User Dashboard'!$C$20)^('T&D'!AJ$4-2022) -> 0.49891419 | AL13: =_xlfn.CONCAT($B$11,"-",C13) -> SDG&E-Total Core
C15: 2022$/Therm | D15: 2022 | E15: =D15+1 -> 2023 | F15: =E15+1 -> 2024
B16: PG&E | C16: Residential | D16: =D5/(1+'User Dashboard'!$C$20)^('T&D'!D$15-2022) -> 0.3825 | E16: =E5/(1+'User Dashboard'!$C$20)^('T&D'!E$15-2022) -> 0.36277451 | F16: =F5/(1+'User Dashboard'!$C$20)^('T&D'!F$15-2022) -> 0.36764706
C17: Commercial | D17: =D6/(1+'User Dashboard'!$C$20)^('T&D'!D$15-2022) -> 0.23276 | E17: =E6/(1+'User Dashboard'!$C$20)^('T&D'!E$15-2022) -> 0.23163431 | F17: =F6/(1+'User Dashboard'!$C$20)^('T&D'!F$15-2022) -> 0.19795271
C18: Total Core | D18: =D7/(1+'User Dashboard'!$C$20)^('T&D'!D$15-2022) -> 0.28163 | E18: =E7/(1+'User Dashboard'!$C$20)^('T&D'!E$15-2022) -> 0.28027255 | F18: =F7/(1+'User Dashboard'!$C$20)^('T&D'!F$15-2022) -> 0.30005767
B19: SoCal Gas | C19: Residential | D19: =D8/(1+'User Dashboard'!$C$20)^('T&D'!D$15-2022) -> 0.23 | E19: =E8/(1+'User Dashboard'!$C$20)^('T&D'!E$15-2022) -> 0.21568627 | F19: =F8/(1+'User Dashboard'!$C$20)^('T&D'!F$15-2022) -> 0.21145713
C20: Commercial | D20: =D9/(1+'User Dashboard'!$C$20)^('T&D'!D$15-2022) -> 0.13 | E20: =E9/(1+'User Dashboard'!$C$20)^('T&D'!E$15-2022) -> 0.12745098 | F20: =F9/(1+'User Dashboard'!$C$20)^('T&D'!F$15-2022) -> 0.12495194
C21: Total Core | D21: =D10/(1+'User Dashboard'!$C$20)^('T&D'!D$15-2022) -> 0.19 | E21: =E10/(1+'User Dashboard'!$C$20)^('T&D'!E$15-2022) -> 0.18627451 | F21: =F10/(1+'User Dashboard'!$C$20)^('T&D'!F$15-2022) -> 0.18262207
B22: SDG&E | C22: Residential | D22: =D11/(1+'User Dashboard'!$C$20)^('T&D'!D$15-2022) -> 0.33 | E22: =E11/(1+'User Dashboard'!$C$20)^('T&D'!E$15-2022) -> 0.32352941 | F22: =F11/(1+'User Dashboard'!$C$20)^('T&D'!F$15-2022) -> 0.3171857
C23: Commercial | D23: =D12/(1+'User Dashboard'!$C$20)^('T&D'!D$15-2022) -> 0.2 | E23: =E12/(1+'User Dashboard'!$C$20)^('T&D'!E$15-2022) -> 0.19607843 | F23: =F12/(1+'User Dashboard'!$C$20)^('T&D'!F$15-2022) -> 0.19223376
C24: Total Core | D24: =D13/(1+'User Dashboard'!$C$20)^('T&D'!D$15-2022) -> 0.27 | E24: =E13/(1+'User Dashboard'!$C$20)^('T&D'!E$15-2022) -> 0.26470588 | F24: =F13/(1+'User Dashboard'!$C$20)^('T&D'!F$15-2022) -> 0.25951557
B27: Gas Transportation Allocation
B28: Natural Gas Customer Shape
C29: PG&E | F29: Socal Gas | I29: SDG&E
C30: Residential | D30: Commercial | E30: Total Core | F30: Residential | G30: Commercial | H30: Total Core | I30: Residential | J30: Commercial | K30: Total Core
B31: January | C31: 0.162 | D31: 0.128 | E31: 0.151 | F31: 0.138 | G31: 0.105 | H31: 0.126 | I31: 0.136 | J31: 0.109 | K31: 0.123
B32: February | C32: 0.133 | D32: 0.113 | E32: 0.127 | F32: 0.121 | G32: 0.099 | H32: 0.112 | I32: 0.119 | J32: 0.102 | K32: 0.11
B33: March | C33: 0.098 | D33: 0.092 | E33: 0.096 | F33: 0.105 | G33: 0.092 | H33: 0.1 | I33: 0.109 | J33: 0.096 | K33: 0.102
B34: April | C34: 0.077 | D34: 0.081 | E34: 0.078 | F34: 0.087 | G34: 0.085 | H34: 0.086 | I34: 0.09 | J34: 0.088 | K34: 0.088
B35: May | C35: 0.056 | D35: 0.069 | E35: 0.061 | F35: 0.063 | G35: 0.074 | H35: 0.067 | I35: 0.067 | J35: 0.075 | K35: 0.071
B36: June | C36: 0.046 | D36: 0.061 | E36: 0.051 | F36: 0.049 | G36: 0.07 | H36: 0.057 | I36: 0.051 | J36: 0.068 | K36: 0.059
B37: July | C37: 0.041 | D37: 0.057 | E37: 0.046 | F37: 0.047 | G37: 0.068 | H37: 0.055 | I37: 0.049 | J37: 0.066 | K37: 0.057
B38: August | C38: 0.04 | D38: 0.059 | E38: 0.046 | F38: 0.047 | G38: 0.068 | H38: 0.055 | I38: 0.048 | J38: 0.065 | K38: 0.057
B39: September | C39: 0.043 | D39: 0.062 | E39: 0.049 | F39: 0.047 | G39: 0.069 | H39: 0.055 | I39: 0.047 | J39: 0.065 | K39: 0.056
B40: October | C40: 0.052 | D40: 0.068 | E40: 0.057 | F40: 0.058 | G40: 0.074 | H40: 0.064 | I40: 0.057 | J40: 0.069 | K40: 0.063
B41: November | C41: 0.098 | D41: 0.091 | E41: 0.096 | F41: 0.092 | G41: 0.088 | H41: 0.091 | I41: 0.089 | J41: 0.086 | K41: 0.088
B42: December | C42: 0.154 | D42: 0.119 | E42: 0.142 | F42: 0.145 | G42: 0.107 | H42: 0.132 | I42: 0.139 | J42: 0.11 | K42: 0.126
B45: Winter Throughput | C45: =SUM(C41:C42,C31:C33) -> 0.645 | D45: =SUM(D41:D42,D31:D33) -> 0.543 | E45: =SUM(E41:E42,E31:E33) -> 0.612 | F45: =SUM(F41:F42,F31:F33) -> 0.601 | G45: =SUM(G41:G42,G31:G33) -> 0.491 | H45: =SUM(H41:H42,H31:H33) -> 0.561 | I45: =SUM(I41:I42,I31:I33) -> 0.592 | J45: =SUM(J41:J42,J31:J33) -> 0.503 | K45: =SUM(K41:K42,K31:K33) -> 0.549
B46: Summer | C46: =1-C45 -> 0.355 | D46: =1-D45 -> 0.457 | E46: =1-E45 -> 0.388 | F46: =1-F45 -> 0.399 | G46: =1-G45 -> 0.509 | H46: =1-H45 -> 0.439 | I46: =1-I45 -> 0.408 | J46: =1-J45 -> 0.497 | K46: =1-K45 -> 0.451
B48: Winter Allocation | C48: 1 | D48: 1 | E48: 1 | F48: 1 | G48: 1 | H48: 1 | I48: 1 | J48: 1 | K48: 1
B49: Summer Allocation | C49: =1-C48 -> 0 | D49: =1-D48 -> 0 | E49: =1-E48 -> 0 | F49: =1-F48 -> 0 | G49: =1-G48 -> 0 | H49: =1-H48 -> 0 | I49: =1-I48 -> 0 | J49: =1-J48 -> 0 | K49: =1-K48 -> 0
B51: Winter Allocation | C51: =C48/C45 -> 1.5503876 | D51: =D48/D45 -> 1.8416206 | E51: =E48/E45 -> 1.6339869 | F51: =F48/F45 -> 1.6638935 | G51: =G48/G45 -> 2.0366599 | H51: =H48/H45 -> 1.7825312 | I51: =I48/I45 -> 1.6891892 | J51: =J48/J45 -> 1.9880716 | K51: =K48/K45 -> 1.8214936
B52: Summer Allocation | C52: =C49/C46 -> 0 | D52: =D49/D46 -> 0 | E52: =E49/E46 -> 0 | F52: =F49/F46 -> 0 | G52: =G49/G46 -> 0 | H52: =H49/H46 -> 0 | I52: =I49/I46 -> 0 | J52: =J49/J46 -> 0 | K52: =K49/K46 -> 0
B54: Monthly allocation of annual average gas T&D cost per therm
B55: January | C55: =C$51 -> 1.5503876 | D55: =D$51 -> 1.8416206 | E55: =E$51 -> 1.6339869 | F55: =F$51 -> 1.6638935 | G55: =G$51 -> 2.0366599 | H55: =H$51 -> 1.7825312 | I55: =I$51 -> 1.6891892 | J55: =J$51 -> 1.9880716 | K55: =K$51 -> 1.8214936
B56: February | C56: =C$51 -> 1.5503876 | D56: =D$51 -> 1.8416206 | E56: =E$51 -> 1.6339869 | F56: =F$51 -> 1.6638935 | G56: =G$51 -> 2.0366599 | H56: =H$51 -> 1.7825312 | I56: =I$51 -> 1.6891892 | J56: =J$51 -> 1.9880716 | K56: =K$51 -> 1.8214936
B57: March | C57: =C$51 -> 1.5503876 | D57: =D$51 -> 1.8416206 | E57: =E$51 -> 1.6339869 | F57: =F$51 -> 1.6638935 | G57: =G$51 -> 2.0366599 | H57: =H$51 -> 1.7825312 | I57: =I$51 -> 1.6891892 | J57: =J$51 -> 1.9880716 | K57: =K$51 -> 1.8214936
B58: April | C58: =C$52 -> 0 | D58: =D$52 -> 0 | E58: =E$52 -> 0 | F58: =F$52 -> 0 | G58: =G$52 -> 0 | H58: =H$52 -> 0 | I58: =I$52 -> 0 | J58: =J$52 -> 0 | K58: =K$52 -> 0
B59: May | C59: =C$52 -> 0 | D59: =D$52 -> 0 | E59: =E$52 -> 0 | F59: =F$52 -> 0 | G59: =G$52 -> 0 | H59: =H$52 -> 0 | I59: =I$52 -> 0 | J59: =J$52 -> 0 | K59: =K$52 -> 0
B60: June | C60: =C$52 -> 0 | D60: =D$52 -> 0 | E60: =E$52 -> 0 | F60: =F$52 -> 0 | G60: =G$52 -> 0 | H60: =H$52 -> 0 | I60: =I$52 -> 0 | J60: =J$52 -> 0 | K60: =K$52 -> 0
B61: July | C61: =C$52 -> 0 | D61: =D$52 -> 0 | E61: =E$52 -> 0 | F61: =F$52 -> 0 | G61: =G$52 -> 0 | H61: =H$52 -> 0 | I61: =I$52 -> 0 | J61: =J$52 -> 0 | K61: =K$52 -> 0
B62: August | C62: =C$52 -> 0 | D62: =D$52 -> 0 | E62: =E$52 -> 0 | F62: =F$52 -> 0 | G62: =G$52 -> 0 | H62: =H$52 -> 0 | I62: =I$52 -> 0 | J62: =J$52 -> 0 | K62: =K$52 -> 0
B63: September | C63: =C$52 -> 0 | D63: =D$52 -> 0 | E63: =E$52 -> 0 | F63: =F$52 -> 0 | G63: =G$52 -> 0 | H63: =H$52 -> 0 | I63: =I$52 -> 0 | J63: =J$52 -> 0 | K63: =K$52 -> 0
B64: October | C64: =C$52 -> 0 | D64: =D$52 -> 0 | E64: =E$52 -> 0 | F64: =F$52 -> 0 | G64: =G$52 -> 0 | H64: =H$52 -> 0 | I64: =I$52 -> 0 | J64: =J$52 -> 0 | K64: =K$52 -> 0
B65: November | C65: =C$51 -> 1.5503876 | D65: =D$51 -> 1.8416206 | E65: =E$51 -> 1.6339869 | F65: =F$51 -> 1.6638935 | G65: =G$51 -> 2.0366599 | H65: =H$51 -> 1.7825312 | I65: =I$51 -> 1.6891892 | J65: =J$51 -> 1.9880716 | K65: =K$51 -> 1.8214936
B66: December | C66: =C$51 -> 1.5503876 | D66: =D$51 -> 1.8416206 | E66: =E$51 -> 1.6339869 | F66: =F$51 -> 1.6638935 | G66: =G$51 -> 2.0366599 | H66: =H$51 -> 1.7825312 | I66: =I$51 -> 1.6891892 | J66: =J$51 -> 1.9880716 | K66: =K$51 -> 1.8214936
B68: Key | C68: =_xlfn.CONCAT($C$29,"-",C30) -> PG&E-Residential | D68: =_xlfn.CONCAT($C$29,"-",D30) -> PG&E-Commercial | E68: =_xlfn.CONCAT($C$29,"-",E30) -> PG&E-Total Core | F68: =_xlfn.CONCAT($F$29,"-",F30) -> Socal Gas-Residential | G68: =_xlfn.CONCAT($F$29,"-",G30) -> Socal Gas-Commercial | H68: =_xlfn.CONCAT($F$29,"-",H30) -> Socal Gas-Total Core | I68: =_xlfn.CONCAT($I$29,"-",I30) -> SDG&E-Residential | J68: =_xlfn.CONCAT($I$29,"-",J30) -> SDG&E-Commercial | K68: =_xlfn.CONCAT($I$29,"-",K30) -> SDG&E-Total Core

Sheet Methane Leakage
B2: Methane leakage adders | C2: Selected Adder at Specified GWP time horizon | D2: Upstream - In-State | E2: Upstream - National Average
B3: Variable | D3: used in TRC | E3: used in SCT | F3: Note
B4: Upstream methane leakage adder | C4: =IF('User Dashboard'!$C$10="TRC",'Methane Leakage'!D4,'Methane Leakage'!E4)*$C$16/$C$14 -> 0.0557 | D4: =D5*$C$21 -> 0.0557 | E4: =E5*$C$21 -> 0.20985401 | F4: Methane leakage upstream of natural gas power plants. Also applies to programs that change natural gas consumption only. Methane leakage avoided cost is this percentage times the value of GHG emissions
B5: Upstream methane leakage rate | C5: =IF('User Dashboard'!$C$10="TRC",'Methane Leakage'!D5,'Methane Leakage'!E5) -> 0.00610472 | D5: 0.00610472 | E5: 0.023
B7: Residential behind-the-meter methane leakage adder | C7: =C8*C21 -> 0.037864964 | F7: Applies only to programs that eliminate natural gas appliances from a residential building.
B8: Residential behind-the-meter methane leakage rate | C8: 0.00415
B11: Active GWP time horizon | C11: 100-yr | D11: Choose from dropdown (100-yr default)
B13: Methane leakage GWPs (AR4)
B14: 100-yr | C14: 25
B15: 20-yr | C15: 72
B16: Active GWP | C16: =INDEX(C14:C15,MATCH(C11,B14:B15,0)) -> 25
B18: Methane leakage rate conversion
B19: Methane GWP if Leaked | C19: 25
B20: Difference in molar mass between CH4 and CO2 | C20: 2.74
B21: Methane leakage rate to adder conversion | C21: =C19/C20 -> 9.1240876

Sheet Other Inputs
B2: Compression Factor and Loss Input
C4: PG&E | D4: SoCal Gas | E4: SDG&E
B5: Compression Factor | C5: 0 | D5: 0.0039 | E5: 0.004
B6: Loss and Unaccounted | C6: 0.0241 | D6: 0.0137 | E6: 0.01
B7: * PG&E LUAF figure includes both LUAF and compression
B9: IRP Inputs
B11: Inflation | C11: 0.02
B12: PG&E | C12: 0 | D12: 0.0727
B13: SoCalGas | C13: 0 | D13: 0.071
B14: SDG&E | C14: 0 | D14: 0.0718
C16: TRC | D16: SCT
B17: Real Discount Rate | D17: 0.03
B18: Nominal Discount Rate | C18: =AVERAGE(C12:C14) -> 0 | D18: =(1+C11)*(1+D17)-1 -> 0.0506
B20: Unit Conversion
B22: Therms / MMBtu | C22: 10

Sheet AGIC
B2: Measure Inputs
B4: Program Year | C4: 2021
B5: Inflation Rate | C5: ='User Dashboard'!$C$20 -> 0.02
B7: Project Name | C7: Utility | D7: Subdivision/Development | E7: Building Type | F7: Avoided Mainline Extension (ft) | G7: Avoided Number of Services | H7: Avoided Number of Meters
B8: Example_Project_Name_PGE | C8: PG&E | D8: New Greenfield | E8: Residential Single Family | F8: 1 | G8: 1 | H8: 1
B9: Example_Project_Name_SCG | C9: Socal Gas | D9: New Greenfield | E9: Residential Single Family | F9: 1 | G9: 1 | H9: 1
B10: Example_Project_Name_SDGE | C10: SDG&E | D10: New Greenfield | E10: Residential Single Family | F10: 1 | G10: 1 | H10: 1
B20: Measure Results
B22: Project Name | C22: ="Total Avoided Mainline Extension Costs ($" &$C$4 & ")" -> Total Avoided Mainline Extension Costs ($2021) | D22: ="Total Avoided Service Extension Costs ($" &$C$4 & ")" -> Total Avoided Service Extension Costs ($2021) | E22: ="Total Avoided Meter Costs ($" &$C$4 & ")" -> Total Avoided Meter Costs ($2021) | F22: ="Total Avoided Gas Infrastructure Costs ($" &$C$4 & ")" -> Total Avoided Gas Infrastructure Costs ($2021) | G22: Input Dollar Year
B23: =IF(B8="", "", B8) -> Example_Project_Name_PGE | C23: {=IFERROR(INDEX($D$41:$F$44, MATCH(1, ($D8 = $B$41:$B$44)*($E8=$C$41:$C$44), 0), MATCH($C8, $D$40:$F$40, 0))*(1+$C$5)^($C$4-$G23), 0)*$F8} -> 21.42 | D23: =IFERROR(INDEX($D$49:$F$50, MATCH($D8, $B$49:$B$50, 0), MATCH($C8, $D$48:$F$48, 0)) *(1+$C$5)^($C$4-$G23), 0)*$G8 -> 848.64 | E23: {=IFERROR(INDEX($D$55:$F$62, MATCH(1, ($D8 = $B$55:$B$62)*($E8=$C$55:$C$62), 0), MATCH($C8, $D$54:$F$54, 0))*(1+$C$5)^($C$4-$G23), 0)*$H8} -> 588.54 | F23: =SUM($C23:$E23) -> 1458.6 | G23: =IFERROR(INDEX($D$37:$F$37, MATCH($C8, $D$40:$F$40, 0)), "") -> 2020
B24: =IF(B9="", "", B9) -> Example_Project_Name_SCG | C24: {=IFERROR(INDEX($D$41:$F$44, MATCH(1, ($D9 = $B$41:$B$44)*($E9=$C$41:$C$44), 0), MATCH($C9, $D$40:$F$40, 0))*(1+$C$5)^($C$4-$G24), 0)*$F9} -> 30.82 | D24: =IFERROR(INDEX($D$49:$F$50, MATCH($D9, $B$49:$B$50, 0), MATCH($C9, $D$48:$F$48, 0)) *(1+$C$5)^($C$4-$G24), 0)*$G9 -> 7620 | E24: {=IFERROR(INDEX($D$55:$F$62, MATCH(1, ($D9 = $B$55:$B$62)*($E9=$C$55:$C$62), 0), MATCH($C9, $D$54:$F$54, 0))*(1+$C$5)^($C$4-$G24), 0)*$H9} -> 489 | F24: =SUM($C24:$E24) -> 8139.82 | G24: =IFERROR(INDEX($D$37:$F$37, MATCH($C9, $D$40:$F$40, 0)), "") -> 2021
B25: =IF(B10="", "", B10) -> Example_Project_Name_SDGE | C25: {=IFERROR(INDEX($D$41:$F$44, MATCH(1, ($D10 = $B$41:$B$44)*($E10=$C$41:$C$44), 0), MATCH($C10, $D$40:$F$40, 0))*(1+$C$5)^($C$4-$G25), 0)*$F10} -> 38.69 | D25: =IFERROR(INDEX($D$49:$F$50, MATCH($D10, $B$49:$B$50, 0), MATCH($C10, $D$48:$F$48, 0)) *(1+$C$5)^($C$4-$G25), 0)*$G10 -> 3163.3761 | E25: {=IFERROR(INDEX($D$55:$F$62, MATCH(1, ($D10 = $B$55:$B$62)*($E10=$C$55:$C$62), 0), MATCH($C10, $D$54:$F$54, 0))*(1+$C$5)^($C$4-$G25), 0)*$H10} -> 264.79258 | F25: =SUM($C25:$E25) -> 3466.8587 | G25: =IFERROR(INDEX($D$37:$F$37, MATCH($C10, $D$40:$F$40, 0)), "") -> 2024
B26: =IF(B11="", "", B11) | C26: {=IFERROR(INDEX($D$41:$F$44, MATCH(1, ($D11 = $B$41:$B$44)*($E11=$C$41:$C$44), 0), MATCH($C11, $D$40:$F$40, 0))*(1+$C$5)^($C$4-$G26), 0)*$F11} -> 0 | D26: =IFERROR(INDEX($D$49:$F$50, MATCH($D11, $B$49:$B$50, 0), MATCH($C11, $D$48:$F$48, 0)) *(1+$C$5)^($C$4-$G26), 0)*$G11 -> 0 | E26: {=IFERROR(INDEX($D$55:$F$62, MATCH(1, ($D11 = $B$55:$B$62)*($E11=$C$55:$C$62), 0), MATCH($C11, $D$54:$F$54, 0))*(1+$C$5)^($C$4-$G26), 0)*$H11} -> 0 | F26: =SUM($C26:$E26) -> 0 | G26: =IFERROR(INDEX($D$37:$F$37, MATCH($C11, $D$40:$F$40, 0)), "")
B27: =IF(B12="", "", B12) | C27: {=IFERROR(INDEX($D$41:$F$44, MATCH(1, ($D12 = $B$41:$B$44)*($E12=$C$41:$C$44), 0), MATCH($C12, $D$40:$F$40, 0))*(1+$C$5)^($C$4-$G27), 0)*$F12} -> 0 | D27: =IFERROR(INDEX($D$49:$F$50, MATCH($D12, $B$49:$B$50, 0), MATCH($C12, $D$48:$F$48, 0)) *(1+$C$5)^($C$4-$G27), 0)*$G12 -> 0 | E27: {=IFERROR(INDEX($D$55:$F$62, MATCH(1, ($D12 = $B$55:$B$62)*($E12=$C$55:$C$62), 0), MATCH($C12, $D$54:$F$54, 0))*(1+$C$5)^($C$4-$G27), 0)*$H12} -> 0 | F27: =SUM($C27:$E27) -> 0 | G27: =IFERROR(INDEX($D$37:$F$37, MATCH($C12, $D$40:$F$40, 0)), "")
B28: =IF(B13="", "", B13) | C28: {=IFERROR(INDEX($D$41:$F$44, MATCH(1, ($D13 = $B$41:$B$44)*($E13=$C$41:$C$44), 0), MATCH($C13, $D$40:$F$40, 0))*(1+$C$5)^($C$4-$G28), 0)*$F13} -> 0 | D28: =IFERROR(INDEX($D$49:$F$50, MATCH($D13, $B$49:$B$50, 0), MATCH($C13, $D$48:$F$48, 0)) *(1+$C$5)^($C$4-$G28), 0)*$G13 -> 0 | E28: {=IFERROR(INDEX($D$55:$F$62, MATCH(1, ($D13 = $B$55:$B$62)*($E13=$C$55:$C$62), 0), MATCH($C13, $D$54:$F$54, 0))*(1+$C$5)^($C$4-$G28), 0)*$H13} -> 0 | F28: =SUM($C28:$E28) -> 0 | G28: =IFERROR(INDEX($D$37:$F$37, MATCH($C13, $D$40:$F$40, 0)), "")
B29: =IF(B14="", "", B14) | C29: {=IFERROR(INDEX($D$41:$F$44, MATCH(1, ($D14 = $B$41:$B$44)*($E14=$C$41:$C$44), 0), MATCH($C14, $D$40:$F$40, 0))*(1+$C$5)^($C$4-$G29), 0)*$F14} -> 0 | D29: =IFERROR(INDEX($D$49:$F$50, MATCH($D14, $B$49:$B$50, 0), MATCH($C14, $D$48:$F$48, 0)) *(1+$C$5)^($C$4-$G29), 0)*$G14 -> 0 | E29: {=IFERROR(INDEX($D$55:$F$62, MATCH(1, ($D14 = $B$55:$B$62)*($E14=$C$55:$C$62), 0), MATCH($C14, $D$54:$F$54, 0))*(1+$C$5)^($C$4-$G29), 0)*$H14} -> 0 | F29: =SUM($C29:$E29) -> 0 | G29: =IFERROR(INDEX($D$37:$F$37, MATCH($C14, $D$40:$F$40, 0)), "")
B30: =IF(B15="", "", B15) | C30: {=IFERROR(INDEX($D$41:$F$44, MATCH(1, ($D15 = $B$41:$B$44)*($E15=$C$41:$C$44), 0), MATCH($C15, $D$40:$F$40, 0))*(1+$C$5)^($C$4-$G30), 0)*$F15} -> 0 | D30: =IFERROR(INDEX($D$49:$F$50, MATCH($D15, $B$49:$B$50, 0), MATCH($C15, $D$48:$F$48, 0)) *(1+$C$5)^($C$4-$G30), 0)*$G15 -> 0 | E30: {=IFERROR(INDEX($D$55:$F$62, MATCH(1, ($D15 = $B$55:$B$62)*($E15=$C$55:$C$62), 0), MATCH($C15, $D$54:$F$54, 0))*(1+$C$5)^($C$4-$G30), 0)*$H15} -> 0 | F30: =SUM($C30:$E30) -> 0 | G30: =IFERROR(INDEX($D$37:$F$37, MATCH($C15, $D$40:$F$40, 0)), "")
B31: =IF(B16="", "", B16) | C31: {=IFERROR(INDEX($D$41:$F$44, MATCH(1, ($D16 = $B$41:$B$44)*($E16=$C$41:$C$44), 0), MATCH($C16, $D$40:$F$40, 0))*(1+$C$5)^($C$4-$G31), 0)*$F16} -> 0 | D31: =IFERROR(INDEX($D$49:$F$50, MATCH($D16, $B$49:$B$50, 0), MATCH($C16, $D$48:$F$48, 0)) *(1+$C$5)^($C$4-$G31), 0)*$G16 -> 0 | E31: {=IFERROR(INDEX($D$55:$F$62, MATCH(1, ($D16 = $B$55:$B$62)*($E16=$C$55:$C$62), 0), MATCH($C16, $D$54:$F$54, 0))*(1+$C$5)^($C$4-$G31), 0)*$H16} -> 0 | F31: =SUM($C31:$E31) -> 0 | G31: =IFERROR(INDEX($D$37:$F$37, MATCH($C16, $D$40:$F$40, 0)), "")
B32: =IF(B17="", "", B17) | C32: {=IFERROR(INDEX($D$41:$F$44, MATCH(1, ($D17 = $B$41:$B$44)*($E17=$C$41:$C$44), 0), MATCH($C17, $D$40:$F$40, 0))*(1+$C$5)^($C$4-$G32), 0)*$F17} -> 0 | D32: =IFERROR(INDEX($D$49:$F$50, MATCH($D17, $B$49:$B$50, 0), MATCH($C17, $D$48:$F$48, 0)) *(1+$C$5)^($C$4-$G32), 0)*$G17 -> 0 | E32: {=IFERROR(INDEX($D$55:$F$62, MATCH(1, ($D17 = $B$55:$B$62)*($E17=$C$55:$C$62), 0), MATCH($C17, $D$54:$F$54, 0))*(1+$C$5)^($C$4-$G32), 0)*$H17} -> 0 | F32: =SUM($C32:$E32) -> 0 | G32: =IFERROR(INDEX($D$37:$F$37, MATCH($C17, $D$40:$F$40, 0)), "")
B35: Assumptions
B37: Input Dollar Year | D37: 2020 | E37: 2021 | F37: 2024
B39: Mainline Extension ($/ft)
B40: Subdivision | C40: Building Type | D40: PG&E | E40: Socal Gas | F40: SDG&E
B41: New Greenfield | C41: Residential Single Family | D41: 21 | E41: 30.82 | F41: =38.69*(1.02)^($F$37-2021) -> 41.058138
B42: New Greenfield | C42: Residential Multi-Family | D42: 22 | E42: 30.82 | F42: =38.69*(1.02)^($F$37-2021) -> 41.058138
B43: New Greenfield | C43: Small/Medium Commercial | D43: 46 | E43: 30.82 | F43: =38.69*(1.02)^($F$37-2021) -> 41.058138
B44: New Greenfield | C44: Large Commercial | D44: 46 | E44: 30.82 | F44: =38.69*(1.02)^($F$37-2021) -> 41.058138
B46: Service Extension ($/service or building)
B47: * Excluding trenching costs
B48: Subdivision | D48: PG&E | E48: Socal Gas | F48: SDG&E
B49: Existing | D49: 3615 | E49: 7620 | F49: 3357
B50: New Greenfield | D50: 832 | E50: 7620 | F50: 3357
B52: Meter ($/meter)
B54: Subdivision | C54: Building Type | D54: PG&E | E54: Socal Gas | F54: SDG&E
B55: Existing | C55: Residential Single Family | D55: 468 | E55: 489 | F55: 281
B56: Existing | C56: Residential Multi-Family | D56: 445 | E56: 330 | F56: 281
B57: Existing | C57: Small/Medium Commercial | D57: 1384 | E57: 330 | F57: 281
B58: Existing | C58: Large Commercial | D58: 1384 | E58: 13184 | F58: 8012
B59: New Greenfield | C59: Residential Single Family | D59: 577 | E59: 489 | F59: 281
B60: New Greenfield | C60: Residential Multi-Family | D60: 559 | E60: 330 | F60: 281
B61: New Greenfield | C61: Small/Medium Commercial | D61: 605 | E61: 330 | F61: 281
B62: New Greenfield | C62: Large Commercial | D62: 605 | E62: 13184 | F62: 8012

Sheet IEPR Gas Prices Nominal
B2: Gas Price Forecast (Nominal $/MMBtu)
F4: PG&E BB (Hub PG&E) | G4: PG&E BB (Hub PG&E) | I4: PG&E Citygate | J4: PG&E LT (Hub PG&E) | L4: SoCalGas (Hub SoCalGas) | P4: Average PG&E/SoCalGas | Q4: Average PG&E/SoCalGas, including Transportation
B5: Year | C5: Month | D5: Date | E5: Month-Year | F5: Monthly gas price | G5: Transportation rate | H5: Burnertip price | I5: Monthly gas price | J5: Transportation rate | K5: Burnertip price | L5: Monthly gas price | M5: Transportation rate | N5: Burnertip price | S5: Commodity Price | T5: ='User Dashboard'!E$58 -> 2023 | U5: ='User Dashboard'!F$58 -> 2024 | V5: ='User Dashboard'!G$58 -> 2025 | W5: ='User Dashboard'!H$58 -> 2026 | X5: ='User Dashboard'!I$58 -> 2027 | Y5: ='User Dashboard'!J$58 -> 2028 | Z5: ='User Dashboard'!K$58 -> 2029 | AA5: ='User Dashboard'!L$58 -> 2030 | ... AY5: ='User Dashboard'!AJ$58 -> 2054
B6: =YEAR(D6) -> 2022 | C6: =MONTH(D6) -> 1 | D6: 44562 | E6: =C6&"-"&B6 -> 1-2022 | F6: ='IEPR Gas Prices Real'!F6*(INDEX('GDP Deflator'!$C$5:$C$89,MATCH('IEPR Gas Prices Nominal'!$B6,'GDP Deflator'!$B$5:$B$89,0))/100) -> 7.1456828 | G6: ='IEPR Gas Prices Real'!G6*(INDEX('GDP Deflator'!$C$5:$C$89,MATCH('IEPR Gas Prices Nominal'!$B6,'GDP Deflator'!$B$5:$B$89,0))/100) -> 0.88808089 | H6: ='IEPR Gas Prices Real'!H6*(INDEX('GDP Deflator'!$C$5:$C$89,MATCH('IEPR Gas Prices Nominal'!$B6,'GDP Deflator'!$B$5:$B$89,0))/100) -> 8.0337637 | I6: ='IEPR Gas Prices Real'!I6*(INDEX('GDP Deflator'!$C$5:$C$89,MATCH('IEPR Gas Prices Nominal'!$B6,'GDP Deflator'!$B$5:$B$89,0))/100) -> 7.690506 | J6: ='IEPR Gas Prices Real'!J6*(INDEX('GDP Deflator'!$C$5:$C$89,MATCH('IEPR Gas Prices Nominal'!$B6,'GDP Deflator'!$B$5:$B$89,0))/100) -> 1.4664363 | K6: ='IEPR Gas Prices Real'!K6*(INDEX('GDP Deflator'!$C$5:$C$89,MATCH('IEPR Gas Prices Nominal'!$B6,'GDP Deflator'!$B$5:$B$89,0))/100) -> 9.1569423 | L6: ='IEPR Gas Prices Real'!L6*(INDEX('GDP Deflator'!$C$5:$C$89,MATCH('IEPR Gas Prices Nominal'!$B6,'GDP Deflator'!$B$5:$B$89,0))/100) -> 7.6634408 | M6: ='IEPR Gas Prices Real'!M6*(INDEX('GDP Deflator'!$C$5:$C$89,MATCH('IEPR Gas Prices Nominal'!$B6,'GDP Deflator'!$B$5:$B$89,0))/100) -> 0.69253054 | N6: ='IEPR Gas Prices Real'!N6*(INDEX('GDP Deflator'!$C$5:$C$89,MATCH('IEPR Gas Prices Nominal'!$B6,'GDP Deflator'!$B$5:$B$89,0))/100) -> 8.3559713 | P6: =AVERAGE(F6,I6,L6) -> 7.4998765 | Q6: =AVERAGE(H6,K6,N6) -> 8.5155591 | S6: 1 | T6: =INDEX($P$6:$P$401,MATCH(_xlfn.CONCAT($S6,"-",T$5),$E$6:$E$401,0)) -> 5.8063148 | U6: =INDEX($P$6:$P$401,MATCH(_xlfn.CONCAT($S6,"-",U$5),$E$6:$E$401,0)) -> 5.7880168 | V6: =INDEX($P$6:$P$401,MATCH(_xlfn.CONCAT($S6,"-",V$5),$E$6:$E$401,0)) -> 5.9385103 | W6: =INDEX($P$6:$P$401,MATCH(_xlfn.CONCAT($S6,"-",W$5),$E$6:$E$401,0)) -> 6.0746326 | X6: =INDEX($P$6:$P$401,MATCH(_xlfn.CONCAT($S6,"-",X$5),$E$6:$E$401,0)) -> 6.1995546 | Y6: =INDEX($P$6:$P$401,MATCH(_xlfn.CONCAT($S6,"-",Y$5),$E$6:$E$401,0)) -> 6.3245975 | Z6: =INDEX($P$6:$P$401,MATCH(_xlfn.CONCAT($S6,"-",Z$5),$E$6:$E$401,0)) -> 6.4528316 | AA6: =INDEX($P$6:$P$401,MATCH(_xlfn.CONCAT($S6,"-",AA$5),$E$6:$E$401,0)) -> 6.5841668 | ... AY6: =INDEX($P$6:$P$401,MATCH(_xlfn.CONCAT($S6,"-",AY$5),$E$6:$E$401,0)) -> 10.930327
B7: =YEAR(D7) -> 2022 | C7: =MONTH(D7) -> 2 | D7: 44593 | E7: =C7&"-"&B7 -> 2-2022 | F7: ='IEPR Gas Prices Real'!F7*(INDEX('GDP Deflator'!$C$5:$C$89,MATCH('IEPR Gas Prices Nominal'!$B7,'GDP Deflator'!$B$5:$B$89,0))/100) -> 6.9893046 | G7: ='IEPR Gas Prices Real'!G7*(INDEX('GDP Deflator'!$C$5:$C$89,MATCH('IEPR Gas Prices Nominal'!$B7,'GDP Deflator'!$B$5:$B$89,0))/100) -> 0.88808089 | H7: ='IEPR Gas Prices Real'!H7*(INDEX('GDP Deflator'!$C$5:$C$89,MATCH('IEPR Gas Prices Nominal'!$B7,'GDP Deflator'!$B$5:$B$89,0))/100) -> 7.8773855 | I7: ='IEPR Gas Prices Real'!I7*(INDEX('GDP Deflator'!$C$5:$C$89,MATCH('IEPR Gas Prices Nominal'!$B7,'GDP Deflator'!$B$5:$B$89,0))/100) -> 7.5222047 | J7: ='IEPR Gas Prices Real'!J7*(INDEX('GDP Deflator'!$C$5:$C$89,MATCH('IEPR Gas Prices Nominal'!$B7,'GDP Deflator'!$B$5:$B$89,0))/100) -> 1.4664363 | K7: ='IEPR Gas Prices Real'!K7*(INDEX('GDP Deflator'!$C$5:$C$89,MATCH('IEPR Gas Prices Nominal'!$B7,'GDP Deflator'!$B$5:$B$89,0))/100) -> 8.988641 | L7: ='IEPR Gas Prices Real'!L7*(INDEX('GDP Deflator'!$C$5:$C$89,MATCH('IEPR Gas Prices Nominal'!$B7,'GDP Deflator'!$B$5:$B$89,0))/100) -> 7.4957318 | M7: ='IEPR Gas Prices Real'!M7*(INDEX('GDP Deflator'!$C$5:$C$89,MATCH('IEPR Gas Prices Nominal'!$B7,'GDP Deflator'!$B$5:$B$89,0))/100) -> 0.69253054 | N7: ='IEPR Gas Prices Real'!N7*(INDEX('GDP Deflator'!$C$5:$C$89,MATCH('IEPR Gas Prices Nominal'!$B7,'GDP Deflator'!$B$5:$B$89,0))/100) -> 8.1882623 | P7: =AVERAGE(F7,I7,L7) -> 7.335747 | Q7: =AVERAGE(H7,K7,N7) -> 8.3514296 | S7: 2 | T7: =INDEX($P$6:$P$401,MATCH(_xlfn.CONCAT($S7,"-",T$5),$E$6:$E$401,0)) -> 5.6657735 | U7: =INDEX($P$6:$P$401,MATCH(_xlfn.CONCAT($S7,"-",U$5),$E$6:$E$401,0)) -> 5.66267 | V7: =INDEX($P$6:$P$401,MATCH(_xlfn.CONCAT($S7,"-",V$5),$E$6:$E$401,0)) -> 5.8084916 | W7: =INDEX($P$6:$P$401,MATCH(_xlfn.CONCAT($S7,"-",W$5),$E$6:$E$401,0)) -> 5.9412448 | X7: =INDEX($P$6:$P$401,MATCH(_xlfn.CONCAT($S7,"-",X$5),$E$6:$E$401,0)) -> 6.0633526 | Y7: =INDEX($P$6:$P$401,MATCH(_xlfn.CONCAT($S7,"-",Y$5),$E$6:$E$401,0)) -> 6.1857897 | Z7: =INDEX($P$6:$P$401,MATCH(_xlfn.CONCAT($S7,"-",Z$5),$E$6:$E$401,0)) -> 6.3112829 | AA7: =INDEX($P$6:$P$401,MATCH(_xlfn.CONCAT($S7,"-",AA$5),$E$6:$E$401,0)) -> 6.4396653 | ... AY7: =INDEX($P$6:$P$401,MATCH(_xlfn.CONCAT($S7,"-",AY$5),$E$6:$E$401,0)) -> 10.690843
B8: =YEAR(D8) -> 2022 | C8: =MONTH(D8) -> 3 | D8: 44621 | E8: =C8&"-"&B8 -> 3-2022 | F8: ='IEPR Gas Prices Real'!F8*(INDEX('GDP Deflator'!$C$5:$C$89,MATCH('IEPR Gas Prices Nominal'!$B8,'GDP Deflator'!$B$5:$B$89,0))/100) -> 6.4164671 | G8: ='IEPR Gas Prices Real'!G8*(INDEX('GDP Deflator'!$C$5:$C$89,MATCH('IEPR Gas Prices Nominal'!$B8,'GDP Deflator'!$B$5:$B$89,0))/100) -> 0.88808089 | H8: ='IEPR Gas Prices Real'!H8*(INDEX('GDP Deflator'!$C$5:$C$89,MATCH('IEPR Gas Prices Nominal'!$B8,'GDP Deflator'!$B$5:$B$89,0))/100) -> 7.304548 | I8: ='IEPR Gas Prices Real'!I8*(INDEX('GDP Deflator'!$C$5:$C$89,MATCH('IEPR Gas Prices Nominal'!$B8,'GDP Deflator'!$B$5:$B$89,0))/100) -> 6.9056912 | J8: ='IEPR Gas Prices Real'!J8*(INDEX('GDP Deflator'!$C$5:$C$89,MATCH('IEPR Gas Prices Nominal'!$B8,'GDP Deflator'!$B$5:$B$89,0))/100) -> 1.4664363 | K8: ='IEPR Gas Prices Real'!K8*(INDEX('GDP Deflator'!$C$5:$C$89,MATCH('IEPR Gas Prices Nominal'!$B8,'GDP Deflator'!$B$5:$B$89,0))/100) -> 8.3721275 | L8: ='IEPR Gas Prices Real'!L8*(INDEX('GDP Deflator'!$C$5:$C$89,MATCH('IEPR Gas Prices Nominal'!$B8,'GDP Deflator'!$B$5:$B$89,0))/100) -> 6.881388 | M8: ='IEPR Gas Prices Real'!M8*(INDEX('GDP Deflator'!$C$5:$C$89,MATCH('IEPR Gas Prices Nominal'!$B8,'GDP Deflator'!$B$5:$B$89,0))/100) -> 0.69253054 | N8: ='IEPR Gas Prices Real'!N8*(INDEX('GDP Deflator'!$C$5:$C$89,MATCH('IEPR Gas Prices Nominal'!$B8,'GDP Deflator'!$B$5:$B$89,0))/100) -> 7.5739185 | P8: =AVERAGE(F8,I8,L8) -> 6.7345154 | Q8: =AVERAGE(H8,K8,N8) -> 7.750198 | S8: 3 | T8: =INDEX($P$6:$P$401,MATCH(_xlfn.CONCAT($S8,"-",T$5),$E$6:$E$401,0)) -> 5.1890417 | U8: =INDEX($P$6:$P$401,MATCH(_xlfn.CONCAT($S8,"-",U$5),$E$6:$E$401,0)) -> 5.1997741 | V8: =INDEX($P$6:$P$401,MATCH(_xlfn.CONCAT($S8,"-",V$5),$E$6:$E$401,0)) -> 5.3323788 | W8: =INDEX($P$6:$P$401,MATCH(_xlfn.CONCAT($S8,"-",W$5),$E$6:$E$401,0)) -> 5.4538935 | X8: =INDEX($P$6:$P$401,MATCH(_xlfn.CONCAT($S8,"-",X$5),$E$6:$E$401,0)) -> 5.5659196 | Y8: =INDEX($P$6:$P$401,MATCH(_xlfn.CONCAT($S8,"-",Y$5),$E$6:$E$401,0)) -> 5.6784419 | Z8: =INDEX($P$6:$P$401,MATCH(_xlfn.CONCAT($S8,"-",Z$5),$E$6:$E$401,0)) -> 5.7937098 | AA8: =INDEX($P$6:$P$401,MATCH(_xlfn.CONCAT($S8,"-",AA$5),$E$6:$E$401,0)) -> 5.9114979 | ... AY8: =INDEX($P$6:$P$401,MATCH(_xlfn.CONCAT($S8,"-",AY$5),$E$6:$E$401,0)) -> 9.8143723
B9: =YEAR(D9) -> 2022 | C9: =MONTH(D9) -> 4 | D9: 44652 | E9: =C9&"-"&B9 -> 4-2022 | F9: ='IEPR Gas Prices Real'!F9*(INDEX('GDP Deflator'!$C$5:$C$89,MATCH('IEPR Gas Prices Nominal'!$B9,'GDP Deflator'!$B$5:$B$89,0))/100) -> 6.3075504 | G9: ='IEPR Gas Prices Real'!G9*(INDEX('GDP Deflator'!$C$5:$C$89,MATCH('IEPR Gas Prices Nominal'!$B9,'GDP Deflator'!$B$5:$B$89,0))/100) -> 0.88808089 | H9: ='IEPR Gas Prices Real'!H9*(INDEX('GDP Deflator'!$C$5:$C$89,MATCH('IEPR Gas Prices Nominal'!$B9,'GDP Deflator'!$B$5:$B$89,0))/100) -> 7.1956313 | I9: ='IEPR Gas Prices Real'!I9*(INDEX('GDP Deflator'!$C$5:$C$89,MATCH('IEPR Gas Prices Nominal'!$B9,'GDP Deflator'!$B$5:$B$89,0))/100) -> 6.7884701 | J9: ='IEPR Gas Prices Real'!J9*(INDEX('GDP Deflator'!$C$5:$C$89,MATCH('IEPR Gas Prices Nominal'!$B9,'GDP Deflator'!$B$5:$B$89,0))/100) -> 1.4664363 | K9: ='IEPR Gas Prices Real'!K9*(INDEX('GDP Deflator'!$C$5:$C$89,MATCH('IEPR Gas Prices Nominal'!$B9,'GDP Deflator'!$B$5:$B$89,0))/100) -> 8.2549064 | L9: ='IEPR Gas Prices Real'!L9*(INDEX('GDP Deflator'!$C$5:$C$89,MATCH('IEPR Gas Prices Nominal'!$B9,'GDP Deflator'!$B$5:$B$89,0))/100) -> 6.7645794 | M9: ='IEPR Gas Prices Real'!M9*(INDEX('GDP Deflator'!$C$5:$C$89,MATCH('IEPR Gas Prices Nominal'!$B9,'GDP Deflator'!$B$5:$B$89,0))/100) -> 0.69253054 | N9: ='IEPR Gas Prices Real'!N9*(INDEX('GDP Deflator'!$C$5:$C$89,MATCH('IEPR Gas Prices Nominal'!$B9,'GDP Deflator'!$B$5:$B$89,0))/100) -> 7.45711 | P9: =AVERAGE(F9,I9,L9) -> 6.6202 | Q9: =AVERAGE(H9,K9,N9) -> 7.6358825 | S9: 4 | T9: =INDEX($P$6:$P$401,MATCH(_xlfn.CONCAT($S9,"-",T$5),$E$6:$E$401,0)) -> 5.0888001 | U9: =INDEX($P$6:$P$401,MATCH(_xlfn.CONCAT($S9,"-",U$5),$E$6:$E$401,0)) -> 5.1127013 | V9: =INDEX($P$6:$P$401,MATCH(_xlfn.CONCAT($S9,"-",V$5),$E$6:$E$401,0)) -> 5.2418111 | W9: =INDEX($P$6:$P$401,MATCH(_xlfn.CONCAT($S9,"-",W$5),$E$6:$E$401,0)) -> 5.3609111 | X9: =INDEX($P$6:$P$401,MATCH(_xlfn.CONCAT($S9,"-",X$5),$E$6:$E$401,0)) -> 5.470963 | Y9: =INDEX($P$6:$P$401,MATCH(_xlfn.CONCAT($S9,"-",Y$5),$E$6:$E$401,0)) -> 5.5816934 | Z9: =INDEX($P$6:$P$401,MATCH(_xlfn.CONCAT($S9,"-",Z$5),$E$6:$E$401,0)) -> 5.6950636 | AA9: =INDEX($P$6:$P$401,MATCH(_xlfn.CONCAT($S9,"-",AA$5),$E$6:$E$401,0)) -> 5.8107813 | ... AY9: =INDEX($P$6:$P$401,MATCH(_xlfn.CONCAT($S9,"-",AY$5),$E$6:$E$401,0)) -> 9.6475235
B10: =YEAR(D10) -> 2022 | C10: =MONTH(D10) -> 5 | D10: 44682 | E10: =C10&"-"&B10 -> 5-2022 | F10: ='IEPR Gas Prices Real'!F10*(INDEX('GDP Deflator'!$C$5:$C$89,MATCH('IEPR Gas Prices Nominal'!$B10,'GDP Deflator'!$B$5:$B$89,0))/100) -> 6.5273432 | G10: ='IEPR Gas Prices Real'!G10*(INDEX('GDP Deflator'!$C$5:$C$89,MATCH('IEPR Gas Prices Nominal'!$B10,'GDP Deflator'!$B$5:$B$89,0))/100) -> 0.88808089 | H10: ='IEPR Gas Prices Real'!H10*(INDEX('GDP Deflator'!$C$5:$C$89,MATCH('IEPR Gas Prices Nominal'!$B10,'GDP Deflator'!$B$5:$B$89,0))/100) -> 7.4154241 | I10: ='IEPR Gas Prices Real'!I10*(INDEX('GDP Deflator'!$C$5:$C$89,MATCH('IEPR Gas Prices Nominal'!$B10,'GDP Deflator'!$B$5:$B$89,0))/100) -> 7.0250211 | J10: ='IEPR Gas Prices Real'!J10*(INDEX('GDP Deflator'!$C$5:$C$89,MATCH('IEPR Gas Prices Nominal'!$B10,'GDP Deflator'!$B$5:$B$89,0))/100) -> 1.4664363 | K10: ='IEPR Gas Prices Real'!K10*(INDEX('GDP Deflator'!$C$5:$C$89,MATCH('IEPR Gas Prices Nominal'!$B10,'GDP Deflator'!$B$5:$B$89,0))/100) -> 8.4914574 | L10: ='IEPR Gas Prices Real'!L10*(INDEX('GDP Deflator'!$C$5:$C$89,MATCH('IEPR Gas Prices Nominal'!$B10,'GDP Deflator'!$B$5:$B$89,0))/100) -> 7.0002979 | M10: ='IEPR Gas Prices Real'!M10*(INDEX('GDP Deflator'!$C$5:$C$89,MATCH('IEPR Gas Prices Nominal'!$B10,'GDP Deflator'!$B$5:$B$89,0))/100) -> 0.69253054 | N10: ='IEPR Gas Prices Real'!N10*(INDEX('GDP Deflator'!$C$5:$C$89,MATCH('IEPR Gas Prices Nominal'!$B10,'GDP Deflator'!$B$5:$B$89,0))/100) -> 7.6928284 | P10: =AVERAGE(F10,I10,L10) -> 6.8508874 | Q10: =AVERAGE(H10,K10,N10) -> 7.86657 | S10: 5 | T10: =INDEX($P$6:$P$401,MATCH(_xlfn.CONCAT($S10,"-",T$5),$E$6:$E$401,0)) -> 5.2535408 | U10: =INDEX($P$6:$P$401,MATCH(_xlfn.CONCAT($S10,"-",U$5),$E$6:$E$401,0)) -> 5.2920912 | V10: =INDEX($P$6:$P$401,MATCH(_xlfn.CONCAT($S10,"-",V$5),$E$6:$E$401,0)) -> 5.4244125 | W10: =INDEX($P$6:$P$401,MATCH(_xlfn.CONCAT($S10,"-",W$5),$E$6:$E$401,0)) -> 5.5472983 | X10: =INDEX($P$6:$P$401,MATCH(_xlfn.CONCAT($S10,"-",X$5),$E$6:$E$401,0)) -> 5.66111 | Y10: =INDEX($P$6:$P$401,MATCH(_xlfn.CONCAT($S10,"-",Y$5),$E$6:$E$401,0)) -> 5.775821 | Z10: =INDEX($P$6:$P$401,MATCH(_xlfn.CONCAT($S10,"-",Z$5),$E$6:$E$401,0)) -> 5.8932028 | AA10: =INDEX($P$6:$P$401,MATCH(_xlfn.CONCAT($S10,"-",AA$5),$E$6:$E$401,0)) -> 6.0128794 | ... AY10: =INDEX($P$6:$P$401,MATCH(_xlfn.CONCAT($S10,"-",AY$5),$E$6:$E$401,0)) -> 9.983438
B11: =YEAR(D11) -> 2022 | C11: =MONTH(D11) -> 6 | D11: 44713 | E11: =C11&"-"&B11 -> 6-2022 | F11: ='IEPR Gas Prices Real'!F11*(INDEX('GDP Deflator'!$C$5:$C$89,MATCH('IEPR Gas Prices Nominal'!$B11,'GDP Deflator'!$B$5:$B$89,0))/100) -> 5.8933447 | G11: ='IEPR Gas Prices Real'!G11*(INDEX('GDP Deflator'!$C$5:$C$89,MATCH('IEPR Gas Prices Nominal'!$B11,'GDP Deflator'!$B$5:$B$89,0))/100) -> 0.88808089 | H11: ='IEPR Gas Prices Real'!H11*(INDEX('GDP Deflator'!$C$5:$C$89,MATCH('IEPR Gas Prices Nominal'!$B11,'GDP Deflator'!$B$5:$B$89,0))/100) -> 6.7814256 | I11: ='IEPR Gas Prices Real'!I11*(INDEX('GDP Deflator'!$C$5:$C$89,MATCH('IEPR Gas Prices Nominal'!$B11,'GDP Deflator'!$B$5:$B$89,0))/100) -> 6.2825876 | J11: ='IEPR Gas Prices Real'!J11*(INDEX('GDP Deflator'!$C$5:$C$89,MATCH('IEPR Gas Prices Nominal'!$B11,'GDP Deflator'!$B$5:$B$89,0))/100) -> 1.4664363 | K11: ='IEPR Gas Prices Real'!K11*(INDEX('GDP Deflator'!$C$5:$C$89,MATCH('IEPR Gas Prices Nominal'!$B11,'GDP Deflator'!$B$5:$B$89,0))/100) -> 7.7490239 | L11: ='IEPR Gas Prices Real'!L11*(INDEX('GDP Deflator'!$C$5:$C$89,MATCH('IEPR Gas Prices Nominal'!$B11,'GDP Deflator'!$B$5:$B$89,0))/100) -> 6.36177 | M11: ='IEPR Gas Prices Real'!M11*(INDEX('GDP Deflator'!$C$5:$C$89,MATCH('IEPR Gas Prices Nominal'!$B11,'GDP Deflator'!$B$5:$B$89,0))/100) -> 0.69253054 | N11: ='IEPR Gas Prices Real'!N11*(INDEX('GDP Deflator'!$C$5:$C$89,MATCH('IEPR Gas Prices Nominal'!$B11,'GDP Deflator'!$B$5:$B$89,0))/100) -> 7.0543005 | P11: =AVERAGE(F11,I11,L11) -> 6.1792341 | Q11: =AVERAGE(H11,K11,N11) -> 7.1949167 | S11: 6 | T11: =INDEX($P$6:$P$401,MATCH(_xlfn.CONCAT($S11,"-",T$5),$E$6:$E$401,0)) -> 5.3766711 | U11: =INDEX($P$6:$P$401,MATCH(_xlfn.CONCAT($S11,"-",U$5),$E$6:$E$401,0)) -> 5.4303937 | V11: =INDEX($P$6:$P$401,MATCH(_xlfn.CONCAT($S11,"-",V$5),$E$6:$E$401,0)) -> 5.5648209 | W11: =INDEX($P$6:$P$401,MATCH(_xlfn.CONCAT($S11,"-",W$5),$E$6:$E$401,0)) -> 5.690515 | X11: =INDEX($P$6:$P$401,MATCH(_xlfn.CONCAT($S11,"-",X$5),$E$6:$E$401,0)) -> 5.8071968 | Y11: =INDEX($P$6:$P$401,MATCH(_xlfn.CONCAT($S11,"-",Y$5),$E$6:$E$401,0)) -> 5.9250034 | Z11: =INDEX($P$6:$P$401,MATCH(_xlfn.CONCAT($S11,"-",Z$5),$E$6:$E$401,0)) -> 6.0454874 | AA11: =INDEX($P$6:$P$401,MATCH(_xlfn.CONCAT($S11,"-",AA$5),$E$6:$E$401,0)) -> 6.1681877 | ... AY11: =INDEX($P$6:$P$401,MATCH(_xlfn.CONCAT($S11,"-",AY$5),$E$6:$E$401,0)) -> 10.241688
B12: =YEAR(D12) -> 2022 | C12: =MONTH(D12) -> 7 | D12: 44743 | E12: =C12&"-"&B12 -> 7-2022 | F12: ='IEPR Gas Prices Real'!F12*(INDEX('GDP Deflator'!$C$5:$C$89,MATCH('IEPR Gas Prices Nominal'!$B12,'GDP Deflator'!$B$5:$B$89,0))/100) -> 5.8054427 | G12: ='IEPR Gas Prices Real'!G12*(INDEX('GDP Deflator'!$C$5:$C$89,MATCH('IEPR Gas Prices Nominal'!$B12,'GDP Deflator'!$B$5:$B$89,0))/100) -> 0.88808089 | H12: ='IEPR Gas Prices Real'!H12*(INDEX('GDP Deflator'!$C$5:$C$89,MATCH('IEPR Gas Prices Nominal'!$B12,'GDP Deflator'!$B$5:$B$89,0))/100) -> 6.6935236 | I12: ='IEPR Gas Prices Real'!I12*(INDEX('GDP Deflator'!$C$5:$C$89,MATCH('IEPR Gas Prices Nominal'!$B12,'GDP Deflator'!$B$5:$B$89,0))/100) -> 6.1774084 | J12: ='IEPR Gas Prices Real'!J12*(INDEX('GDP Deflator'!$C$5:$C$89,MATCH('IEPR Gas Prices Nominal'!$B12,'GDP Deflator'!$B$5:$B$89,0))/100) -> 1.4664363 | K12: ='IEPR Gas Prices Real'!K12*(INDEX('GDP Deflator'!$C$5:$C$89,MATCH('IEPR Gas Prices Nominal'!$B12,'GDP Deflator'!$B$5:$B$89,0))/100) -> 7.6438447 | L12: ='IEPR Gas Prices Real'!L12*(INDEX('GDP Deflator'!$C$5:$C$89,MATCH('IEPR Gas Prices Nominal'!$B12,'GDP Deflator'!$B$5:$B$89,0))/100) -> 6.2747856 | M12: ='IEPR Gas Prices Real'!M12*(INDEX('GDP Deflator'!$C$5:$C$89,MATCH('IEPR Gas Prices Nominal'!$B12,'GDP Deflator'!$B$5:$B$89,0))/100) -> 0.69253054 | N12: ='IEPR Gas Prices Real'!N12*(INDEX('GDP Deflator'!$C$5:$C$89,MATCH('IEPR Gas Prices Nominal'!$B12,'GDP Deflator'!$B$5:$B$89,0))/100) -> 6.9673161 | P12: =AVERAGE(F12,I12,L12) -> 6.0858789 | Q12: =AVERAGE(H12,K12,N12) -> 7.1015615 | S12: 7 | T12: =INDEX($P$6:$P$401,MATCH(_xlfn.CONCAT($S12,"-",T$5),$E$6:$E$401,0)) -> 5.4065406 | U12: =INDEX($P$6:$P$401,MATCH(_xlfn.CONCAT($S12,"-",U$5),$E$6:$E$401,0)) -> 5.4749788 | V12: =INDEX($P$6:$P$401,MATCH(_xlfn.CONCAT($S12,"-",V$5),$E$6:$E$401,0)) -> 5.6091468 | W12: =INDEX($P$6:$P$401,MATCH(_xlfn.CONCAT($S12,"-",W$5),$E$6:$E$401,0)) -> 5.7354667 | X12: =INDEX($P$6:$P$401,MATCH(_xlfn.CONCAT($S12,"-",X$5),$E$6:$E$401,0)) -> 5.8530014 | Y12: =INDEX($P$6:$P$401,MATCH(_xlfn.CONCAT($S12,"-",Y$5),$E$6:$E$401,0)) -> 5.9718739 | Z12: =INDEX($P$6:$P$401,MATCH(_xlfn.CONCAT($S12,"-",Z$5),$E$6:$E$401,0)) -> 6.0933819 | AA12: =INDEX($P$6:$P$401,MATCH(_xlfn.CONCAT($S12,"-",AA$5),$E$6:$E$401,0)) -> 6.2169849 | ... AY12: =INDEX($P$6:$P$401,MATCH(_xlfn.CONCAT($S12,"-",AY$5),$E$6:$E$401,0)) -> 10.323099
B13: =YEAR(D13) -> 2022 | C13: =MONTH(D13) -> 8 | D13: 44774 | E13: =C13&"-"&B13 -> 8-2022 | F13: ='IEPR Gas Prices Real'!F13*(INDEX('GDP Deflator'!$C$5:$C$89,MATCH('IEPR Gas Prices Nominal'!$B13,'GDP Deflator'!$B$5:$B$89,0))/100) -> 5.6269735 | G13: ='IEPR Gas Prices Real'!G13*(INDEX('GDP Deflator'!$C$5:$C$89,MATCH('IEPR Gas Prices Nominal'!$B13,'GDP Deflator'!$B$5:$B$89,0))/100) -> 0.88808089 | H13: ='IEPR Gas Prices Real'!H13*(INDEX('GDP Deflator'!$C$5:$C$89,MATCH('IEPR Gas Prices Nominal'!$B13,'GDP Deflator'!$B$5:$B$89,0))/100) -> 6.5150544 | I13: ='IEPR Gas Prices Real'!I13*(INDEX('GDP Deflator'!$C$5:$C$89,MATCH('IEPR Gas Prices Nominal'!$B13,'GDP Deflator'!$B$5:$B$89,0))/100) -> 5.9758565 | J13: ='IEPR Gas Prices Real'!J13*(INDEX('GDP Deflator'!$C$5:$C$89,MATCH('IEPR Gas Prices Nominal'!$B13,'GDP Deflator'!$B$5:$B$89,0))/100) -> 1.4664363 | K13: ='IEPR Gas Prices Real'!K13*(INDEX('GDP Deflator'!$C$5:$C$89,MATCH('IEPR Gas Prices Nominal'!$B13,'GDP Deflator'!$B$5:$B$89,0))/100) -> 7.4422928 | L13: ='IEPR Gas Prices Real'!L13*(INDEX('GDP Deflator'!$C$5:$C$89,MATCH('IEPR Gas Prices Nominal'!$B13,'GDP Deflator'!$B$5:$B$89,0))/100) -> 6.0899139 | M13: ='IEPR Gas Prices Real'!M13*(INDEX('GDP Deflator'!$C$5:$C$89,MATCH('IEPR Gas Prices Nominal'!$B13,'GDP Deflator'!$B$5:$B$89,0))/100) -> 0.69253054 | N13: ='IEPR Gas Prices Real'!N13*(INDEX('GDP Deflator'!$C$5:$C$89,MATCH('IEPR Gas Prices Nominal'!$B13,'GDP Deflator'!$B$5:$B$89,0))/100) -> 6.7824444 | P13: =AVERAGE(F13,I13,L13) -> 5.8975813 | Q13: =AVERAGE(H13,K13,N13) -> 6.9132639 | S13: 8 | T13: =INDEX($P$6:$P$401,MATCH(_xlfn.CONCAT($S13,"-",T$5),$E$6:$E$401,0)) -> 5.3520919 | U13: =INDEX($P$6:$P$401,MATCH(_xlfn.CONCAT($S13,"-",U$5),$E$6:$E$401,0)) -> 5.4341815 | V13: =INDEX($P$6:$P$401,MATCH(_xlfn.CONCAT($S13,"-",V$5),$E$6:$E$401,0)) -> 5.5659978 | W13: =INDEX($P$6:$P$401,MATCH(_xlfn.CONCAT($S13,"-",W$5),$E$6:$E$401,0)) -> 5.6909733 | X13: =INDEX($P$6:$P$401,MATCH(_xlfn.CONCAT($S13,"-",X$5),$E$6:$E$401,0)) -> 5.807528 | Y13: =INDEX($P$6:$P$401,MATCH(_xlfn.CONCAT($S13,"-",Y$5),$E$6:$E$401,0)) -> 5.9256125 | Z13: =INDEX($P$6:$P$401,MATCH(_xlfn.CONCAT($S13,"-",Z$5),$E$6:$E$401,0)) -> 6.0462497 | AA13: =INDEX($P$6:$P$401,MATCH(_xlfn.CONCAT($S13,"-",AA$5),$E$6:$E$401,0)) -> 6.1688277 | ... AY13: =INDEX($P$6:$P$401,MATCH(_xlfn.CONCAT($S13,"-",AY$5),$E$6:$E$401,0)) -> 10.243521
B14: =YEAR(D14) -> 2022 | C14: =MONTH(D14) -> 9 | D14: 44805 | E14: =C14&"-"&B14 -> 9-2022 | F14: ='IEPR Gas Prices Real'!F14*(INDEX('GDP Deflator'!$C$5:$C$89,MATCH('IEPR Gas Prices Nominal'!$B14,'GDP Deflator'!$B$5:$B$89,0))/100) -> 5.5706035 | G14: ='IEPR Gas Prices Real'!G14*(INDEX('GDP Deflator'!$C$5:$C$89,MATCH('IEPR Gas Prices Nominal'!$B14,'GDP Deflator'!$B$5:$B$89,0))/100) -> 0.88808089 | H14: ='IEPR Gas Prices Real'!H14*(INDEX('GDP Deflator'!$C$5:$C$89,MATCH('IEPR Gas Prices Nominal'!$B14,'GDP Deflator'!$B$5:$B$89,0))/100) -> 6.4586844 | I14: ='IEPR Gas Prices Real'!I14*(INDEX('GDP Deflator'!$C$5:$C$89,MATCH('IEPR Gas Prices Nominal'!$B14,'GDP Deflator'!$B$5:$B$89,0))/100) -> 5.9038982 | J14: ='IEPR Gas Prices Real'!J14*(INDEX('GDP Deflator'!$C$5:$C$89,MATCH('IEPR Gas Prices Nominal'!$B14,'GDP Deflator'!$B$5:$B$89,0))/100) -> 1.4664363 | K14: ='IEPR Gas Prices Real'!K14*(INDEX('GDP Deflator'!$C$5:$C$89,MATCH('IEPR Gas Prices Nominal'!$B14,'GDP Deflator'!$B$5:$B$89,0))/100) -> 7.3703346 | L14: ='IEPR Gas Prices Real'!L14*(INDEX('GDP Deflator'!$C$5:$C$89,MATCH('IEPR Gas Prices Nominal'!$B14,'GDP Deflator'!$B$5:$B$89,0))/100) -> 6.037239 | M14: ='IEPR Gas Prices Real'!M14*(INDEX('GDP Deflator'!$C$5:$C$89,MATCH('IEPR Gas Prices Nominal'!$B14,'GDP Deflator'!$B$5:$B$89,0))/100) -> 0.69253054 | N14: ='IEPR Gas Prices Real'!N14*(INDEX('GDP Deflator'!$C$5:$C$89,MATCH('IEPR Gas Prices Nominal'!$B14,'GDP Deflator'!$B$5:$B$89,0))/100) -> 6.7297695 | P14: =AVERAGE(F14,I14,L14) -> 5.8372469 | Q14: =AVERAGE(H14,K14,N14) -> 6.8529295 | S14: 9 | T14: =INDEX($P$6:$P$401,MATCH(_xlfn.CONCAT($S14,"-",T$5),$E$6:$E$401,0)) -> 5.414506 | U14: =INDEX($P$6:$P$401,MATCH(_xlfn.CONCAT($S14,"-",U$5),$E$6:$E$401,0)) -> 5.5121311 | V14: =INDEX($P$6:$P$401,MATCH(_xlfn.CONCAT($S14,"-",V$5),$E$6:$E$401,0)) -> 5.6444675 | W14: =INDEX($P$6:$P$401,MATCH(_xlfn.CONCAT($S14,"-",W$5),$E$6:$E$401,0)) -> 5.770827 | X14: =INDEX($P$6:$P$401,MATCH(_xlfn.CONCAT($S14,"-",X$5),$E$6:$E$401,0)) -> 5.8889479 | Y14: =INDEX($P$6:$P$401,MATCH(_xlfn.CONCAT($S14,"-",Y$5),$E$6:$E$401,0)) -> 6.0088255 | Z14: =INDEX($P$6:$P$401,MATCH(_xlfn.CONCAT($S14,"-",Z$5),$E$6:$E$401,0)) -> 6.1312282 | AA14: =INDEX($P$6:$P$401,MATCH(_xlfn.CONCAT($S14,"-",AA$5),$E$6:$E$401,0)) -> 6.2554591 | ... AY14: =INDEX($P$6:$P$401,MATCH(_xlfn.CONCAT($S14,"-",AY$5),$E$6:$E$401,0)) -> 10.387765
B15: =YEAR(D15) -> 2022 | C15: =MONTH(D15) -> 10 | D15: 44835 | E15: =C15&"-"&B15 -> 10-2022 | F15: ='IEPR Gas Prices Real'!F15*(INDEX('GDP Deflator'!$C$5:$C$89,MATCH('IEPR Gas Prices Nominal'!$B15,'GDP Deflator'!$B$5:$B$89,0))/100) -> 5.4037543 | G15: ='IEPR Gas Prices Real'!G15*(INDEX('GDP Deflator'!$C$5:$C$89,MATCH('IEPR Gas Prices Nominal'!$B15,'GDP Deflator'!$B$5:$B$89,0))/100) -> 0.88808089 | H15: ='IEPR Gas Prices Real'!H15*(INDEX('GDP Deflator'!$C$5:$C$89,MATCH('IEPR Gas Prices Nominal'!$B15,'GDP Deflator'!$B$5:$B$89,0))/100) -> 6.2918351 | I15: ='IEPR Gas Prices Real'!I15*(INDEX('GDP Deflator'!$C$5:$C$89,MATCH('IEPR Gas Prices Nominal'!$B15,'GDP Deflator'!$B$5:$B$89,0))/100) -> 5.7147492 | J15: ='IEPR Gas Prices Real'!J15*(INDEX('GDP Deflator'!$C$5:$C$89,MATCH('IEPR Gas Prices Nominal'!$B15,'GDP Deflator'!$B$5:$B$89,0))/100) -> 1.4664363 | K15: ='IEPR Gas Prices Real'!K15*(INDEX('GDP Deflator'!$C$5:$C$89,MATCH('IEPR Gas Prices Nominal'!$B15,'GDP Deflator'!$B$5:$B$89,0))/100) -> 7.1811855 | L15: ='IEPR Gas Prices Real'!L15*(INDEX('GDP Deflator'!$C$5:$C$89,MATCH('IEPR Gas Prices Nominal'!$B15,'GDP Deflator'!$B$5:$B$89,0))/100) -> 5.8649002 | M15: ='IEPR Gas Prices Real'!M15*(INDEX('GDP Deflator'!$C$5:$C$89,MATCH('IEPR Gas Prices Nominal'!$B15,'GDP Deflator'!$B$5:$B$89,0))/100) -> 0.69253054 | N15: ='IEPR Gas Prices Real'!N15*(INDEX('GDP Deflator'!$C$5:$C$89,MATCH('IEPR Gas Prices Nominal'!$B15,'GDP Deflator'!$B$5:$B$89,0))/100) -> 6.5574307 | P15: =AVERAGE(F15,I15,L15) -> 5.6611345 | Q15: =AVERAGE(H15,K15,N15) -> 6.6768171 | S15: 10 | T15: =INDEX($P$6:$P$401,MATCH(_xlfn.CONCAT($S15,"-",T$5),$E$6:$E$401,0)) -> 5.3705103 | U15: =INDEX($P$6:$P$401,MATCH(_xlfn.CONCAT($S15,"-",U$5),$E$6:$E$401,0)) -> 5.4818719 | V15: =INDEX($P$6:$P$401,MATCH(_xlfn.CONCAT($S15,"-",V$5),$E$6:$E$401,0)) -> 5.6121192 | W15: =INDEX($P$6:$P$401,MATCH(_xlfn.CONCAT($S15,"-",W$5),$E$6:$E$401,0)) -> 5.7373789 | X15: =INDEX($P$6:$P$401,MATCH(_xlfn.CONCAT($S15,"-",X$5),$E$6:$E$401,0)) -> 5.8547463 | Y15: =INDEX($P$6:$P$401,MATCH(_xlfn.CONCAT($S15,"-",Y$5),$E$6:$E$401,0)) -> 5.9740645 | Z15: =INDEX($P$6:$P$401,MATCH(_xlfn.CONCAT($S15,"-",Z$5),$E$6:$E$401,0)) -> 6.0958301 | AA15: =INDEX($P$6:$P$401,MATCH(_xlfn.CONCAT($S15,"-",AA$5),$E$6:$E$401,0)) -> 6.2192743 | ... AY15: =INDEX($P$6:$P$401,MATCH(_xlfn.CONCAT($S15,"-",AY$5),$E$6:$E$401,0)) -> 10.328066
B16: =YEAR(D16) -> 2022 | C16: =MONTH(D16) -> 11 | D16: 44866 | E16: =C16&"-"&B16 -> 11-2022 | F16: ='IEPR Gas Prices Real'!F16*(INDEX('GDP Deflator'!$C$5:$C$89,MATCH('IEPR Gas Prices Nominal'!$B16,'GDP Deflator'!$B$5:$B$89,0))/100) -> 5.5294241 | G16: ='IEPR Gas Prices Real'!G16*(INDEX('GDP Deflator'!$C$5:$C$89,MATCH('IEPR Gas Prices Nominal'!$B16,'GDP Deflator'!$B$5:$B$89,0))/100) -> 0.88808089 | H16: ='IEPR Gas Prices Real'!H16*(INDEX('GDP Deflator'!$C$5:$C$89,MATCH('IEPR Gas Prices Nominal'!$B16,'GDP Deflator'!$B$5:$B$89,0))/100) -> 6.417505 | I16: ='IEPR Gas Prices Real'!I16*(INDEX('GDP Deflator'!$C$5:$C$89,MATCH('IEPR Gas Prices Nominal'!$B16,'GDP Deflator'!$B$5:$B$89,0))/100) -> 5.8344022 | J16: ='IEPR Gas Prices Real'!J16*(INDEX('GDP Deflator'!$C$5:$C$89,MATCH('IEPR Gas Prices Nominal'!$B16,'GDP Deflator'!$B$5:$B$89,0))/100) -> 1.4664363 | K16: ='IEPR Gas Prices Real'!K16*(INDEX('GDP Deflator'!$C$5:$C$89,MATCH('IEPR Gas Prices Nominal'!$B16,'GDP Deflator'!$B$5:$B$89,0))/100) -> 7.3008385 | L16: ='IEPR Gas Prices Real'!L16*(INDEX('GDP Deflator'!$C$5:$C$89,MATCH('IEPR Gas Prices Nominal'!$B16,'GDP Deflator'!$B$5:$B$89,0))/100) -> 6.0104238 | M16: ='IEPR Gas Prices Real'!M16*(INDEX('GDP Deflator'!$C$5:$C$89,MATCH('IEPR Gas Prices Nominal'!$B16,'GDP Deflator'!$B$5:$B$89,0))/100) -> 0.69253054 | N16: ='IEPR Gas Prices Real'!N16*(INDEX('GDP Deflator'!$C$5:$C$89,MATCH('IEPR Gas Prices Nominal'!$B16,'GDP Deflator'!$B$5:$B$89,0))/100) -> 6.7029543 | P16: =AVERAGE(F16,I16,L16) -> 5.7914167 | Q16: =AVERAGE(H16,K16,N16) -> 6.8070993 | S16: 11 | T16: =INDEX($P$6:$P$401,MATCH(_xlfn.CONCAT($S16,"-",T$5),$E$6:$E$401,0)) -> 5.6225295 | U16: =INDEX($P$6:$P$401,MATCH(_xlfn.CONCAT($S16,"-",U$5),$E$6:$E$401,0)) -> 5.7544026 | V16: =INDEX($P$6:$P$401,MATCH(_xlfn.CONCAT($S16,"-",V$5),$E$6:$E$401,0)) -> 5.8896954 | W16: =INDEX($P$6:$P$401,MATCH(_xlfn.CONCAT($S16,"-",W$5),$E$6:$E$401,0)) -> 6.0207562 | X16: =INDEX($P$6:$P$401,MATCH(_xlfn.CONCAT($S16,"-",X$5),$E$6:$E$401,0)) -> 6.1438483 | Y16: =INDEX($P$6:$P$401,MATCH(_xlfn.CONCAT($S16,"-",Y$5),$E$6:$E$401,0)) -> 6.2692018 | Z16: =INDEX($P$6:$P$401,MATCH(_xlfn.CONCAT($S16,"-",Z$5),$E$6:$E$401,0)) -> 6.3970575 | AA16: =INDEX($P$6:$P$401,MATCH(_xlfn.CONCAT($S16,"-",AA$5),$E$6:$E$401,0)) -> 6.5265289 | ... AY16: =INDEX($P$6:$P$401,MATCH(_xlfn.CONCAT($S16,"-",AY$5),$E$6:$E$401,0)) -> 10.838717
B17: =YEAR(D17) -> 2022 | C17: =MONTH(D17) -> 12 | D17: 44896 | E17: =C17&"-"&B17 -> 12-2022 | F17: ='IEPR Gas Prices Real'!F17*(INDEX('GDP Deflator'!$C$5:$C$89,MATCH('IEPR Gas Prices Nominal'!$B17,'GDP Deflator'!$B$5:$B$89,0))/100) -> 5.4313298 | G17: ='IEPR Gas Prices Real'!G17*(INDEX('GDP Deflator'!$C$5:$C$89,MATCH('IEPR Gas Prices Nominal'!$B17,'GDP Deflator'!$B$5:$B$89,0))/100) -> 0.88808089 | H17: ='IEPR Gas Prices Real'!H17*(INDEX('GDP Deflator'!$C$5:$C$89,MATCH('IEPR Gas Prices Nominal'!$B17,'GDP Deflator'!$B$5:$B$89,0))/100) -> 6.3194107 | I17: ='IEPR Gas Prices Real'!I17*(INDEX('GDP Deflator'!$C$5:$C$89,MATCH('IEPR Gas Prices Nominal'!$B17,'GDP Deflator'!$B$5:$B$89,0))/100) -> 5.7171989 | J17: ='IEPR Gas Prices Real'!J17*(INDEX('GDP Deflator'!$C$5:$C$89,MATCH('IEPR Gas Prices Nominal'!$B17,'GDP Deflator'!$B$5:$B$89,0))/100) -> 1.4664363 | K17: ='IEPR Gas Prices Real'!K17*(INDEX('GDP Deflator'!$C$5:$C$89,MATCH('IEPR Gas Prices Nominal'!$B17,'GDP Deflator'!$B$5:$B$89,0))/100) -> 7.1836352 | L17: ='IEPR Gas Prices Real'!L17*(INDEX('GDP Deflator'!$C$5:$C$89,MATCH('IEPR Gas Prices Nominal'!$B17,'GDP Deflator'!$B$5:$B$89,0))/100) -> 5.9132352 | M17: ='IEPR Gas Prices Real'!M17*(INDEX('GDP Deflator'!$C$5:$C$89,MATCH('IEPR Gas Prices Nominal'!$B17,'GDP Deflator'!$B$5:$B$89,0))/100) -> 0.69253054 | N17: ='IEPR Gas Prices Real'!N17*(INDEX('GDP Deflator'!$C$5:$C$89,MATCH('IEPR Gas Prices Nominal'!$B17,'GDP Deflator'!$B$5:$B$89,0))/100) -> 6.6057658 | P17: =AVERAGE(F17,I17,L17) -> 5.6872546 | Q17: =AVERAGE(H17,K17,N17) -> 6.7029372 | S17: 12 | T17: =INDEX($P$6:$P$401,MATCH(_xlfn.CONCAT($S17,"-",T$5),$E$6:$E$401,0)) -> 5.6542169 | U17: =INDEX($P$6:$P$401,MATCH(_xlfn.CONCAT($S17,"-",U$5),$E$6:$E$401,0)) -> 5.8022798 | V17: =INDEX($P$6:$P$401,MATCH(_xlfn.CONCAT($S17,"-",V$5),$E$6:$E$401,0)) -> 5.9372574 | W17: =INDEX($P$6:$P$401,MATCH(_xlfn.CONCAT($S17,"-",W$5),$E$6:$E$401,0)) -> 6.0689791 | X17: =INDEX($P$6:$P$401,MATCH(_xlfn.CONCAT($S17,"-",X$5),$E$6:$E$401,0)) -> 6.1929842 | Y17: =INDEX($P$6:$P$401,MATCH(_xlfn.CONCAT($S17,"-",Y$5),$E$6:$E$401,0)) -> 6.319485 | Z17: =INDEX($P$6:$P$401,MATCH(_xlfn.CONCAT($S17,"-",Z$5),$E$6:$E$401,0)) -> 6.4484413 | AA17: =INDEX($P$6:$P$401,MATCH(_xlfn.CONCAT($S17,"-",AA$5),$E$6:$E$401,0)) -> 6.5788791 | ... AY17: =INDEX($P$6:$P$401,MATCH(_xlfn.CONCAT($S17,"-",AY$5),$E$6:$E$401,0)) -> 10.926067
B18: =YEAR(D18) -> 2023 | C18: =MONTH(D18) -> 1 | D18: 44927 | E18: =C18&"-"&B18 -> 1-2023 | F18: ='IEPR Gas Prices Real'!F18*(INDEX('GDP Deflator'!$C$5:$C$89,MATCH('IEPR Gas Prices Nominal'!$B18,'GDP Deflator'!$B$5:$B$89,0))/100) -> 5.544792 | G18: ='IEPR Gas Prices Real'!G18*(INDEX('GDP Deflator'!$C$5:$C$89,MATCH('IEPR Gas Prices Nominal'!$B18,'GDP Deflator'!$B$5:$B$89,0))/100) -> 0.90873263 | H18: ='IEPR Gas Prices Real'!H18*(INDEX('GDP Deflator'!$C$5:$C$89,MATCH('IEPR Gas Prices Nominal'!$B18,'GDP Deflator'!$B$5:$B$89,0))/100) -> 6.4535246 | I18: ='IEPR Gas Prices Real'!I18*(INDEX('GDP Deflator'!$C$5:$C$89,MATCH('IEPR Gas Prices Nominal'!$B18,'GDP Deflator'!$B$5:$B$89,0))/100) -> 5.8367813 | J18: ='IEPR Gas Prices Real'!J18*(INDEX('GDP Deflator'!$C$5:$C$89,MATCH('IEPR Gas Prices Nominal'!$B18,'GDP Deflator'!$B$5:$B$89,0))/100) -> 1.5005373 | K18: ='IEPR Gas Prices Real'!K18*(INDEX('GDP Deflator'!$C$5:$C$89,MATCH('IEPR Gas Prices Nominal'!$B18,'GDP Deflator'!$B$5:$B$89,0))/100) -> 7.3373186 | L18: ='IEPR Gas Prices Real'!L18*(INDEX('GDP Deflator'!$C$5:$C$89,MATCH('IEPR Gas Prices Nominal'!$B18,'GDP Deflator'!$B$5:$B$89,0))/100) -> 6.037371 | M18: ='IEPR Gas Prices Real'!M18*(INDEX('GDP Deflator'!$C$5:$C$89,MATCH('IEPR Gas Prices Nominal'!$B18,'GDP Deflator'!$B$5:$B$89,0))/100) -> 0.70863489 | N18: ='IEPR Gas Prices Real'!N18*(INDEX('GDP Deflator'!$C$5:$C$89,MATCH('IEPR Gas Prices Nominal'!$B18,'GDP Deflator'!$B$5:$B$89,0))/100) -> 6.7460059 | P18: =AVERAGE(F18,I18,L18) -> 5.8063148 | Q18: =AVERAGE(H18,K18,N18) -> 6.8456164 | S18: Average | T18: =AVERAGE(T6:T17) -> 5.4333781 | U18: =AVERAGE(U6:U17) -> 5.4954577 | V18: =AVERAGE(V6:V17) -> 5.6307591 | W18: =AVERAGE(W6:W17) -> 5.7577397 | X18: =AVERAGE(X6:X17) -> 5.8757627 | Y18: =AVERAGE(Y6:Y17) -> 5.9950342 | Z18: =AVERAGE(Z6:Z17) -> 6.1169806 | AA18: =AVERAGE(AA6:AA17) -> 6.2410944 | ... AY18: =AVERAGE(AY6:AY17) -> 10.362952
B19: =YEAR(D19) -> 2023 | C19: =MONTH(D19) -> 2 | D19: 44958 | E19: =C19&"-"&B19 -> 2-2023 | F19: ='IEPR Gas Prices Real'!F19*(INDEX('GDP Deflator'!$C$5:$C$89,MATCH('IEPR Gas Prices Nominal'!$B19,'GDP Deflator'!$B$5:$B$89,0))/100) -> 5.4103453 | G19: ='IEPR Gas Prices Real'!G19*(INDEX('GDP Deflator'!$C$5:$C$89,MATCH('IEPR Gas Prices Nominal'!$B19,'GDP Deflator'!$B$5:$B$89,0))/100) -> 0.90873263 | H19: ='IEPR Gas Prices Real'!H19*(INDEX('GDP Deflator'!$C$5:$C$89,MATCH('IEPR Gas Prices Nominal'!$B19,'GDP Deflator'!$B$5:$B$89,0))/100) -> 6.319078 | I19: ='IEPR Gas Prices Real'!I19*(INDEX('GDP Deflator'!$C$5:$C$89,MATCH('IEPR Gas Prices Nominal'!$B19,'GDP Deflator'!$B$5:$B$89,0))/100) -> 5.6954 | J19: ='IEPR Gas Prices Real'!J19*(INDEX('GDP Deflator'!$C$5:$C$89,MATCH('IEPR Gas Prices Nominal'!$B19,'GDP Deflator'!$B$5:$B$89,0))/100) -> 1.5005373 | K19: ='IEPR Gas Prices Real'!K19*(INDEX('GDP Deflator'!$C$5:$C$89,MATCH('IEPR Gas Prices Nominal'!$B19,'GDP Deflator'!$B$5:$B$89,0))/100) -> 7.1959373 | L19: ='IEPR Gas Prices Real'!L19*(INDEX('GDP Deflator'!$C$5:$C$89,MATCH('IEPR Gas Prices Nominal'!$B19,'GDP Deflator'!$B$5:$B$89,0))/100) -> 5.8915752 | M19: ='IEPR Gas Prices Real'!M19*(INDEX('GDP Deflator'!$C$5:$C$89,MATCH('IEPR Gas Prices Nominal'!$B19,'GDP Deflator'!$B$5:$B$89,0))/100) -> 0.70863489 | N19: ='IEPR Gas Prices Real'!N19*(INDEX('GDP Deflator'!$C$5:$C$89,MATCH('IEPR Gas Prices Nominal'!$B19,'GDP Deflator'!$B$5:$B$89,0))/100) -> 6.6002101 | P19: =AVERAGE(F19,I19,L19) -> 5.6657735 | Q19: =AVERAGE(H19,K19,N19) -> 6.7050751
B20: =YEAR(D20) -> 2023 | C20: =MONTH(D20) -> 3 | D20: 44986 | E20: =C20&"-"&B20 -> 3-2023 | F20: ='IEPR Gas Prices Real'!F20*(INDEX('GDP Deflator'!$C$5:$C$89,MATCH('IEPR Gas Prices Nominal'!$B20,'GDP Deflator'!$B$5:$B$89,0))/100) -> 4.9548891 | G20: ='IEPR Gas Prices Real'!G20*(INDEX('GDP Deflator'!$C$5:$C$89,MATCH('IEPR Gas Prices Nominal'!$B20,'GDP Deflator'!$B$5:$B$89,0))/100) -> 0.90873263 | H20: ='IEPR Gas Prices Real'!H20*(INDEX('GDP Deflator'!$C$5:$C$89,MATCH('IEPR Gas Prices Nominal'!$B20,'GDP Deflator'!$B$5:$B$89,0))/100) -> 5.8636217 | I20: ='IEPR Gas Prices Real'!I20*(INDEX('GDP Deflator'!$C$5:$C$89,MATCH('IEPR Gas Prices Nominal'!$B20,'GDP Deflator'!$B$5:$B$89,0))/100) -> 5.2160809 | J20: ='IEPR Gas Prices Real'!J20*(INDEX('GDP Deflator'!$C$5:$C$89,MATCH('IEPR Gas Prices Nominal'!$B20,'GDP Deflator'!$B$5:$B$89,0))/100) -> 1.5005373 | K20: ='IEPR Gas Prices Real'!K20*(INDEX('GDP Deflator'!$C$5:$C$89,MATCH('IEPR Gas Prices Nominal'!$B20,'GDP Deflator'!$B$5:$B$89,0))/100) -> 6.7166183 | L20: ='IEPR Gas Prices Real'!L20*(INDEX('GDP Deflator'!$C$5:$C$89,MATCH('IEPR Gas Prices Nominal'!$B20,'GDP Deflator'!$B$5:$B$89,0))/100) -> 5.396155 | M20: ='IEPR Gas Prices Real'!M20*(INDEX('GDP Deflator'!$C$5:$C$89,MATCH('IEPR Gas Prices Nominal'!$B20,'GDP Deflator'!$B$5:$B$89,0))/100) -> 0.70863489 | N20: ='IEPR Gas Prices Real'!N20*(INDEX('GDP Deflator'!$C$5:$C$89,MATCH('IEPR Gas Prices Nominal'!$B20,'GDP Deflator'!$B$5:$B$89,0))/100) -> 6.1047899 | P20: =AVERAGE(F20,I20,L20) -> 5.1890417 | Q20: =AVERAGE(H20,K20,N20) -> 6.2283433 | S20: Burnertip Price | T20: ='User Dashboard'!E$58 -> 2023 | U20: ='User Dashboard'!F$58 -> 2024 | V20: ='User Dashboard'!G$58 -> 2025 | W20: ='User Dashboard'!H$58 -> 2026 | X20: ='User Dashboard'!I$58 -> 2027 | Y20: ='User Dashboard'!J$58 -> 2028 | Z20: ='User Dashboard'!K$58 -> 2029 | AA20: ='User Dashboard'!L$58 -> 2030 | ... AY20: ='User Dashboard'!AJ$58 -> 2054
B21: =YEAR(D21) -> 2023 | C21: =MONTH(D21) -> 4 | D21: 45017 | E21: =C21&"-"&B21 -> 4-2023 | F21: ='IEPR Gas Prices Real'!F21*(INDEX('GDP Deflator'!$C$5:$C$89,MATCH('IEPR Gas Prices Nominal'!$B21,'GDP Deflator'!$B$5:$B$89,0))/100) -> 4.8589573 | G21: ='IEPR Gas Prices Real'!G21*(INDEX('GDP Deflator'!$C$5:$C$89,MATCH('IEPR Gas Prices Nominal'!$B21,'GDP Deflator'!$B$5:$B$89,0))/100) -> 0.90873263 | H21: ='IEPR Gas Prices Real'!H21*(INDEX('GDP Deflator'!$C$5:$C$89,MATCH('IEPR Gas Prices Nominal'!$B21,'GDP Deflator'!$B$5:$B$89,0))/100) -> 5.7676899 | I21: ='IEPR Gas Prices Real'!I21*(INDEX('GDP Deflator'!$C$5:$C$89,MATCH('IEPR Gas Prices Nominal'!$B21,'GDP Deflator'!$B$5:$B$89,0))/100) -> 5.115224 | J21: ='IEPR Gas Prices Real'!J21*(INDEX('GDP Deflator'!$C$5:$C$89,MATCH('IEPR Gas Prices Nominal'!$B21,'GDP Deflator'!$B$5:$B$89,0))/100) -> 1.5005373 | K21: ='IEPR Gas Prices Real'!K21*(INDEX('GDP Deflator'!$C$5:$C$89,MATCH('IEPR Gas Prices Nominal'!$B21,'GDP Deflator'!$B$5:$B$89,0))/100) -> 6.6157613 | L21: ='IEPR Gas Prices Real'!L21*(INDEX('GDP Deflator'!$C$5:$C$89,MATCH('IEPR Gas Prices Nominal'!$B21,'GDP Deflator'!$B$5:$B$89,0))/100) -> 5.292219 | M21: ='IEPR Gas Prices Real'!M21*(INDEX('GDP Deflator'!$C$5:$C$89,MATCH('IEPR Gas Prices Nominal'!$B21,'GDP Deflator'!$B$5:$B$89,0))/100) -> 0.70863489 | N21: ='IEPR Gas Prices Real'!N21*(INDEX('GDP Deflator'!$C$5:$C$89,MATCH('IEPR Gas Prices Nominal'!$B21,'GDP Deflator'!$B$5:$B$89,0))/100) -> 6.0008539 | P21: =AVERAGE(F21,I21,L21) -> 5.0888001 | Q21: =AVERAGE(H21,K21,N21) -> 6.1281017 | S21: 1 | T21: =INDEX($Q$6:$Q$401,MATCH(_xlfn.CONCAT($S21,"-",T$20),$E$6:$E$401,0)) -> 6.8456164 | U21: =INDEX($Q$6:$Q$401,MATCH(_xlfn.CONCAT($S21,"-",U$20),$E$6:$E$401,0)) -> 6.8940993 | V21: =INDEX($Q$6:$Q$401,MATCH(_xlfn.CONCAT($S21,"-",V$20),$E$6:$E$401,0)) -> 7.1157384 | W21: =INDEX($Q$6:$Q$401,MATCH(_xlfn.CONCAT($S21,"-",W$20),$E$6:$E$401,0)) -> 7.3272471 | X21: =INDEX($Q$6:$Q$401,MATCH(_xlfn.CONCAT($S21,"-",X$20),$E$6:$E$401,0)) -> 7.530285 | Y21: =INDEX($Q$6:$Q$401,MATCH(_xlfn.CONCAT($S21,"-",Y$20),$E$6:$E$401,0)) -> 7.7379185 | Z21: =INDEX($Q$6:$Q$401,MATCH(_xlfn.CONCAT($S21,"-",Z$20),$E$6:$E$401,0)) -> 7.9536297 | AA21: =INDEX($Q$6:$Q$401,MATCH(_xlfn.CONCAT($S21,"-",AA$20),$E$6:$E$401,0)) -> 8.1777913 | ... AY21: =INDEX($Q$6:$Q$401,MATCH(_xlfn.CONCAT($S21,"-",AY$20),$E$6:$E$401,0)) -> 17.823852
B22: =YEAR(D22) -> 2023 | C22: =MONTH(D22) -> 5 | D22: 45047 | E22: =C22&"-"&B22 -> 5-2023 | F22: ='IEPR Gas Prices Real'!F22*(INDEX('GDP Deflator'!$C$5:$C$89,MATCH('IEPR Gas Prices Nominal'!$B22,'GDP Deflator'!$B$5:$B$89,0))/100) -> 5.0160357 | G22: ='IEPR Gas Prices Real'!G22*(INDEX('GDP Deflator'!$C$5:$C$89,MATCH('IEPR Gas Prices Nominal'!$B22,'GDP Deflator'!$B$5:$B$89,0))/100) -> 0.90873263 | H22: ='IEPR Gas Prices Real'!H22*(INDEX('GDP Deflator'!$C$5:$C$89,MATCH('IEPR Gas Prices Nominal'!$B22,'GDP Deflator'!$B$5:$B$89,0))/100) -> 5.9247683 | I22: ='IEPR Gas Prices Real'!I22*(INDEX('GDP Deflator'!$C$5:$C$89,MATCH('IEPR Gas Prices Nominal'!$B22,'GDP Deflator'!$B$5:$B$89,0))/100) -> 5.2807236 | J22: ='IEPR Gas Prices Real'!J22*(INDEX('GDP Deflator'!$C$5:$C$89,MATCH('IEPR Gas Prices Nominal'!$B22,'GDP Deflator'!$B$5:$B$89,0))/100) -> 1.5005373 | K22: ='IEPR Gas Prices Real'!K22*(INDEX('GDP Deflator'!$C$5:$C$89,MATCH('IEPR Gas Prices Nominal'!$B22,'GDP Deflator'!$B$5:$B$89,0))/100) -> 6.781261 | L22: ='IEPR Gas Prices Real'!L22*(INDEX('GDP Deflator'!$C$5:$C$89,MATCH('IEPR Gas Prices Nominal'!$B22,'GDP Deflator'!$B$5:$B$89,0))/100) -> 5.4638631 | M22: ='IEPR Gas Prices Real'!M22*(INDEX('GDP Deflator'!$C$5:$C$89,MATCH('IEPR Gas Prices Nominal'!$B22,'GDP Deflator'!$B$5:$B$89,0))/100) -> 0.70863489 | N22: ='IEPR Gas Prices Real'!N22*(INDEX('GDP Deflator'!$C$5:$C$89,MATCH('IEPR Gas Prices Nominal'!$B22,'GDP Deflator'!$B$5:$B$89,0))/100) -> 6.172498 | P22: =AVERAGE(F22,I22,L22) -> 5.2535408 | Q22: =AVERAGE(H22,K22,N22) -> 6.2928424 | S22: 2 | T22: =INDEX($Q$6:$Q$401,MATCH(_xlfn.CONCAT($S22,"-",T$20),$E$6:$E$401,0)) -> 6.7050751 | U22: =INDEX($Q$6:$Q$401,MATCH(_xlfn.CONCAT($S22,"-",U$20),$E$6:$E$401,0)) -> 6.7687525 | V22: =INDEX($Q$6:$Q$401,MATCH(_xlfn.CONCAT($S22,"-",V$20),$E$6:$E$401,0)) -> 6.9857197 | W22: =INDEX($Q$6:$Q$401,MATCH(_xlfn.CONCAT($S22,"-",W$20),$E$6:$E$401,0)) -> 7.1938593 | X22: =INDEX($Q$6:$Q$401,MATCH(_xlfn.CONCAT($S22,"-",X$20),$E$6:$E$401,0)) -> 7.394083 | Y22: =INDEX($Q$6:$Q$401,MATCH(_xlfn.CONCAT($S22,"-",Y$20),$E$6:$E$401,0)) -> 7.5991108 | Z22: =INDEX($Q$6:$Q$401,MATCH(_xlfn.CONCAT($S22,"-",Z$20),$E$6:$E$401,0)) -> 7.812081 | AA22: =INDEX($Q$6:$Q$401,MATCH(_xlfn.CONCAT($S22,"-",AA$20),$E$6:$E$401,0)) -> 8.0332898 | ... AY22: =INDEX($Q$6:$Q$401,MATCH(_xlfn.CONCAT($S22,"-",AY$20),$E$6:$E$401,0)) -> 17.584367
B23: =YEAR(D23) -> 2023 | C23: =MONTH(D23) -> 6 | D23: 45078 | E23: =C23&"-"&B23 -> 6-2023 | F23: ='IEPR Gas Prices Real'!F23*(INDEX('GDP Deflator'!$C$5:$C$89,MATCH('IEPR Gas Prices Nominal'!$B23,'GDP Deflator'!$B$5:$B$89,0))/100) -> 5.1333716 | G23: ='IEPR Gas Prices Real'!G23*(INDEX('GDP Deflator'!$C$5:$C$89,MATCH('IEPR Gas Prices Nominal'!$B23,'GDP Deflator'!$B$5:$B$89,0))/100) -> 0.90873263 | H23: ='IEPR Gas Prices Real'!H23*(INDEX('GDP Deflator'!$C$5:$C$89,MATCH('IEPR Gas Prices Nominal'!$B23,'GDP Deflator'!$B$5:$B$89,0))/100) -> 6.0421042 | I23: ='IEPR Gas Prices Real'!I23*(INDEX('GDP Deflator'!$C$5:$C$89,MATCH('IEPR Gas Prices Nominal'!$B23,'GDP Deflator'!$B$5:$B$89,0))/100) -> 5.4043918 | J23: ='IEPR Gas Prices Real'!J23*(INDEX('GDP Deflator'!$C$5:$C$89,MATCH('IEPR Gas Prices Nominal'!$B23,'GDP Deflator'!$B$5:$B$89,0))/100) -> 1.5005373 | K23: ='IEPR Gas Prices Real'!K23*(INDEX('GDP Deflator'!$C$5:$C$89,MATCH('IEPR Gas Prices Nominal'!$B23,'GDP Deflator'!$B$5:$B$89,0))/100) -> 6.9049292 | L23: ='IEPR Gas Prices Real'!L23*(INDEX('GDP Deflator'!$C$5:$C$89,MATCH('IEPR Gas Prices Nominal'!$B23,'GDP Deflator'!$B$5:$B$89,0))/100) -> 5.5922499 | M23: ='IEPR Gas Prices Real'!M23*(INDEX('GDP Deflator'!$C$5:$C$89,MATCH('IEPR Gas Prices Nominal'!$B23,'GDP Deflator'!$B$5:$B$89,0))/100) -> 0.70863489 | N23: ='IEPR Gas Prices Real'!N23*(INDEX('GDP Deflator'!$C$5:$C$89,MATCH('IEPR Gas Prices Nominal'!$B23,'GDP Deflator'!$B$5:$B$89,0))/100) -> 6.3008848 | P23: =AVERAGE(F23,I23,L23) -> 5.3766711 | Q23: =AVERAGE(H23,K23,N23) -> 6.4159727 | S23: 3 | T23: =INDEX($Q$6:$Q$401,MATCH(_xlfn.CONCAT($S23,"-",T$20),$E$6:$E$401,0)) -> 6.2283433 | U23: =INDEX($Q$6:$Q$401,MATCH(_xlfn.CONCAT($S23,"-",U$20),$E$6:$E$401,0)) -> 6.3058566 | V23: =INDEX($Q$6:$Q$401,MATCH(_xlfn.CONCAT($S23,"-",V$20),$E$6:$E$401,0)) -> 6.5096069 | W23: =INDEX($Q$6:$Q$401,MATCH(_xlfn.CONCAT($S23,"-",W$20),$E$6:$E$401,0)) -> 6.706508 | X23: =INDEX($Q$6:$Q$401,MATCH(_xlfn.CONCAT($S23,"-",X$20),$E$6:$E$401,0)) -> 6.89665 | Y23: =INDEX($Q$6:$Q$401,MATCH(_xlfn.CONCAT($S23,"-",Y$20),$E$6:$E$401,0)) -> 7.091763 | Z23: =INDEX($Q$6:$Q$401,MATCH(_xlfn.CONCAT($S23,"-",Z$20),$E$6:$E$401,0)) -> 7.2945079 | AA23: =INDEX($Q$6:$Q$401,MATCH(_xlfn.CONCAT($S23,"-",AA$20),$E$6:$E$401,0)) -> 7.5051224 | ... AY23: =INDEX($Q$6:$Q$401,MATCH(_xlfn.CONCAT($S23,"-",AY$20),$E$6:$E$401,0)) -> 16.707896
B24: =YEAR(D24) -> 2023 | C24: =MONTH(D24) -> 7 | D24: 45108 | E24: =C24&"-"&B24 -> 7-2023 | F24: ='IEPR Gas Prices Real'!F24*(INDEX('GDP Deflator'!$C$5:$C$89,MATCH('IEPR Gas Prices Nominal'!$B24,'GDP Deflator'!$B$5:$B$89,0))/100) -> 5.1616593 | G24: ='IEPR Gas Prices Real'!G24*(INDEX('GDP Deflator'!$C$5:$C$89,MATCH('IEPR Gas Prices Nominal'!$B24,'GDP Deflator'!$B$5:$B$89,0))/100) -> 0.90873263 | H24: ='IEPR Gas Prices Real'!H24*(INDEX('GDP Deflator'!$C$5:$C$89,MATCH('IEPR Gas Prices Nominal'!$B24,'GDP Deflator'!$B$5:$B$89,0))/100) -> 6.0703919 | I24: ='IEPR Gas Prices Real'!I24*(INDEX('GDP Deflator'!$C$5:$C$89,MATCH('IEPR Gas Prices Nominal'!$B24,'GDP Deflator'!$B$5:$B$89,0))/100) -> 5.4343151 | J24: ='IEPR Gas Prices Real'!J24*(INDEX('GDP Deflator'!$C$5:$C$89,MATCH('IEPR Gas Prices Nominal'!$B24,'GDP Deflator'!$B$5:$B$89,0))/100) -> 1.5005373 | K24: ='IEPR Gas Prices Real'!K24*(INDEX('GDP Deflator'!$C$5:$C$89,MATCH('IEPR Gas Prices Nominal'!$B24,'GDP Deflator'!$B$5:$B$89,0))/100) -> 6.9348524 | L24: ='IEPR Gas Prices Real'!L24*(INDEX('GDP Deflator'!$C$5:$C$89,MATCH('IEPR Gas Prices Nominal'!$B24,'GDP Deflator'!$B$5:$B$89,0))/100) -> 5.6236475 | M24: ='IEPR Gas Prices Real'!M24*(INDEX('GDP Deflator'!$C$5:$C$89,MATCH('IEPR Gas Prices Nominal'!$B24,'GDP Deflator'!$B$5:$B$89,0))/100) -> 0.70863489 | N24: ='IEPR Gas Prices Real'!N24*(INDEX('GDP Deflator'!$C$5:$C$89,MATCH('IEPR Gas Prices Nominal'!$B24,'GDP Deflator'!$B$5:$B$89,0))/100) -> 6.3322824 | P24: =AVERAGE(F24,I24,L24) -> 5.4065406 | Q24: =AVERAGE(H24,K24,N24) -> 6.4458423 | S24: 4 | T24: =INDEX($Q$6:$Q$401,MATCH(_xlfn.CONCAT($S24,"-",T$20),$E$6:$E$401,0)) -> 6.1281017 | U24: =INDEX($Q$6:$Q$401,MATCH(_xlfn.CONCAT($S24,"-",U$20),$E$6:$E$401,0)) -> 6.2187839 | V24: =INDEX($Q$6:$Q$401,MATCH(_xlfn.CONCAT($S24,"-",V$20),$E$6:$E$401,0)) -> 6.4190393 | W24: =INDEX($Q$6:$Q$401,MATCH(_xlfn.CONCAT($S24,"-",W$20),$E$6:$E$401,0)) -> 6.6135256 | X24: =INDEX($Q$6:$Q$401,MATCH(_xlfn.CONCAT($S24,"-",X$20),$E$6:$E$401,0)) -> 6.8016934 | Y24: =INDEX($Q$6:$Q$401,MATCH(_xlfn.CONCAT($S24,"-",Y$20),$E$6:$E$401,0)) -> 6.9950144 | Z24: =INDEX($Q$6:$Q$401,MATCH(_xlfn.CONCAT($S24,"-",Z$20),$E$6:$E$401,0)) -> 7.1958617 | AA24: =INDEX($Q$6:$Q$401,MATCH(_xlfn.CONCAT($S24,"-",AA$20),$E$6:$E$401,0)) -> 7.4044058 | ... AY24: =INDEX($Q$6:$Q$401,MATCH(_xlfn.CONCAT($S24,"-",AY$20),$E$6:$E$401,0)) -> 16.541048
B25: =YEAR(D25) -> 2023 | C25: =MONTH(D25) -> 8 | D25: 45139 | E25: =C25&"-"&B25 -> 8-2023 | F25: ='IEPR Gas Prices Real'!F25*(INDEX('GDP Deflator'!$C$5:$C$89,MATCH('IEPR Gas Prices Nominal'!$B25,'GDP Deflator'!$B$5:$B$89,0))/100) -> 5.1094477 | G25: ='IEPR Gas Prices Real'!G25*(INDEX('GDP Deflator'!$C$5:$C$89,MATCH('IEPR Gas Prices Nominal'!$B25,'GDP Deflator'!$B$5:$B$89,0))/100) -> 0.90873263 | H25: ='IEPR Gas Prices Real'!H25*(INDEX('GDP Deflator'!$C$5:$C$89,MATCH('IEPR Gas Prices Nominal'!$B25,'GDP Deflator'!$B$5:$B$89,0))/100) -> 6.0181803 | I25: ='IEPR Gas Prices Real'!I25*(INDEX('GDP Deflator'!$C$5:$C$89,MATCH('IEPR Gas Prices Nominal'!$B25,'GDP Deflator'!$B$5:$B$89,0))/100) -> 5.3794869 | J25: ='IEPR Gas Prices Real'!J25*(INDEX('GDP Deflator'!$C$5:$C$89,MATCH('IEPR Gas Prices Nominal'!$B25,'GDP Deflator'!$B$5:$B$89,0))/100) -> 1.5005373 | K25: ='IEPR Gas Prices Real'!K25*(INDEX('GDP Deflator'!$C$5:$C$89,MATCH('IEPR Gas Prices Nominal'!$B25,'GDP Deflator'!$B$5:$B$89,0))/100) -> 6.8800242 | L25: ='IEPR Gas Prices Real'!L25*(INDEX('GDP Deflator'!$C$5:$C$89,MATCH('IEPR Gas Prices Nominal'!$B25,'GDP Deflator'!$B$5:$B$89,0))/100) -> 5.567341 | M25: ='IEPR Gas Prices Real'!M25*(INDEX('GDP Deflator'!$C$5:$C$89,MATCH('IEPR Gas Prices Nominal'!$B25,'GDP Deflator'!$B$5:$B$89,0))/100) -> 0.70863489 | N25: ='IEPR Gas Prices Real'!N25*(INDEX('GDP Deflator'!$C$5:$C$89,MATCH('IEPR Gas Prices Nominal'!$B25,'GDP Deflator'!$B$5:$B$89,0))/100) -> 6.2759759 | P25: =AVERAGE(F25,I25,L25) -> 5.3520919 | Q25: =AVERAGE(H25,K25,N25) -> 6.3913935 | S25: 5 | T25: =INDEX($Q$6:$Q$401,MATCH(_xlfn.CONCAT($S25,"-",T$20),$E$6:$E$401,0)) -> 6.2928424 | U25: =INDEX($Q$6:$Q$401,MATCH(_xlfn.CONCAT($S25,"-",U$20),$E$6:$E$401,0)) -> 6.3981737 | V25: =INDEX($Q$6:$Q$401,MATCH(_xlfn.CONCAT($S25,"-",V$20),$E$6:$E$401,0)) -> 6.6016407 | W25: =INDEX($Q$6:$Q$401,MATCH(_xlfn.CONCAT($S25,"-",W$20),$E$6:$E$401,0)) -> 6.7999129 | X25: =INDEX($Q$6:$Q$401,MATCH(_xlfn.CONCAT($S25,"-",X$20),$E$6:$E$401,0)) -> 6.9918404 | Y25: =INDEX($Q$6:$Q$401,MATCH(_xlfn.CONCAT($S25,"-",Y$20),$E$6:$E$401,0)) -> 7.1891421 | Z25: =INDEX($Q$6:$Q$401,MATCH(_xlfn.CONCAT($S25,"-",Z$20),$E$6:$E$401,0)) -> 7.3940009 | AA25: =INDEX($Q$6:$Q$401,MATCH(_xlfn.CONCAT($S25,"-",AA$20),$E$6:$E$401,0)) -> 7.6065038 | ... AY25: =INDEX($Q$6:$Q$401,MATCH(_xlfn.CONCAT($S25,"-",AY$20),$E$6:$E$401,0)) -> 16.876962
B26: =YEAR(D26) -> 2023 | C26: =MONTH(D26) -> 9 | D26: 45170 | E26: =C26&"-"&B26 -> 9-2023 | F26: ='IEPR Gas Prices Real'!F26*(INDEX('GDP Deflator'!$C$5:$C$89,MATCH('IEPR Gas Prices Nominal'!$B26,'GDP Deflator'!$B$5:$B$89,0))/100) -> 5.1687995 | G26: ='IEPR Gas Prices Real'!G26*(INDEX('GDP Deflator'!$C$5:$C$89,MATCH('IEPR Gas Prices Nominal'!$B26,'GDP Deflator'!$B$5:$B$89,0))/100) -> 0.90873263 | H26: ='IEPR Gas Prices Real'!H26*(INDEX('GDP Deflator'!$C$5:$C$89,MATCH('IEPR Gas Prices Nominal'!$B26,'GDP Deflator'!$B$5:$B$89,0))/100) -> 6.0775321 | I26: ='IEPR Gas Prices Real'!I26*(INDEX('GDP Deflator'!$C$5:$C$89,MATCH('IEPR Gas Prices Nominal'!$B26,'GDP Deflator'!$B$5:$B$89,0))/100) -> 5.4421191 | J26: ='IEPR Gas Prices Real'!J26*(INDEX('GDP Deflator'!$C$5:$C$89,MATCH('IEPR Gas Prices Nominal'!$B26,'GDP Deflator'!$B$5:$B$89,0))/100) -> 1.5005373 | K26: ='IEPR Gas Prices Real'!K26*(INDEX('GDP Deflator'!$C$5:$C$89,MATCH('IEPR Gas Prices Nominal'!$B26,'GDP Deflator'!$B$5:$B$89,0))/100) -> 6.9426565 | L26: ='IEPR Gas Prices Real'!L26*(INDEX('GDP Deflator'!$C$5:$C$89,MATCH('IEPR Gas Prices Nominal'!$B26,'GDP Deflator'!$B$5:$B$89,0))/100) -> 5.6325994 | M26: ='IEPR Gas Prices Real'!M26*(INDEX('GDP Deflator'!$C$5:$C$89,MATCH('IEPR Gas Prices Nominal'!$B26,'GDP Deflator'!$B$5:$B$89,0))/100) -> 0.70863489 | N26: ='IEPR Gas Prices Real'!N26*(INDEX('GDP Deflator'!$C$5:$C$89,MATCH('IEPR Gas Prices Nominal'!$B26,'GDP Deflator'!$B$5:$B$89,0))/100) -> 6.3412343 | P26: =AVERAGE(F26,I26,L26) -> 5.414506 | Q26: =AVERAGE(H26,K26,N26) -> 6.4538076 | S26: 6 | T26: =INDEX($Q$6:$Q$401,MATCH(_xlfn.CONCAT($S26,"-",T$20),$E$6:$E$401,0)) -> 6.4159727 | U26: =INDEX($Q$6:$Q$401,MATCH(_xlfn.CONCAT($S26,"-",U$20),$E$6:$E$401,0)) -> 6.5364763 | V26: =INDEX($Q$6:$Q$401,MATCH(_xlfn.CONCAT($S26,"-",V$20),$E$6:$E$401,0)) -> 6.742049 | W26: =INDEX($Q$6:$Q$401,MATCH(_xlfn.CONCAT($S26,"-",W$20),$E$6:$E$401,0)) -> 6.9431296 | X26: =INDEX($Q$6:$Q$401,MATCH(_xlfn.CONCAT($S26,"-",X$20),$E$6:$E$401,0)) -> 7.1379272 | Y26: =INDEX($Q$6:$Q$401,MATCH(_xlfn.CONCAT($S26,"-",Y$20),$E$6:$E$401,0)) -> 7.3383245 | Z26: =INDEX($Q$6:$Q$401,MATCH(_xlfn.CONCAT($S26,"-",Z$20),$E$6:$E$401,0)) -> 7.5462856 | AA26: =INDEX($Q$6:$Q$401,MATCH(_xlfn.CONCAT($S26,"-",AA$20),$E$6:$E$401,0)) -> 7.7618122 | ... AY26: =INDEX($Q$6:$Q$401,MATCH(_xlfn.CONCAT($S26,"-",AY$20),$E$6:$E$401,0)) -> 17.135212
B27: =YEAR(D27) -> 2023 | C27: =MONTH(D27) -> 10 | D27: 45200 | E27: =C27&"-"&B27 -> 10-2023 | F27: ='IEPR Gas Prices Real'!F27*(INDEX('GDP Deflator'!$C$5:$C$89,MATCH('IEPR Gas Prices Nominal'!$B27,'GDP Deflator'!$B$5:$B$89,0))/100) -> 5.1265682 | G27: ='IEPR Gas Prices Real'!G27*(INDEX('GDP Deflator'!$C$5:$C$89,MATCH('IEPR Gas Prices Nominal'!$B27,'GDP Deflator'!$B$5:$B$89,0))/100) -> 0.90873263 | H27: ='IEPR Gas Prices Real'!H27*(INDEX('GDP Deflator'!$C$5:$C$89,MATCH('IEPR Gas Prices Nominal'!$B27,'GDP Deflator'!$B$5:$B$89,0))/100) -> 6.0353008 | I27: ='IEPR Gas Prices Real'!I27*(INDEX('GDP Deflator'!$C$5:$C$89,MATCH('IEPR Gas Prices Nominal'!$B27,'GDP Deflator'!$B$5:$B$89,0))/100) -> 5.397798 | J27: ='IEPR Gas Prices Real'!J27*(INDEX('GDP Deflator'!$C$5:$C$89,MATCH('IEPR Gas Prices Nominal'!$B27,'GDP Deflator'!$B$5:$B$89,0))/100) -> 1.5005373 | K27: ='IEPR Gas Prices Real'!K27*(INDEX('GDP Deflator'!$C$5:$C$89,MATCH('IEPR Gas Prices Nominal'!$B27,'GDP Deflator'!$B$5:$B$89,0))/100) -> 6.8983353 | L27: ='IEPR Gas Prices Real'!L27*(INDEX('GDP Deflator'!$C$5:$C$89,MATCH('IEPR Gas Prices Nominal'!$B27,'GDP Deflator'!$B$5:$B$89,0))/100) -> 5.5871646 | M27: ='IEPR Gas Prices Real'!M27*(INDEX('GDP Deflator'!$C$5:$C$89,MATCH('IEPR Gas Prices Nominal'!$B27,'GDP Deflator'!$B$5:$B$89,0))/100) -> 0.70863489 | N27: ='IEPR Gas Prices Real'!N27*(INDEX('GDP Deflator'!$C$5:$C$89,MATCH('IEPR Gas Prices Nominal'!$B27,'GDP Deflator'!$B$5:$B$89,0))/100) -> 6.2957995 | P27: =AVERAGE(F27,I27,L27) -> 5.3705103 | Q27: =AVERAGE(H27,K27,N27) -> 6.4098119 | S27: 7 | T27: =INDEX($Q$6:$Q$401,MATCH(_xlfn.CONCAT($S27,"-",T$20),$E$6:$E$401,0)) -> 6.4458423 | U27: =INDEX($Q$6:$Q$401,MATCH(_xlfn.CONCAT($S27,"-",U$20),$E$6:$E$401,0)) -> 6.5810613 | V27: =INDEX($Q$6:$Q$401,MATCH(_xlfn.CONCAT($S27,"-",V$20),$E$6:$E$401,0)) -> 6.786375 | W27: =INDEX($Q$6:$Q$401,MATCH(_xlfn.CONCAT($S27,"-",W$20),$E$6:$E$401,0)) -> 6.9880812 | X27: =INDEX($Q$6:$Q$401,MATCH(_xlfn.CONCAT($S27,"-",X$20),$E$6:$E$401,0)) -> 7.1837318 | Y27: =INDEX($Q$6:$Q$401,MATCH(_xlfn.CONCAT($S27,"-",Y$20),$E$6:$E$401,0)) -> 7.385195 | Z27: =INDEX($Q$6:$Q$401,MATCH(_xlfn.CONCAT($S27,"-",Z$20),$E$6:$E$401,0)) -> 7.5941801 | AA27: =INDEX($Q$6:$Q$401,MATCH(_xlfn.CONCAT($S27,"-",AA$20),$E$6:$E$401,0)) -> 7.8106093 | ... AY27: =INDEX($Q$6:$Q$401,MATCH(_xlfn.CONCAT($S27,"-",AY$20),$E$6:$E$401,0)) -> 17.216623
B28: =YEAR(D28) -> 2023 | C28: =MONTH(D28) -> 11 | D28: 45231 | E28: =C28&"-"&B28 -> 11-2023 | F28: ='IEPR Gas Prices Real'!F28*(INDEX('GDP Deflator'!$C$5:$C$89,MATCH('IEPR Gas Prices Nominal'!$B28,'GDP Deflator'!$B$5:$B$89,0))/100) -> 5.366896 | G28: ='IEPR Gas Prices Real'!G28*(INDEX('GDP Deflator'!$C$5:$C$89,MATCH('IEPR Gas Prices Nominal'!$B28,'GDP Deflator'!$B$5:$B$89,0))/100) -> 0.90873263 | H28: ='IEPR Gas Prices Real'!H28*(INDEX('GDP Deflator'!$C$5:$C$89,MATCH('IEPR Gas Prices Nominal'!$B28,'GDP Deflator'!$B$5:$B$89,0))/100) -> 6.2756287 | I28: ='IEPR Gas Prices Real'!I28*(INDEX('GDP Deflator'!$C$5:$C$89,MATCH('IEPR Gas Prices Nominal'!$B28,'GDP Deflator'!$B$5:$B$89,0))/100) -> 5.6509914 | J28: ='IEPR Gas Prices Real'!J28*(INDEX('GDP Deflator'!$C$5:$C$89,MATCH('IEPR Gas Prices Nominal'!$B28,'GDP Deflator'!$B$5:$B$89,0))/100) -> 1.5005373 | K28: ='IEPR Gas Prices Real'!K28*(INDEX('GDP Deflator'!$C$5:$C$89,MATCH('IEPR Gas Prices Nominal'!$B28,'GDP Deflator'!$B$5:$B$89,0))/100) -> 7.1515288 | L28: ='IEPR Gas Prices Real'!L28*(INDEX('GDP Deflator'!$C$5:$C$89,MATCH('IEPR Gas Prices Nominal'!$B28,'GDP Deflator'!$B$5:$B$89,0))/100) -> 5.849701 | M28: ='IEPR Gas Prices Real'!M28*(INDEX('GDP Deflator'!$C$5:$C$89,MATCH('IEPR Gas Prices Nominal'!$B28,'GDP Deflator'!$B$5:$B$89,0))/100) -> 0.70863489 | N28: ='IEPR Gas Prices Real'!N28*(INDEX('GDP Deflator'!$C$5:$C$89,MATCH('IEPR Gas Prices Nominal'!$B28,'GDP Deflator'!$B$5:$B$89,0))/100) -> 6.5583359 | P28: =AVERAGE(F28,I28,L28) -> 5.6225295 | Q28: =AVERAGE(H28,K28,N28) -> 6.6618311 | S28: 8 | T28: =INDEX($Q$6:$Q$401,MATCH(_xlfn.CONCAT($S28,"-",T$20),$E$6:$E$401,0)) -> 6.3913935 | U28: =INDEX($Q$6:$Q$401,MATCH(_xlfn.CONCAT($S28,"-",U$20),$E$6:$E$401,0)) -> 6.5402641 | V28: =INDEX($Q$6:$Q$401,MATCH(_xlfn.CONCAT($S28,"-",V$20),$E$6:$E$401,0)) -> 6.7432259 | W28: =INDEX($Q$6:$Q$401,MATCH(_xlfn.CONCAT($S28,"-",W$20),$E$6:$E$401,0)) -> 6.9435879 | X28: =INDEX($Q$6:$Q$401,MATCH(_xlfn.CONCAT($S28,"-",X$20),$E$6:$E$401,0)) -> 7.1382584 | Y28: =INDEX($Q$6:$Q$401,MATCH(_xlfn.CONCAT($S28,"-",Y$20),$E$6:$E$401,0)) -> 7.3389336 | Z28: =INDEX($Q$6:$Q$401,MATCH(_xlfn.CONCAT($S28,"-",Z$20),$E$6:$E$401,0)) -> 7.5470479 | AA28: =INDEX($Q$6:$Q$401,MATCH(_xlfn.CONCAT($S28,"-",AA$20),$E$6:$E$401,0)) -> 7.7624522 | ... AY28: =INDEX($Q$6:$Q$401,MATCH(_xlfn.CONCAT($S28,"-",AY$20),$E$6:$E$401,0)) -> 17.137045
B29: =YEAR(D29) -> 2023 | C29: =MONTH(D29) -> 12 | D29: 45261 | E29: =C29&"-"&B29 -> 12-2023 | F29: ='IEPR Gas Prices Real'!F29*(INDEX('GDP Deflator'!$C$5:$C$89,MATCH('IEPR Gas Prices Nominal'!$B29,'GDP Deflator'!$B$5:$B$89,0))/100) -> 5.3968961 | G29: ='IEPR Gas Prices Real'!G29*(INDEX('GDP Deflator'!$C$5:$C$89,MATCH('IEPR Gas Prices Nominal'!$B29,'GDP Deflator'!$B$5:$B$89,0))/100) -> 0.90873263 | H29: ='IEPR Gas Prices Real'!H29*(INDEX('GDP Deflator'!$C$5:$C$89,MATCH('IEPR Gas Prices Nominal'!$B29,'GDP Deflator'!$B$5:$B$89,0))/100) -> 6.3056287 | I29: ='IEPR Gas Prices Real'!I29*(INDEX('GDP Deflator'!$C$5:$C$89,MATCH('IEPR Gas Prices Nominal'!$B29,'GDP Deflator'!$B$5:$B$89,0))/100) -> 5.6827318 | J29: ='IEPR Gas Prices Real'!J29*(INDEX('GDP Deflator'!$C$5:$C$89,MATCH('IEPR Gas Prices Nominal'!$B29,'GDP Deflator'!$B$5:$B$89,0))/100) -> 1.5005373 | K29: ='IEPR Gas Prices Real'!K29*(INDEX('GDP Deflator'!$C$5:$C$89,MATCH('IEPR Gas Prices Nominal'!$B29,'GDP Deflator'!$B$5:$B$89,0))/100) -> 7.1832692 | L29: ='IEPR Gas Prices Real'!L29*(INDEX('GDP Deflator'!$C$5:$C$89,MATCH('IEPR Gas Prices Nominal'!$B29,'GDP Deflator'!$B$5:$B$89,0))/100) -> 5.8830228 | M29: ='IEPR Gas Prices Real'!M29*(INDEX('GDP Deflator'!$C$5:$C$89,MATCH('IEPR Gas Prices Nominal'!$B29,'GDP Deflator'!$B$5:$B$89,0))/100) -> 0.70863489 | N29: ='IEPR Gas Prices Real'!N29*(INDEX('GDP Deflator'!$C$5:$C$89,MATCH('IEPR Gas Prices Nominal'!$B29,'GDP Deflator'!$B$5:$B$89,0))/100) -> 6.5916577 | P29: =AVERAGE(F29,I29,L29) -> 5.6542169 | Q29: =AVERAGE(H29,K29,N29) -> 6.6935185 | S29: 9 | T29: =INDEX($Q$6:$Q$401,MATCH(_xlfn.CONCAT($S29,"-",T$20),$E$6:$E$401,0)) -> 6.4538076 | U29: =INDEX($Q$6:$Q$401,MATCH(_xlfn.CONCAT($S29,"-",U$20),$E$6:$E$401,0)) -> 6.6182137 | V29: =INDEX($Q$6:$Q$401,MATCH(_xlfn.CONCAT($S29,"-",V$20),$E$6:$E$401,0)) -> 6.8216956 | W29: =INDEX($Q$6:$Q$401,MATCH(_xlfn.CONCAT($S29,"-",W$20),$E$6:$E$401,0)) -> 7.0234416 | X29: =INDEX($Q$6:$Q$401,MATCH(_xlfn.CONCAT($S29,"-",X$20),$E$6:$E$401,0)) -> 7.2196783 | Y29: =INDEX($Q$6:$Q$401,MATCH(_xlfn.CONCAT($S29,"-",Y$20),$E$6:$E$401,0)) -> 7.4221466 | Z29: =INDEX($Q$6:$Q$401,MATCH(_xlfn.CONCAT($S29,"-",Z$20),$E$6:$E$401,0)) -> 7.6320264 | AA29: =INDEX($Q$6:$Q$401,MATCH(_xlfn.CONCAT($S29,"-",AA$20),$E$6:$E$401,0)) -> 7.8490836 | ... AY29: =INDEX($Q$6:$Q$401,MATCH(_xlfn.CONCAT($S29,"-",AY$20),$E$6:$E$401,0)) -> 17.28129
B30: =YEAR(D30) -> 2024 | C30: =MONTH(D30) -> 1 | D30: 45292 | E30: =C30&"-"&B30 -> 1-2024 | F30: ='IEPR Gas Prices Real'!F30*(INDEX('GDP Deflator'!$C$5:$C$89,MATCH('IEPR Gas Prices Nominal'!$B30,'GDP Deflator'!$B$5:$B$89,0))/100) -> 5.5252827 | G30: ='IEPR Gas Prices Real'!G30*(INDEX('GDP Deflator'!$C$5:$C$89,MATCH('IEPR Gas Prices Nominal'!$B30,'GDP Deflator'!$B$5:$B$89,0))/100) -> 0.96712376 | H30: ='IEPR Gas Prices Real'!H30*(INDEX('GDP Deflator'!$C$5:$C$89,MATCH('IEPR Gas Prices Nominal'!$B30,'GDP Deflator'!$B$5:$B$89,0))/100) -> 6.4924065 | I30: ='IEPR Gas Prices Real'!I30*(INDEX('GDP Deflator'!$C$5:$C$89,MATCH('IEPR Gas Prices Nominal'!$B30,'GDP Deflator'!$B$5:$B$89,0))/100) -> 5.8168268 | J30: ='IEPR Gas Prices Real'!J30*(INDEX('GDP Deflator'!$C$5:$C$89,MATCH('IEPR Gas Prices Nominal'!$B30,'GDP Deflator'!$B$5:$B$89,0))/100) -> 1.5969552 | K30: ='IEPR Gas Prices Real'!K30*(INDEX('GDP Deflator'!$C$5:$C$89,MATCH('IEPR Gas Prices Nominal'!$B30,'GDP Deflator'!$B$5:$B$89,0))/100) -> 7.4137821 | L30: ='IEPR Gas Prices Real'!L30*(INDEX('GDP Deflator'!$C$5:$C$89,MATCH('IEPR Gas Prices Nominal'!$B30,'GDP Deflator'!$B$5:$B$89,0))/100) -> 6.0219408 | M30: ='IEPR Gas Prices Real'!M30*(INDEX('GDP Deflator'!$C$5:$C$89,MATCH('IEPR Gas Prices Nominal'!$B30,'GDP Deflator'!$B$5:$B$89,0))/100) -> 0.75416863 | N30: ='IEPR Gas Prices Real'!N30*(INDEX('GDP Deflator'!$C$5:$C$89,MATCH('IEPR Gas Prices Nominal'!$B30,'GDP Deflator'!$B$5:$B$89,0))/100) -> 6.7761094 | P30: =AVERAGE(F30,I30,L30) -> 5.7880168 | Q30: =AVERAGE(H30,K30,N30) -> 6.8940993 | S30: 10 | T30: =INDEX($Q$6:$Q$401,MATCH(_xlfn.CONCAT($S30,"-",T$20),$E$6:$E$401,0)) -> 6.4098119 | U30: =INDEX($Q$6:$Q$401,MATCH(_xlfn.CONCAT($S30,"-",U$20),$E$6:$E$401,0)) -> 6.5879545 | V30: =INDEX($Q$6:$Q$401,MATCH(_xlfn.CONCAT($S30,"-",V$20),$E$6:$E$401,0)) -> 6.7893474 | W30: =INDEX($Q$6:$Q$401,MATCH(_xlfn.CONCAT($S30,"-",W$20),$E$6:$E$401,0)) -> 6.9899935 | X30: =INDEX($Q$6:$Q$401,MATCH(_xlfn.CONCAT($S30,"-",X$20),$E$6:$E$401,0)) -> 7.1854767 | Y30: =INDEX($Q$6:$Q$401,MATCH(_xlfn.CONCAT($S30,"-",Y$20),$E$6:$E$401,0)) -> 7.3873856 | Z30: =INDEX($Q$6:$Q$401,MATCH(_xlfn.CONCAT($S30,"-",Z$20),$E$6:$E$401,0)) -> 7.5966282 | AA30: =INDEX($Q$6:$Q$401,MATCH(_xlfn.CONCAT($S30,"-",AA$20),$E$6:$E$401,0)) -> 7.8128988 | ... AY30: =INDEX($Q$6:$Q$401,MATCH(_xlfn.CONCAT($S30,"-",AY$20),$E$6:$E$401,0)) -> 17.22159
B31: =YEAR(D31) -> 2024 | C31: =MONTH(D31) -> 2 | D31: 45323 | E31: =C31&"-"&B31 -> 2-2024 | F31: ='IEPR Gas Prices Real'!F31*(INDEX('GDP Deflator'!$C$5:$C$89,MATCH('IEPR Gas Prices Nominal'!$B31,'GDP Deflator'!$B$5:$B$89,0))/100) -> 5.4062867 | G31: ='IEPR Gas Prices Real'!G31*(INDEX('GDP Deflator'!$C$5:$C$89,MATCH('IEPR Gas Prices Nominal'!$B31,'GDP Deflator'!$B$5:$B$89,0))/100) -> 0.96712376 | H31: ='IEPR Gas Prices Real'!H31*(INDEX('GDP Deflator'!$C$5:$C$89,MATCH('IEPR Gas Prices Nominal'!$B31,'GDP Deflator'!$B$5:$B$89,0))/100) -> 6.3734105 | I31: ='IEPR Gas Prices Real'!I31*(INDEX('GDP Deflator'!$C$5:$C$89,MATCH('IEPR Gas Prices Nominal'!$B31,'GDP Deflator'!$B$5:$B$89,0))/100) -> 5.6904849 | J31: ='IEPR Gas Prices Real'!J31*(INDEX('GDP Deflator'!$C$5:$C$89,MATCH('IEPR Gas Prices Nominal'!$B31,'GDP Deflator'!$B$5:$B$89,0))/100) -> 1.5969552 | K31: ='IEPR Gas Prices Real'!K31*(INDEX('GDP Deflator'!$C$5:$C$89,MATCH('IEPR Gas Prices Nominal'!$B31,'GDP Deflator'!$B$5:$B$89,0))/100) -> 7.2874401 | L31: ='IEPR Gas Prices Real'!L31*(INDEX('GDP Deflator'!$C$5:$C$89,MATCH('IEPR Gas Prices Nominal'!$B31,'GDP Deflator'!$B$5:$B$89,0))/100) -> 5.8912383 | M31: ='IEPR Gas Prices Real'!M31*(INDEX('GDP Deflator'!$C$5:$C$89,MATCH('IEPR Gas Prices Nominal'!$B31,'GDP Deflator'!$B$5:$B$89,0))/100) -> 0.75416863 | N31: ='IEPR Gas Prices Real'!N31*(INDEX('GDP Deflator'!$C$5:$C$89,MATCH('IEPR Gas Prices Nominal'!$B31,'GDP Deflator'!$B$5:$B$89,0))/100) -> 6.645407 | P31: =AVERAGE(F31,I31,L31) -> 5.66267 | Q31: =AVERAGE(H31,K31,N31) -> 6.7687525 | S31: 11 | T31: =INDEX($Q$6:$Q$401,MATCH(_xlfn.CONCAT($S31,"-",T$20),$E$6:$E$401,0)) -> 6.6618311 | U31: =INDEX($Q$6:$Q$401,MATCH(_xlfn.CONCAT($S31,"-",U$20),$E$6:$E$401,0)) -> 6.8604851 | V31: =INDEX($Q$6:$Q$401,MATCH(_xlfn.CONCAT($S31,"-",V$20),$E$6:$E$401,0)) -> 7.0669235 | W31: =INDEX($Q$6:$Q$401,MATCH(_xlfn.CONCAT($S31,"-",W$20),$E$6:$E$401,0)) -> 7.2733707 | X31: =INDEX($Q$6:$Q$401,MATCH(_xlfn.CONCAT($S31,"-",X$20),$E$6:$E$401,0)) -> 7.4745787 | Y31: =INDEX($Q$6:$Q$401,MATCH(_xlfn.CONCAT($S31,"-",Y$20),$E$6:$E$401,0)) -> 7.6825229 | Z31: =INDEX($Q$6:$Q$401,MATCH(_xlfn.CONCAT($S31,"-",Z$20),$E$6:$E$401,0)) -> 7.8978557 | AA31: =INDEX($Q$6:$Q$401,MATCH(_xlfn.CONCAT($S31,"-",AA$20),$E$6:$E$401,0)) -> 8.1201533 | ... AY31: =INDEX($Q$6:$Q$401,MATCH(_xlfn.CONCAT($S31,"-",AY$20),$E$6:$E$401,0)) -> 17.732241
B32: =YEAR(D32) -> 2024 | C32: =MONTH(D32) -> 3 | D32: 45352 | E32: =C32&"-"&B32 -> 3-2024 | F32: ='IEPR Gas Prices Real'!F32*(INDEX('GDP Deflator'!$C$5:$C$89,MATCH('IEPR Gas Prices Nominal'!$B32,'GDP Deflator'!$B$5:$B$89,0))/100) -> 4.9649556 | G32: ='IEPR Gas Prices Real'!G32*(INDEX('GDP Deflator'!$C$5:$C$89,MATCH('IEPR Gas Prices Nominal'!$B32,'GDP Deflator'!$B$5:$B$89,0))/100) -> 0.96712376 | H32: ='IEPR Gas Prices Real'!H32*(INDEX('GDP Deflator'!$C$5:$C$89,MATCH('IEPR Gas Prices Nominal'!$B32,'GDP Deflator'!$B$5:$B$89,0))/100) -> 5.9320793 | I32: ='IEPR Gas Prices Real'!I32*(INDEX('GDP Deflator'!$C$5:$C$89,MATCH('IEPR Gas Prices Nominal'!$B32,'GDP Deflator'!$B$5:$B$89,0))/100) -> 5.2249745 | J32: ='IEPR Gas Prices Real'!J32*(INDEX('GDP Deflator'!$C$5:$C$89,MATCH('IEPR Gas Prices Nominal'!$B32,'GDP Deflator'!$B$5:$B$89,0))/100) -> 1.5969552 | K32: ='IEPR Gas Prices Real'!K32*(INDEX('GDP Deflator'!$C$5:$C$89,MATCH('IEPR Gas Prices Nominal'!$B32,'GDP Deflator'!$B$5:$B$89,0))/100) -> 6.8219297 | L32: ='IEPR Gas Prices Real'!L32*(INDEX('GDP Deflator'!$C$5:$C$89,MATCH('IEPR Gas Prices Nominal'!$B32,'GDP Deflator'!$B$5:$B$89,0))/100) -> 5.4093922 | M32: ='IEPR Gas Prices Real'!M32*(INDEX('GDP Deflator'!$C$5:$C$89,MATCH('IEPR Gas Prices Nominal'!$B32,'GDP Deflator'!$B$5:$B$89,0))/100) -> 0.75416863 | N32: ='IEPR Gas Prices Real'!N32*(INDEX('GDP Deflator'!$C$5:$C$89,MATCH('IEPR Gas Prices Nominal'!$B32,'GDP Deflator'!$B$5:$B$89,0))/100) -> 6.1635608 | P32: =AVERAGE(F32,I32,L32) -> 5.1997741 | Q32: =AVERAGE(H32,K32,N32) -> 6.3058566 | S32: 12 | T32: =INDEX($Q$6:$Q$401,MATCH(_xlfn.CONCAT($S32,"-",T$20),$E$6:$E$401,0)) -> 6.6935185 | U32: =INDEX($Q$6:$Q$401,MATCH(_xlfn.CONCAT($S32,"-",U$20),$E$6:$E$401,0)) -> 6.9083623 | V32: =INDEX($Q$6:$Q$401,MATCH(_xlfn.CONCAT($S32,"-",V$20),$E$6:$E$401,0)) -> 7.1144855 | W32: =INDEX($Q$6:$Q$401,MATCH(_xlfn.CONCAT($S32,"-",W$20),$E$6:$E$401,0)) -> 7.3215936 | X32: =INDEX($Q$6:$Q$401,MATCH(_xlfn.CONCAT($S32,"-",X$20),$E$6:$E$401,0)) -> 7.5237146 | Y32: =INDEX($Q$6:$Q$401,MATCH(_xlfn.CONCAT($S32,"-",Y$20),$E$6:$E$401,0)) -> 7.732806 | Z32: =INDEX($Q$6:$Q$401,MATCH(_xlfn.CONCAT($S32,"-",Z$20),$E$6:$E$401,0)) -> 7.9492394 | AA32: =INDEX($Q$6:$Q$401,MATCH(_xlfn.CONCAT($S32,"-",AA$20),$E$6:$E$401,0)) -> 8.1725036 | ... AY32: =INDEX($Q$6:$Q$401,MATCH(_xlfn.CONCAT($S32,"-",AY$20),$E$6:$E$401,0)) -> 17.819591
B33: =YEAR(D33) -> 2024 | C33: =MONTH(D33) -> 4 | D33: 45383 | E33: =C33&"-"&B33 -> 4-2024 | F33: ='IEPR Gas Prices Real'!F33*(INDEX('GDP Deflator'!$C$5:$C$89,MATCH('IEPR Gas Prices Nominal'!$B33,'GDP Deflator'!$B$5:$B$89,0))/100) -> 4.8824112 | G33: ='IEPR Gas Prices Real'!G33*(INDEX('GDP Deflator'!$C$5:$C$89,MATCH('IEPR Gas Prices Nominal'!$B33,'GDP Deflator'!$B$5:$B$89,0))/100) -> 0.96712376 | H33: ='IEPR Gas Prices Real'!H33*(INDEX('GDP Deflator'!$C$5:$C$89,MATCH('IEPR Gas Prices Nominal'!$B33,'GDP Deflator'!$B$5:$B$89,0))/100) -> 5.849535 | I33: ='IEPR Gas Prices Real'!I33*(INDEX('GDP Deflator'!$C$5:$C$89,MATCH('IEPR Gas Prices Nominal'!$B33,'GDP Deflator'!$B$5:$B$89,0))/100) -> 5.1371449 | J33: ='IEPR Gas Prices Real'!J33*(INDEX('GDP Deflator'!$C$5:$C$89,MATCH('IEPR Gas Prices Nominal'!$B33,'GDP Deflator'!$B$5:$B$89,0))/100) -> 1.5969552 | K33: ='IEPR Gas Prices Real'!K33*(INDEX('GDP Deflator'!$C$5:$C$89,MATCH('IEPR Gas Prices Nominal'!$B33,'GDP Deflator'!$B$5:$B$89,0))/100) -> 6.7341001 | L33: ='IEPR Gas Prices Real'!L33*(INDEX('GDP Deflator'!$C$5:$C$89,MATCH('IEPR Gas Prices Nominal'!$B33,'GDP Deflator'!$B$5:$B$89,0))/100) -> 5.3185479 | M33: ='IEPR Gas Prices Real'!M33*(INDEX('GDP Deflator'!$C$5:$C$89,MATCH('IEPR Gas Prices Nominal'!$B33,'GDP Deflator'!$B$5:$B$89,0))/100) -> 0.75416863 | N33: ='IEPR Gas Prices Real'!N33*(INDEX('GDP Deflator'!$C$5:$C$89,MATCH('IEPR Gas Prices Nominal'!$B33,'GDP Deflator'!$B$5:$B$89,0))/100) -> 6.0727166 | P33: =AVERAGE(F33,I33,L33) -> 5.1127013 | Q33: =AVERAGE(H33,K33,N33) -> 6.2187839
B34: =YEAR(D34) -> 2024 | C34: =MONTH(D34) -> 5 | D34: 45413 | E34: =C34&"-"&B34 -> 5-2024 | F34: ='IEPR Gas Prices Real'!F34*(INDEX('GDP Deflator'!$C$5:$C$89,MATCH('IEPR Gas Prices Nominal'!$B34,'GDP Deflator'!$B$5:$B$89,0))/100) -> 5.0543376 | G34: ='IEPR Gas Prices Real'!G34*(INDEX('GDP Deflator'!$C$5:$C$89,MATCH('IEPR Gas Prices Nominal'!$B34,'GDP Deflator'!$B$5:$B$89,0))/100) -> 0.96712376 | H34: ='IEPR Gas Prices Real'!H34*(INDEX('GDP Deflator'!$C$5:$C$89,MATCH('IEPR Gas Prices Nominal'!$B34,'GDP Deflator'!$B$5:$B$89,0))/100) -> 6.0214614 | I34: ='IEPR Gas Prices Real'!I34*(INDEX('GDP Deflator'!$C$5:$C$89,MATCH('IEPR Gas Prices Nominal'!$B34,'GDP Deflator'!$B$5:$B$89,0))/100) -> 5.3170459 | J34: ='IEPR Gas Prices Real'!J34*(INDEX('GDP Deflator'!$C$5:$C$89,MATCH('IEPR Gas Prices Nominal'!$B34,'GDP Deflator'!$B$5:$B$89,0))/100) -> 1.5969552 | K34: ='IEPR Gas Prices Real'!K34*(INDEX('GDP Deflator'!$C$5:$C$89,MATCH('IEPR Gas Prices Nominal'!$B34,'GDP Deflator'!$B$5:$B$89,0))/100) -> 6.9140011 | L34: ='IEPR Gas Prices Real'!L34*(INDEX('GDP Deflator'!$C$5:$C$89,MATCH('IEPR Gas Prices Nominal'!$B34,'GDP Deflator'!$B$5:$B$89,0))/100) -> 5.5048899 | M34: ='IEPR Gas Prices Real'!M34*(INDEX('GDP Deflator'!$C$5:$C$89,MATCH('IEPR Gas Prices Nominal'!$B34,'GDP Deflator'!$B$5:$B$89,0))/100) -> 0.75416863 | N34: ='IEPR Gas Prices Real'!N34*(INDEX('GDP Deflator'!$C$5:$C$89,MATCH('IEPR Gas Prices Nominal'!$B34,'GDP Deflator'!$B$5:$B$89,0))/100) -> 6.2590585 | P34: =AVERAGE(F34,I34,L34) -> 5.2920912 | Q34: =AVERAGE(H34,K34,N34) -> 6.3981737
B35: =YEAR(D35) -> 2024 | C35: =MONTH(D35) -> 6 | D35: 45444 | E35: =C35&"-"&B35 -> 6-2024 | F35: ='IEPR Gas Prices Real'!F35*(INDEX('GDP Deflator'!$C$5:$C$89,MATCH('IEPR Gas Prices Nominal'!$B35,'GDP Deflator'!$B$5:$B$89,0))/100) -> 5.1870595 | G35: ='IEPR Gas Prices Real'!G35*(INDEX('GDP Deflator'!$C$5:$C$89,MATCH('IEPR Gas Prices Nominal'!$B35,'GDP Deflator'!$B$5:$B$89,0))/100) -> 0.96712376 | H35: ='IEPR Gas Prices Real'!H35*(INDEX('GDP Deflator'!$C$5:$C$89,MATCH('IEPR Gas Prices Nominal'!$B35,'GDP Deflator'!$B$5:$B$89,0))/100) -> 6.1541833 | I35: ='IEPR Gas Prices Real'!I35*(INDEX('GDP Deflator'!$C$5:$C$89,MATCH('IEPR Gas Prices Nominal'!$B35,'GDP Deflator'!$B$5:$B$89,0))/100) -> 5.4556453 | J35: ='IEPR Gas Prices Real'!J35*(INDEX('GDP Deflator'!$C$5:$C$89,MATCH('IEPR Gas Prices Nominal'!$B35,'GDP Deflator'!$B$5:$B$89,0))/100) -> 1.5969552 | K35: ='IEPR Gas Prices Real'!K35*(INDEX('GDP Deflator'!$C$5:$C$89,MATCH('IEPR Gas Prices Nominal'!$B35,'GDP Deflator'!$B$5:$B$89,0))/100) -> 7.0526005 | L35: ='IEPR Gas Prices Real'!L35*(INDEX('GDP Deflator'!$C$5:$C$89,MATCH('IEPR Gas Prices Nominal'!$B35,'GDP Deflator'!$B$5:$B$89,0))/100) -> 5.6484764 | M35: ='IEPR Gas Prices Real'!M35*(INDEX('GDP Deflator'!$C$5:$C$89,MATCH('IEPR Gas Prices Nominal'!$B35,'GDP Deflator'!$B$5:$B$89,0))/100) -> 0.75416863 | N35: ='IEPR Gas Prices Real'!N35*(INDEX('GDP Deflator'!$C$5:$C$89,MATCH('IEPR Gas Prices Nominal'!$B35,'GDP Deflator'!$B$5:$B$89,0))/100) -> 6.4026451 | P35: =AVERAGE(F35,I35,L35) -> 5.4303937 | Q35: =AVERAGE(H35,K35,N35) -> 6.5364763
B36: =YEAR(D36) -> 2024 | C36: =MONTH(D36) -> 7 | D36: 45474 | E36: =C36&"-"&B36 -> 7-2024 | F36: ='IEPR Gas Prices Real'!F36*(INDEX('GDP Deflator'!$C$5:$C$89,MATCH('IEPR Gas Prices Nominal'!$B36,'GDP Deflator'!$B$5:$B$89,0))/100) -> 5.2302843 | G36: ='IEPR Gas Prices Real'!G36*(INDEX('GDP Deflator'!$C$5:$C$89,MATCH('IEPR Gas Prices Nominal'!$B36,'GDP Deflator'!$B$5:$B$89,0))/100) -> 0.96712376 | H36: ='IEPR Gas Prices Real'!H36*(INDEX('GDP Deflator'!$C$5:$C$89,MATCH('IEPR Gas Prices Nominal'!$B36,'GDP Deflator'!$B$5:$B$89,0))/100) -> 6.197408 | I36: ='IEPR Gas Prices Real'!I36*(INDEX('GDP Deflator'!$C$5:$C$89,MATCH('IEPR Gas Prices Nominal'!$B36,'GDP Deflator'!$B$5:$B$89,0))/100) -> 5.5000796 | J36: ='IEPR Gas Prices Real'!J36*(INDEX('GDP Deflator'!$C$5:$C$89,MATCH('IEPR Gas Prices Nominal'!$B36,'GDP Deflator'!$B$5:$B$89,0))/100) -> 1.5969552 | K36: ='IEPR Gas Prices Real'!K36*(INDEX('GDP Deflator'!$C$5:$C$89,MATCH('IEPR Gas Prices Nominal'!$B36,'GDP Deflator'!$B$5:$B$89,0))/100) -> 7.0970348 | L36: ='IEPR Gas Prices Real'!L36*(INDEX('GDP Deflator'!$C$5:$C$89,MATCH('IEPR Gas Prices Nominal'!$B36,'GDP Deflator'!$B$5:$B$89,0))/100) -> 5.6945725 | M36: ='IEPR Gas Prices Real'!M36*(INDEX('GDP Deflator'!$C$5:$C$89,MATCH('IEPR Gas Prices Nominal'!$B36,'GDP Deflator'!$B$5:$B$89,0))/100) -> 0.75416863 | N36: ='IEPR Gas Prices Real'!N36*(INDEX('GDP Deflator'!$C$5:$C$89,MATCH('IEPR Gas Prices Nominal'!$B36,'GDP Deflator'!$B$5:$B$89,0))/100) -> 6.4487412 | P36: =AVERAGE(F36,I36,L36) -> 5.4749788 | Q36: =AVERAGE(H36,K36,N36) -> 6.5810613
B37: =YEAR(D37) -> 2024 | C37: =MONTH(D37) -> 8 | D37: 45505 | E37: =C37&"-"&B37 -> 8-2024 | F37: ='IEPR Gas Prices Real'!F37*(INDEX('GDP Deflator'!$C$5:$C$89,MATCH('IEPR Gas Prices Nominal'!$B37,'GDP Deflator'!$B$5:$B$89,0))/100) -> 5.1919429 | G37: ='IEPR Gas Prices Real'!G37*(INDEX('GDP Deflator'!$C$5:$C$89,MATCH('IEPR Gas Prices Nominal'!$B37,'GDP Deflator'!$B$5:$B$89,0))/100) -> 0.96712376 | H37: ='IEPR Gas Prices Real'!H37*(INDEX('GDP Deflator'!$C$5:$C$89,MATCH('IEPR Gas Prices Nominal'!$B37,'GDP Deflator'!$B$5:$B$89,0))/100) -> 6.1590667 | I37: ='IEPR Gas Prices Real'!I37*(INDEX('GDP Deflator'!$C$5:$C$89,MATCH('IEPR Gas Prices Nominal'!$B37,'GDP Deflator'!$B$5:$B$89,0))/100) -> 5.45874 | J37: ='IEPR Gas Prices Real'!J37*(INDEX('GDP Deflator'!$C$5:$C$89,MATCH('IEPR Gas Prices Nominal'!$B37,'GDP Deflator'!$B$5:$B$89,0))/100) -> 1.5969552 | K37: ='IEPR Gas Prices Real'!K37*(INDEX('GDP Deflator'!$C$5:$C$89,MATCH('IEPR Gas Prices Nominal'!$B37,'GDP Deflator'!$B$5:$B$89,0))/100) -> 7.0556952 | L37: ='IEPR Gas Prices Real'!L37*(INDEX('GDP Deflator'!$C$5:$C$89,MATCH('IEPR Gas Prices Nominal'!$B37,'GDP Deflator'!$B$5:$B$89,0))/100) -> 5.6518617 | M37: ='IEPR Gas Prices Real'!M37*(INDEX('GDP Deflator'!$C$5:$C$89,MATCH('IEPR Gas Prices Nominal'!$B37,'GDP Deflator'!$B$5:$B$89,0))/100) -> 0.75416863 | N37: ='IEPR Gas Prices Real'!N37*(INDEX('GDP Deflator'!$C$5:$C$89,MATCH('IEPR Gas Prices Nominal'!$B37,'GDP Deflator'!$B$5:$B$89,0))/100) -> 6.4060303 | P37: =AVERAGE(F37,I37,L37) -> 5.4341815 | Q37: =AVERAGE(H37,K37,N37) -> 6.5402641
B38: =YEAR(D38) -> 2024 | C38: =MONTH(D38) -> 9 | D38: 45536 | E38: =C38&"-"&B38 -> 9-2024 | F38: ='IEPR Gas Prices Real'!F38*(INDEX('GDP Deflator'!$C$5:$C$89,MATCH('IEPR Gas Prices Nominal'!$B38,'GDP Deflator'!$B$5:$B$89,0))/100) -> 5.2670591 | G38: ='IEPR Gas Prices Real'!G38*(INDEX('GDP Deflator'!$C$5:$C$89,MATCH('IEPR Gas Prices Nominal'!$B38,'GDP Deflator'!$B$5:$B$89,0))/100) -> 0.96712376 | H38: ='IEPR Gas Prices Real'!H38*(INDEX('GDP Deflator'!$C$5:$C$89,MATCH('IEPR Gas Prices Nominal'!$B38,'GDP Deflator'!$B$5:$B$89,0))/100) -> 6.2341828 | I38: ='IEPR Gas Prices Real'!I38*(INDEX('GDP Deflator'!$C$5:$C$89,MATCH('IEPR Gas Prices Nominal'!$B38,'GDP Deflator'!$B$5:$B$89,0))/100) -> 5.5366817 | J38: ='IEPR Gas Prices Real'!J38*(INDEX('GDP Deflator'!$C$5:$C$89,MATCH('IEPR Gas Prices Nominal'!$B38,'GDP Deflator'!$B$5:$B$89,0))/100) -> 1.5969552 | K38: ='IEPR Gas Prices Real'!K38*(INDEX('GDP Deflator'!$C$5:$C$89,MATCH('IEPR Gas Prices Nominal'!$B38,'GDP Deflator'!$B$5:$B$89,0))/100) -> 7.1336369 | L38: ='IEPR Gas Prices Real'!L38*(INDEX('GDP Deflator'!$C$5:$C$89,MATCH('IEPR Gas Prices Nominal'!$B38,'GDP Deflator'!$B$5:$B$89,0))/100) -> 5.7326527 | M38: ='IEPR Gas Prices Real'!M38*(INDEX('GDP Deflator'!$C$5:$C$89,MATCH('IEPR Gas Prices Nominal'!$B38,'GDP Deflator'!$B$5:$B$89,0))/100) -> 0.75416863 | N38: ='IEPR Gas Prices Real'!N38*(INDEX('GDP Deflator'!$C$5:$C$89,MATCH('IEPR Gas Prices Nominal'!$B38,'GDP Deflator'!$B$5:$B$89,0))/100) -> 6.4868213 | P38: =AVERAGE(F38,I38,L38) -> 5.5121311 | Q38: =AVERAGE(H38,K38,N38) -> 6.6182137
B39: =YEAR(D39) -> 2024 | C39: =MONTH(D39) -> 10 | D39: 45566 | E39: =C39&"-"&B39 -> 10-2024 | F39: ='IEPR Gas Prices Real'!F39*(INDEX('GDP Deflator'!$C$5:$C$89,MATCH('IEPR Gas Prices Nominal'!$B39,'GDP Deflator'!$B$5:$B$89,0))/100) -> 5.2387827 | G39: ='IEPR Gas Prices Real'!G39*(INDEX('GDP Deflator'!$C$5:$C$89,MATCH('IEPR Gas Prices Nominal'!$B39,'GDP Deflator'!$B$5:$B$89,0))/100) -> 0.96712376 | H39: ='IEPR Gas Prices Real'!H39*(INDEX('GDP Deflator'!$C$5:$C$89,MATCH('IEPR Gas Prices Nominal'!$B39,'GDP Deflator'!$B$5:$B$89,0))/100) -> 6.2059065 | I39: ='IEPR Gas Prices Real'!I39*(INDEX('GDP Deflator'!$C$5:$C$89,MATCH('IEPR Gas Prices Nominal'!$B39,'GDP Deflator'!$B$5:$B$89,0))/100) -> 5.5059296 | J39: ='IEPR Gas Prices Real'!J39*(INDEX('GDP Deflator'!$C$5:$C$89,MATCH('IEPR Gas Prices Nominal'!$B39,'GDP Deflator'!$B$5:$B$89,0))/100) -> 1.5969552 | K39: ='IEPR Gas Prices Real'!K39*(INDEX('GDP Deflator'!$C$5:$C$89,MATCH('IEPR Gas Prices Nominal'!$B39,'GDP Deflator'!$B$5:$B$89,0))/100) -> 7.1028849 | L39: ='IEPR Gas Prices Real'!L39*(INDEX('GDP Deflator'!$C$5:$C$89,MATCH('IEPR Gas Prices Nominal'!$B39,'GDP Deflator'!$B$5:$B$89,0))/100) -> 5.7009035 | M39: ='IEPR Gas Prices Real'!M39*(INDEX('GDP Deflator'!$C$5:$C$89,MATCH('IEPR Gas Prices Nominal'!$B39,'GDP Deflator'!$B$5:$B$89,0))/100) -> 0.75416863 | N39: ='IEPR Gas Prices Real'!N39*(INDEX('GDP Deflator'!$C$5:$C$89,MATCH('IEPR Gas Prices Nominal'!$B39,'GDP Deflator'!$B$5:$B$89,0))/100) -> 6.4550721 | P39: =AVERAGE(F39,I39,L39) -> 5.4818719 | Q39: =AVERAGE(H39,K39,N39) -> 6.5879545
B40: =YEAR(D40) -> 2024 | C40: =MONTH(D40) -> 11 | D40: 45597 | E40: =C40&"-"&B40 -> 11-2024 | F40: ='IEPR Gas Prices Real'!F40*(INDEX('GDP Deflator'!$C$5:$C$89,MATCH('IEPR Gas Prices Nominal'!$B40,'GDP Deflator'!$B$5:$B$89,0))/100) -> 5.499897 | G40: ='IEPR Gas Prices Real'!G40*(INDEX('GDP Deflator'!$C$5:$C$89,MATCH('IEPR Gas Prices Nominal'!$B40,'GDP Deflator'!$B$5:$B$89,0))/100) -> 0.96712376 | H40: ='IEPR Gas Prices Real'!H40*(INDEX('GDP Deflator'!$C$5:$C$89,MATCH('IEPR Gas Prices Nominal'!$B40,'GDP Deflator'!$B$5:$B$89,0))/100) -> 6.4670208 | I40: ='IEPR Gas Prices Real'!I40*(INDEX('GDP Deflator'!$C$5:$C$89,MATCH('IEPR Gas Prices Nominal'!$B40,'GDP Deflator'!$B$5:$B$89,0))/100) -> 5.7792806 | J40: ='IEPR Gas Prices Real'!J40*(INDEX('GDP Deflator'!$C$5:$C$89,MATCH('IEPR Gas Prices Nominal'!$B40,'GDP Deflator'!$B$5:$B$89,0))/100) -> 1.5969552 | K40: ='IEPR Gas Prices Real'!K40*(INDEX('GDP Deflator'!$C$5:$C$89,MATCH('IEPR Gas Prices Nominal'!$B40,'GDP Deflator'!$B$5:$B$89,0))/100) -> 7.3762358 | L40: ='IEPR Gas Prices Real'!L40*(INDEX('GDP Deflator'!$C$5:$C$89,MATCH('IEPR Gas Prices Nominal'!$B40,'GDP Deflator'!$B$5:$B$89,0))/100) -> 5.9840301 | M40: ='IEPR Gas Prices Real'!M40*(INDEX('GDP Deflator'!$C$5:$C$89,MATCH('IEPR Gas Prices Nominal'!$B40,'GDP Deflator'!$B$5:$B$89,0))/100) -> 0.75416863 | N40: ='IEPR Gas Prices Real'!N40*(INDEX('GDP Deflator'!$C$5:$C$89,MATCH('IEPR Gas Prices Nominal'!$B40,'GDP Deflator'!$B$5:$B$89,0))/100) -> 6.7381987 | P40: =AVERAGE(F40,I40,L40) -> 5.7544026 | Q40: =AVERAGE(H40,K40,N40) -> 6.8604851
B41: =YEAR(D41) -> 2024 | C41: =MONTH(D41) -> 12 | D41: 45627 | E41: =C41&"-"&B41 -> 12-2024 | F41: ='IEPR Gas Prices Real'!F41*(INDEX('GDP Deflator'!$C$5:$C$89,MATCH('IEPR Gas Prices Nominal'!$B41,'GDP Deflator'!$B$5:$B$89,0))/100) -> 5.5463309 | G41: ='IEPR Gas Prices Real'!G41*(INDEX('GDP Deflator'!$C$5:$C$89,MATCH('IEPR Gas Prices Nominal'!$B41,'GDP Deflator'!$B$5:$B$89,0))/100) -> 0.96712376 | H41: ='IEPR Gas Prices Real'!H41*(INDEX('GDP Deflator'!$C$5:$C$89,MATCH('IEPR Gas Prices Nominal'!$B41,'GDP Deflator'!$B$5:$B$89,0))/100) -> 6.5134546 | I41: ='IEPR Gas Prices Real'!I41*(INDEX('GDP Deflator'!$C$5:$C$89,MATCH('IEPR Gas Prices Nominal'!$B41,'GDP Deflator'!$B$5:$B$89,0))/100) -> 5.8269862 | J41: ='IEPR Gas Prices Real'!J41*(INDEX('GDP Deflator'!$C$5:$C$89,MATCH('IEPR Gas Prices Nominal'!$B41,'GDP Deflator'!$B$5:$B$89,0))/100) -> 1.5969552 | K41: ='IEPR Gas Prices Real'!K41*(INDEX('GDP Deflator'!$C$5:$C$89,MATCH('IEPR Gas Prices Nominal'!$B41,'GDP Deflator'!$B$5:$B$89,0))/100) -> 7.4239414 | L41: ='IEPR Gas Prices Real'!L41*(INDEX('GDP Deflator'!$C$5:$C$89,MATCH('IEPR Gas Prices Nominal'!$B41,'GDP Deflator'!$B$5:$B$89,0))/100) -> 6.0335223 | M41: ='IEPR Gas Prices Real'!M41*(INDEX('GDP Deflator'!$C$5:$C$89,MATCH('IEPR Gas Prices Nominal'!$B41,'GDP Deflator'!$B$5:$B$89,0))/100) -> 0.75416863 | N41: ='IEPR Gas Prices Real'!N41*(INDEX('GDP Deflator'!$C$5:$C$89,MATCH('IEPR Gas Prices Nominal'!$B41,'GDP Deflator'!$B$5:$B$89,0))/100) -> 6.7876909 | P41: =AVERAGE(F41,I41,L41) -> 5.8022798 | Q41: =AVERAGE(H41,K41,N41) -> 6.9083623
B42: =YEAR(D42) -> 2025 | C42: =MONTH(D42) -> 1 | D42: 45658 | E42: =C42&"-"&B42 -> 1-2025 | F42: ='IEPR Gas Prices Real'!F42*(INDEX('GDP Deflator'!$C$5:$C$89,MATCH('IEPR Gas Prices Nominal'!$B42,'GDP Deflator'!$B$5:$B$89,0))/100) -> 5.6765433 | G42: ='IEPR Gas Prices Real'!G42*(INDEX('GDP Deflator'!$C$5:$C$89,MATCH('IEPR Gas Prices Nominal'!$B42,'GDP Deflator'!$B$5:$B$89,0))/100) -> 1.0293312 | H42: ='IEPR Gas Prices Real'!H42*(INDEX('GDP Deflator'!$C$5:$C$89,MATCH('IEPR Gas Prices Nominal'!$B42,'GDP Deflator'!$B$5:$B$89,0))/100) -> 6.7058746 | I42: ='IEPR Gas Prices Real'!I42*(INDEX('GDP Deflator'!$C$5:$C$89,MATCH('IEPR Gas Prices Nominal'!$B42,'GDP Deflator'!$B$5:$B$89,0))/100) -> 5.9637725 | J42: ='IEPR Gas Prices Real'!J42*(INDEX('GDP Deflator'!$C$5:$C$89,MATCH('IEPR Gas Prices Nominal'!$B42,'GDP Deflator'!$B$5:$B$89,0))/100) -> 1.6996748 | K42: ='IEPR Gas Prices Real'!K42*(INDEX('GDP Deflator'!$C$5:$C$89,MATCH('IEPR Gas Prices Nominal'!$B42,'GDP Deflator'!$B$5:$B$89,0))/100) -> 7.6634473 | L42: ='IEPR Gas Prices Real'!L42*(INDEX('GDP Deflator'!$C$5:$C$89,MATCH('IEPR Gas Prices Nominal'!$B42,'GDP Deflator'!$B$5:$B$89,0))/100) -> 6.175215 | M42: ='IEPR Gas Prices Real'!M42*(INDEX('GDP Deflator'!$C$5:$C$89,MATCH('IEPR Gas Prices Nominal'!$B42,'GDP Deflator'!$B$5:$B$89,0))/100) -> 0.80267838 | N42: ='IEPR Gas Prices Real'!N42*(INDEX('GDP Deflator'!$C$5:$C$89,MATCH('IEPR Gas Prices Nominal'!$B42,'GDP Deflator'!$B$5:$B$89,0))/100) -> 6.9778934 | P42: =AVERAGE(F42,I42,L42) -> 5.9385103 | Q42: =AVERAGE(H42,K42,N42) -> 7.1157384
B43: =YEAR(D43) -> 2025 | C43: =MONTH(D43) -> 2 | D43: 45689 | E43: =C43&"-"&B43 -> 2-2025 | F43: ='IEPR Gas Prices Real'!F43*(INDEX('GDP Deflator'!$C$5:$C$89,MATCH('IEPR Gas Prices Nominal'!$B43,'GDP Deflator'!$B$5:$B$89,0))/100) -> 5.5522517 | G43: ='IEPR Gas Prices Real'!G43*(INDEX('GDP Deflator'!$C$5:$C$89,MATCH('IEPR Gas Prices Nominal'!$B43,'GDP Deflator'!$B$5:$B$89,0))/100) -> 1.0293312 | H43: ='IEPR Gas Prices Real'!H43*(INDEX('GDP Deflator'!$C$5:$C$89,MATCH('IEPR Gas Prices Nominal'!$B43,'GDP Deflator'!$B$5:$B$89,0))/100) -> 6.5815829 | I43: ='IEPR Gas Prices Real'!I43*(INDEX('GDP Deflator'!$C$5:$C$89,MATCH('IEPR Gas Prices Nominal'!$B43,'GDP Deflator'!$B$5:$B$89,0))/100) -> 5.833177 | J43: ='IEPR Gas Prices Real'!J43*(INDEX('GDP Deflator'!$C$5:$C$89,MATCH('IEPR Gas Prices Nominal'!$B43,'GDP Deflator'!$B$5:$B$89,0))/100) -> 1.6996748 | K43: ='IEPR Gas Prices Real'!K43*(INDEX('GDP Deflator'!$C$5:$C$89,MATCH('IEPR Gas Prices Nominal'!$B43,'GDP Deflator'!$B$5:$B$89,0))/100) -> 7.5328518 | L43: ='IEPR Gas Prices Real'!L43*(INDEX('GDP Deflator'!$C$5:$C$89,MATCH('IEPR Gas Prices Nominal'!$B43,'GDP Deflator'!$B$5:$B$89,0))/100) -> 6.040046 | M43: ='IEPR Gas Prices Real'!M43*(INDEX('GDP Deflator'!$C$5:$C$89,MATCH('IEPR Gas Prices Nominal'!$B43,'GDP Deflator'!$B$5:$B$89,0))/100) -> 0.80267838 | N43: ='IEPR Gas Prices Real'!N43*(INDEX('GDP Deflator'!$C$5:$C$89,MATCH('IEPR Gas Prices Nominal'!$B43,'GDP Deflator'!$B$5:$B$89,0))/100) -> 6.8427244 | P43: =AVERAGE(F43,I43,L43) -> 5.8084916 | Q43: =AVERAGE(H43,K43,N43) -> 6.9857197
B44: =YEAR(D44) -> 2025 | C44: =MONTH(D44) -> 3 | D44: 45717 | E44: =C44&"-"&B44 -> 3-2025 | F44: ='IEPR Gas Prices Real'!F44*(INDEX('GDP Deflator'!$C$5:$C$89,MATCH('IEPR Gas Prices Nominal'!$B44,'GDP Deflator'!$B$5:$B$89,0))/100) -> 5.0971347 | G44: ='IEPR Gas Prices Real'!G44*(INDEX('GDP Deflator'!$C$5:$C$89,MATCH('IEPR Gas Prices Nominal'!$B44,'GDP Deflator'!$B$5:$B$89,0))/100) -> 1.0293312 | H44: ='IEPR Gas Prices Real'!H44*(INDEX('GDP Deflator'!$C$5:$C$89,MATCH('IEPR Gas Prices Nominal'!$B44,'GDP Deflator'!$B$5:$B$89,0))/100) -> 6.1264659 | I44: ='IEPR Gas Prices Real'!I44*(INDEX('GDP Deflator'!$C$5:$C$89,MATCH('IEPR Gas Prices Nominal'!$B44,'GDP Deflator'!$B$5:$B$89,0))/100) -> 5.355019 | J44: ='IEPR Gas Prices Real'!J44*(INDEX('GDP Deflator'!$C$5:$C$89,MATCH('IEPR Gas Prices Nominal'!$B44,'GDP Deflator'!$B$5:$B$89,0))/100) -> 1.6996748 | K44: ='IEPR Gas Prices Real'!K44*(INDEX('GDP Deflator'!$C$5:$C$89,MATCH('IEPR Gas Prices Nominal'!$B44,'GDP Deflator'!$B$5:$B$89,0))/100) -> 7.0546938 | L44: ='IEPR Gas Prices Real'!L44*(INDEX('GDP Deflator'!$C$5:$C$89,MATCH('IEPR Gas Prices Nominal'!$B44,'GDP Deflator'!$B$5:$B$89,0))/100) -> 5.5449826 | M44: ='IEPR Gas Prices Real'!M44*(INDEX('GDP Deflator'!$C$5:$C$89,MATCH('IEPR Gas Prices Nominal'!$B44,'GDP Deflator'!$B$5:$B$89,0))/100) -> 0.80267838 | N44: ='IEPR Gas Prices Real'!N44*(INDEX('GDP Deflator'!$C$5:$C$89,MATCH('IEPR Gas Prices Nominal'!$B44,'GDP Deflator'!$B$5:$B$89,0))/100) -> 6.347661 | P44: =AVERAGE(F44,I44,L44) -> 5.3323788 | Q44: =AVERAGE(H44,K44,N44) -> 6.5096069
